Workbook

Sheet 2024
A2: EUTHANASIAS 2024
A3: FECHA | B3: ESTABLO | C3: CABALLO | D3: MICROCHIP | E3: RAZON
A4: 2-ENERO-2024 | B4: GARCIA | C4: LA PATRONA G | D4: 981020033087979
A5: 3-ENERO-2024 | B5: AQUINO | C5: PROSPECT PROJECT | D5: 981020021527287 | E5: END STAGE ARTHRITIS RF FETLOCK
A6: 4-ENERO-2024 | B6: GCA | C6: CONVINCENTE | D6: 981020031383586 | E6: FRACTURA RODILLA IZQUIERDA
A7: 5-ENERO-2024 | B7: LANCARA | C7: BEEMERS BOY | D7: 981020037573957 | E7: CONDYLAR FRACTURE
A8: 5-ENERO-2024 | B8: FANTASTIC 4 | C8: MENTIROSO | D8: 981020025169692 | E8: SEVERE DJD BOTH ANKLES / SEVERE LIGAMENT INJURY WITH BROKEN SPLINT BONES
A9: 5-ENERO-2024 | B9: MARQUEZ | C9: PEQUENO ADRIAN | D9: 985170002956976 | E9: FRACTURA DE LA CANA IZQUIERDA DELANTERA
A10: 7-ENERO-2024 | B10: SANCHEZ | C10: EVERY DAY CAPI | D10: 981020019171896
A11: 8-ENERO-2024 | B11: MAJESTUOSO (1,000) | C11: VALECAT | D11: 981020021436120
A12: 11-ENERO-2024 | B12: DC | C12: GREY HEART | D12: 981020037656742 | E12: COMMINUTED SLAB FRACTURE OF RIGHT CIII
A13: 12-ENERO-2024 | B13: ERV | C13: MILAGRITO | D13: 981020037383964 | E13: SEPTIC JOINT RIGHT INTERCARPAL
A14: 12-ENERO-2024 | B14: TORRES PAGAN | C14: CONCEPTUS | D14: 981020033552035 | E14: LAMINITIS
A15: 12-ENERO-2024 | B15: WILLIAM ALVEIRO | C15: BANDIDO | D15: NO TIENE | E15: COLICO
A16: 13-ENERO-2024 | B16: LEGACY | C16: KUMANDRA | D16: 981020031375259 | E16: TENDONITIS SEVERA IZQUIERDA DELANTERA
A17: 13-ENERO-2024 | B17: VILLA REAL | C17: ORGULLOSO | D17: 981020033580400 | E17: FRACTURA AMBAS RODILLAS
A18: 14-ENERO-2024 | B18: ERA RACING | C18: MRS KITCHEN | D18: 981020049676107 | E18: FRACTURA HOMBRO IZQUIERDO
A19: 15-ENERO-2024 | B19: THREE KINGS | C19: ST. ANDRES | D19: 981020035160579
A20: 16-ENERO-2024 | B20: L & D THOROUGHBRED | C20: JAZHARA | D20: 981020035720582 | E20: FRACTURA RODILLA DERECHA
A21: 16-ENERO-2024 | B21: LEGACY | C21: DIXIE CANDY | D21: 981020023518625 | E21: FETLOCK BREAKDOWN INJURY BOTH HIND LEGS.
A22: 19-ENERO-2024 | B22: EL DURAKO | C22: EL BUFFALO | D22: 981020035728387 | E22: Fractura rodilla derecha
A23: 19-ENERO-2024 | B23: KEANCA | C23: MY MAGICAL MAN | D23: 985141001301755 | E23: Artritis severa menudillo izquierdo delantero
A24: 20-ENERO-2024 | B24: ALEXIS CARTAGENA | C24: NEPTUNO | D24: N/A (PRIVADO) | E24: Colico
A25: 22-ENERO-2024 | B25: SML | C25: MY WAY OR ELSE | D25: 981020025188398 | E25: Artritis septica (menudillo derecho delantero)
A26: 22-ENERO-2024 | B26: SJ FARM | C26: NOICATTIRO | D26: 981020031326852 | E26: Right front ankle fracture sesamoid. Laminitis of both hands can't walk or train.
A27: 22-ENERO-2024 | B27: SACO E SAL | C27: REGINA ISABEL | D27: 981020033095231 | E27: Fractura rodilla derecha
A28: 26-ENERO-2024 | B28: BROTHERS | C28: PRESENTADOR | D28: 981020027766947 | E28: Laminitis cronica.
A29: 31-ENERO-2024 | B29: JF | C29: MISTER PILOT | D29: 981020033142559 | E29: Fractura Húmero
A30: 2-FEBRERO-2024 | B30: N Y N | C30: UNIFIED CONQUEST | D30: 981020031364199 | E30: HERIDA PARTE POSTERIOR DEL MENUDILLO, CUARTILLA IZQUIERDA DELANTERA INCLUYENDO LA VAINA DEL TENDON
A31: 5-FEBRERO-2024 | B31: ANGEL CALDERON | C31: CYBERICA | D31: 981020023488884 | E31: ARTRITIS SEVERA EN MENUDILLO DELANTERO.
A32: 7-FEBRERO-2024 | B32: ROCHE KALIL | C32: ERNESTO M | D32: 0A01787568 | E32: COLICO & POOR BODY CONDITION.
A33: 7-FEBRERO-2024 | B33: YORAM | C33: MINERA | D33: 981020033612721 | E33: ARTRITIS SEVERA DERECHO DELANTERO
A34: 8-FEBRERO-2024 | B34: CARMEN ANITA | C34: INDIAN SENSE | D34: 981020023252791 | E34: ARTRITIS SEVERA
A35: 9-FEBRERO-2024 | B35: LIDIEL | C35: EL MONITOR | D35: 981020023271767 | E35: Artritis severa menudillo izquierdo delantero
A36: 12-FEBRERO-2024 | B36: V.G.O | C36: IAN P.R. | D36: 981020039665310 | E36: FRACTURA AMBAS RODILLAS
A37: 13-FEBRERO-2024 | B37: CENTRAL | C37: EL TIO BOLO | D37: 981020045089585 | E37: ARTRITIS SEVERA RODILLA IZQUIERDA
A38: 13-FEBRERO-2024 | B38: DIVINO NINO | C38: EL MAPA | D38: 981020033105565 | E38: TENDON BREAKDOWN RF LEG
A39: 13-FEBRERO-2024 | B39: DESAFIO | C39: SPEEDY D | D39: 981020037644126 | E39: FRACTURA SESAMOIDE PATA DERECHA DELANTERA
A40: 13-FEBRERO-2024 | B40: ALAMO | C40: CLEMENTE BORICUA | D40: 981020031381064 | E40: FRACTURA AMBAS RODILLAS
A41: 14-FEBRERO-2024 | B41: SILENT | C41: RECOMPENSADO | D41: 981020033097903 | E41: Artritis severa rodilla derecha
A42: 16-FEBRERO-2024 | B42: DC | C42: EL DICTADOR | D42: 981020033755530 | E42: Fractura sesamoide derecho delantero
A43: 16-FEBRERO-2024 | B43: RAFANIL | C43: I'M YOUR LUV | D43: 981020037817398 | E43: Aggressive eye cancer
A44: 19-FEBRERO-2024 | B44: STUD JUNIOR V | C44: DRA. ANA CAROLINA | D44: 981020037782540 | E44: Tendón desgarrado pata izquierda trasera/ Laminitis pata derecha trasera
... A70: 2-ABRIL-2024 | B70: J.A.C. | C70: NIGHT PRINCESS 2022 | D70: 981020049700096 | E70: Cólico severo (referido por Dr. Armand PRHOA)
A71: 2-ABRIL-2024 | B71: EL HERRERO | C71: OUTFORARIDE | D71: 7E0127568 | E71: Fractura y artritis de rodilla izquierda
A72: 2-ABRIL-2024 | B72: RM | C72: EL BRAVO | D72: 981020035717994 | E72: Fractura rodilla derecha
A73: 2-ABRIL-2024 | B73: GARCIA | C73: INCLUDE ME | D73: 981020039152243 | E73: Cólico (Nephrosplenic entrapment/Referido Dr. Armand PRHOA)
A74: 5-ABRIL-2024 | B74: VAGABUNDO | C74: ALEGRIA ALEGRIA | D74: 981020033079238 | E74: Múltiples fracturas rodillas + menudillos delanteros
A75: 6-ABRIL-2024 | B75: NE | C75: CHOCO FACTOR | D75: 981020037642845 | E75: RF Breakdown Injury. (PRHOA)
A76: 15-ABRIL-2024 | B76: RAMZ | C76: EMPRENDEDOR | D76: 981020033592892 | E76: Fractura rodilla derecha
A77: 19-ABRIL-2024 | B77: MATEO IGNACIO | C77: MR. ZACH | D77: 981020033085383 | E77: Fractura caña izquierda delantera
A78: 20-ABRIL-2024 | B78: JOSE LUIS | C78: SR. EMMANUELLI | D78: 981020023276031 | E78: Chronic tendinitis (both front limbs)
A79: 23-ABRIL-2024 | B79: CRUZ FAMILY | C79: POKER COCO | D79: 981020033154143 | E79: Chronic flexor tendinitis L front/R Carpal Fracture
A80: 26-ABRIL-2024 | B80: R RACING | C80: ORO NEGRO | D80: 981020037646963 | E80: Fractura sesamoide izquierdo delantero y rodilla derecha
A81: 27-ABRIL-2024 | B81: JBK | C81: HARLAN'S WAR | D81: 981020033579091 | E81: Fractura sesamoide ambas patas delanteras durante la 3ra carrera. PRHOA.
A82: 29-ABRIL-2024 | B82: CUTTY | C82: BIG RINNIE | D82: 981020019327855 | E82: Fractura rodilla derecha
A83: 1-MAYO-2024 | B83: SONATA | C83: ARGUMENTO | D83: 981020031368873 | E83: Pleuroneumonía. Referido Drs PRHOA.
... A131: 25-JUNIO-2024 | B131: MATEO IGNACIO | C131: HIAWAFFEE ROAD | D131: 981020019167414 | E131: Fractura menudillo izquierdo delantero (sesamoide medial)
A132: 26-JUNIO-2024 | B132: HUMACAO | C132: NIGHT CITY | D132: 9810200320155039/ 981020019164727 | E132: Fractura sesamoide lateral pata derecha delantera
A133: 29-JUNIO-2024 | B133: BULLS FARM | C133: SILVER WEDDING 2022 | D133: 981020043530118 | E133: Accidente en la pista. Fractura húmero. (Dr. García Blanco)
A134: 3-JULIO-2024 | B134: CENTRAL | C134: BROOKS N BAND | D134: 981020033620570 | E134: Artritis ambos menudillos. Fractura rodilla izquierda.
A135: 3-JULIO-2024 | B135: POTRERO HERMOSURA | C135: LADY ANN 2023 | D135: 981020051008914 | E135: Fractura mandibular severa
A136: 4-JULIO-2024 | B136: GARCIA BLANCO (JBK) | C136: JLO CAN DANCE | D136: 981020027312372 | E136: Severe DJD without joint space. Referido PRHOA.
A137: 5-JULIO-2024 | B137: TORRES PAGAN | C137: CORPULENTA | D137: 981020037651754 | E137: Fractura rodilla derecha.
A138: 6-JULIO-2024 | B138: CARLOS DAMIAN | C138: SARA Y | D138: 981020031346704 | E138: LF breakdown injury. Referido PRHOA.
A139: 7-JULIO-2024 | B139: HNOS APONTE | C139: ESTRELLITA | D139: 981020023241072 | E139: Fractura hombro derecho. 6ta carrera. Referido PRHOA.
A140: 8-JULIO-2024 | B140: R RACING | C140: DULCES LABIOS | D140: 981020033595543 | E140: Fractura rodilla izquierda.
A141: 8-JULIO-2024 | B141: CUTTY | C141: EL PAQUI | D141: 981020023652398 | E141: Fractura rodilla izquierda + Artritis (Referido Dr. Bozzo)
A142: 9-JULIO-2024 | B142: EDDY WILLY | C142: TEMPLE STORM | D142: 981020031356081 | E142: Both ankles severe DJD and decrease joint space. (Referido PRHOA.)
A143: 10-JULIO-2024 | B143: LA VICTORIA | C143: EXPRESS TO LA | D143: 981020045148224 | E143: Sever colic. (Referido PRHOA.)
A144: 10-JULIO-2024 | B144: NINIMEL | C144: EVA LUNA | D144: 900182001156556 | E144: Radiocarpal joint sepsis. LF peritendinous abscess.
... A195: 17-SEPTIEMBRE-2024 | B195: MADECO (#1,000) | C195: SWEET SEVENTY NINE | D195: 981020037323484 | E195: R Knee multiple fragments with severe DJD. (Referido PRHOA)
A196: 17-SEPTIEMBRE-2024 | B196: SANCHEZ | C196: CABALLO DE TROYA | D196: 473F42725C | E196: Artritis severa ambas rodillas. (Referido Dr. Loinaz)
A197: 17-SEPTIEMBRE-2024 | B197: V.G.O | C197: AGUASBONENSE | D197: 981020035173053 | E197: Múltiples fracturas rodillas izquierda.
A198: 18-SEPTIEMBRE-2024 | B198: SONATA | C198: CHARGE ACCOUNT | D198: 981020021462781 | E198: Cólico (thromboembolic cecum)
A199: 19-SEPTIEMBRE-2024 | B199: HCDA BASILISA | C199: FIRST CADETE | D199: 981020023586014 | E199: Laminitis
A200: 19-SEPTIEMBRE-2024 | B200: CANITO | C200: FROSTED ARCH | D200: 981020033084361 | E200: Post-race 6:42pm
A201: 20-SEPTIEMBRE-2024 | B201: SHARK | C201: MOSS BOSS | D201: 981020023684540 | E201: Artritis/Sinovitis severa
A202: 23-SEPTIEMBRE-2024 | B202: MOISES | C202: ALFARERO | D202: 981020033601973 | E202: Front ligament desmitis
A203: 23-SEPTIEMBRE-2024 | B203: FLORIDA | C203: FAVISUS REAL | D203: 981020037317644 | E203: C-3 Slab fracture L Knee
A204: 27-SEPTIEMBRE-2024 | B204: LA 010 | C204: VINCENZA M | D204: 981020033732667 | E204: LF Knee C-3 fracture with multiple big fragments both joints. Can't train. (Referido PRHOA)
A205: 27-SEPTIEMBRE-2024 | B205: STAR & STRIPES | C205: CYRANO DE B | D205: 981020045119030 | E205: RF Knee breakdown injury. (Guardia PRHOA)
A206: 30-SEPTIEMBRE-2024 | B206: AQUINO | C206: DIXIE DRAWL | D206: 981020019489831 | E206: Breakdown injury LF fetlock
A207: 1-OCTUBRE-2024 | B207: BULLS FARM | C207: FIRST BABY | D207: 981020037352330 | E207: Septic Joint R Knee
A208: 2-OCTUBRE-2024 | B208: LA 31 | C208: HERALDO | D208: 981020019354353 | E208: Fractura rodilla derecha. Fractura caña derecha delantera. DJD ambos menudillos delanteros. Tendinitis pata derecha delantera.
... A212: 8-OCTUBRE-2024 | B212: K.A.P. | C212: PAPO VIETNAM | D212: 981020037575310 | E212: Fractura apical ambos sesamoides menudillo derecho y caña derecha
A213: 10-OCTUBRE-2024 | B213: GUILLERMO BERRIOS | C213: SPIRIT OF WARRIOR | D213: 985141005077812/ 981020043045789 | E213: C-3 Slab fracture L Knee (Referido PRHOA)
A214: 21-OCTUBRE-2024 | B214: AM | C214: DIVING NINA | D214: 7E01027563 | E214: Fractura catastrófica caña derecha delantera.
A215: 22-OCTUBRE-2024 | B215: CARLOS OYOLA | C215: DAWN MOON | D215: 981020041789646 | E215: Severe arthritis of left carpal and middle carpal joints. (Referido PRHOA)
A216: 23-OCTUBRE-2024 | B216: SKULL | C216: MORNING DESTINY | D216: 981020037786701 | E216: Laminitis severa en ambos cascos delanteros. Rotación y hundimiento. (Referido Dr. Bozzo)
A217: 25-OCTUBRE-2024 | B217: TARRATS NACC | C217: PROBADOR | D217: 981020037816860 | E217: L C-3 Slab fracture
A218: 28-OCTUBRE-2024 | B218: ANALIJAN | C218: CHIQUITINA ROJAS | D218: 981020019156880 | E218: R MC3 Fx.
A219: 4-NOVIEMBRE-2024 | B219: IBE & JOE | C219: BACONAO | D219: 981020021540884 | E219: RF Fetlock sesamoid fracture + RF Suspensory desmitis and tendinitis.
A220: 4-NOVIEMBRE-2024 | B220: GUTIERREZ | C220: POWER OF NATURE | D220: 981020035164928 | E220: Bilateral front limbs tendinitis/desmitis with excessive dorsiflexion of fetlock joints.
A221: 4-NOVIEMBRE-2024 | B221: BROTHERS | C221: CHICA BELLA | D221: 981020035774749 | E221: LF fetlock severe arthritis.
A222: 5-NOVIEMBRE-2024 | B222: BORIKEN | C222: GUANIN DE ORO | D222: 981020037794237 | E222: Fracturas y artritis severa de rodilla derecha.
A223: 9-NOVIEMBRE-2024 | B223: DESAFIO | C223: DOUBLE ERICK | D223: 981020037352313 | E223: RF Knee fx during race. (Guardia PRHOA)
A224: 10-NOVIEMBRE-2024 | B224: SONATA | C224: HOP KAT | D224: 985141001086610 | E224: LF Ankle breakdown injury during race. (Guardia PRHOA)
A225: 11-NOVIEMBRE-2024 | B225: A REYES | C225: CHEROKEE | D225: 981020037328569 | E225: Laminitis crónica casco derecho delantero/Subepiglottic fold granuloma.
A226: 11-NOVIEMBRE-2024 | B226: BEKY | C226: R CHA CHA | D226: 985111001763426 | E226: Artritis menudillo derecho delantero/Fx sesamoide RF ankle
...

Sheet 2025
A1: EUTHANASIAS 2025
A2: FECHA | B2: ESTABLO | C2: CABALLO | D2: MICROCHIP | E2: RAZON
A3: 9-ENERO-2025 | B3: 47 ROSES OF P.R. | C3: PERICIA | D3: 981020031381027 | E3: Multiples fracturas rodilla derecha
A4: 14-ENERO-2025 | B4: DMA | C4: MATTER OF TRUST | D4: 981020037363425 | E4: LF MC III lateral condylar fracture
A5: 21-ENERO-2025 | B5: JAC | C5: VENEZUELA FIRST | D5: 981020033086157 | E5: Artritis severa menudillo izquierdo delantero
A6: 24-ENERO-2025 | B6: TORRES PAGAN | C6: AFIRMADO | D6: 981020045134542 | E6: L Dorsal MC III cortical fracture
A7: 26-ENERO-2025 | B7: LOS LEE | C7: POSEIDON | D7: 981020045154834 | E7: Rodilla derecha- Slab FX
A8: 27-ENERO-2025 | B8: CINCO HERMANOS | C8: FIESTA BRAVA | D8: 981020039627868 | E8: Fractura en ambas rodillas
A9: 28-ENERO-2025 | B9: SILOE | C9: COBRADOR | D9: 990000004659991 | E9: Fractura/artritis rodilla izquierda
A10: 31-ENERO-2025 | B10: LA 010 | C10: CARICIA DEL CIELO | D10: 981020037655891 | E10: Colic last night + Severe DJD Knee + LF ankle fracture (sesamoids). (Referido PRHOA)
A11: 4-FEBRERO-2025 | B11: ANTONIO E ISABEL | C11: MUNAY | D11: 981020045096215 | E11: R Knee distal radius big fracture, proximal intermediate fx. (Referido PRHOA)
A12: 4-FEBRERO-2025 | B12: DU-RA-KO | C12: MAURICIO | D12: 981020039318212 | E12: Fractura rodilla izquierda.
A13: 10-FEBRERO-2025 | B13: ADORNO | C13: AMAIA MY LOVE | D13: 981020035165913 | E13: Artritis en ambos menudillos delanteros.
A14: 11-FEBRERO-2025 | B14: M SANTIAGO | C14: ARABIAN HEART | D14: 981020045133028 | E14: Diagnóstico previo de problemas neurológicos. Hoy recumbente incapaz de pararse.
... A37: 10-MARZO-2025 | B37: RM | C37: SMALL GUN | D37: 981020037356076 | E37: Chronic tendinitis on both front limbs
A38: 12-MARZO-2025 | B38: CTA | C38: CRUISES CREEK | D38: 0A02461076 | E38: Cólico. Colon desplazado.
A39: 14-MARZO-2025 | B39: R RACING | C39: DON ICO T | D39: 981020033766894 | E39: Bilateral pleuropneumonia.
A40: 15-MARZO-2025 | B40: GCA | C40: K MENA | D40: 981020023226058 | E40: Fracture LF P-1
A41: 17-MARZO-2025 | B41: HISTORY | C41: DYLAN THE GREAT | D41: 981020033772308 | E41: R Carpal severe OA secundary to chronic chip fractures. (Referido PRHOA)
A42: 18-MARZO-2025 | B42: GUILLERMO BERRIOS | C42: AMAZING TRIP | D42: 981020031332003 | E42: RF ankle severe DJD with no joint space. Splint bones fractures with collateral fragments. (Referido PRHOA)
A43: 22-MARZO-2025 | B43: RAFANIL | C43: CENTAURO | D43: 981020031358339 | E43: Laminitis LF hoof
A44: 28-MARZO-2025 | B44: NUEVA GENERACIÓN | C44: ANUALIZADA | D44: 981020031385780 | E44: C-3 Slab fracture (Referido PRHOA)
A45: 7-ABRIL-2025 | B45: JR | C45: DIME RUBÉN M | D45: 981020045155381 | E45: Múltiples fracturas en ambas rodillas.
A46: 8-ABRIL-2025 | B46: L&D THOROUGHBRED | C46: DAMA DE HIERRO | D46: 981020051143307 | E46: Fractura hombro derecho. (Se fue a la pista)
A47: 8-ABRIL-2025 | B47: R RACING | C47: PATRIÓTICA | D47: 981020037355507 | E47: Artritis crónica ambos menudillos delanteros. Fractura sagital L C-3. Artritis séptica L RC.
A48: 8-ABRIL-2025 | B48: ORIÓN | C48: EL INTRÉPIDO | D48: 981020045124783 | E48: Fractura rodilla izquierda (C-3 Slab).
A49: 22-ABRIL-2025 | B49: CHAD | C49: MI BOTICARIA | D49: 981020037339477 | E49: Near complete tear in medial pastern bundle of the DDFT. (Referido PRHOA)
A50: 25-ABRIL-2025 | B50: PRECISE STAR | C50: JESS'S STRIDE | D50: 981020025195230 | E50: Cólico.
... A64: 26-MAYO-2025 | B64: R RACING | C64: LOLITO | D64: 981020037350886 | E64: L C3 Slab fracture.
A65: 26-MAYO-2025 | B65: HACIENDA EL SUEÑO | C65: CHIQUILIN | D65: N/A | E65: Tétano.
A66: 29-MAYO-2025 | B66: JI DIAMOND | C66: MAMI OLGA | D66: 981020031358368 | E66: Bilateral front limbs suspensory desmitis in subluxation of pastern joints.
A67: 29-MAYO-2025 | B67: CARMEN ANITA | C67: CRIOLLITO | D67: 981020023533123 | E67: Cólico (enteritis).
A68: 30-MAYO-2025 | B68: DMA | C68: JUST CROWN | D68: 981020031349176 | E68: Artritis menudillo izquierdo delantero.
A69: 30-MAYO-2025 | B69: LA 010 | C69: SIMÉTRICO | D69: 981020037640759 | E69: Referido PRHOA
A70: 30-MAYO-2025 | B70: INVICTUS | C70: TIZ THE SKY | D70: 981020033568849 | E70: Mid-body fracture of medial sesamoid + apical fracture of lateral sesamoid.
A71: 1-JUNIO-2025 | B71: GRAN POLLO | C71: GRAN LEXY | D71: 981020037297457 | E71: Fractura sesamoide derecho delantero.
A72: 7-JUNIO-2025 | B72: DENIAN | C72: AMERICAN SUNSHINE | D72: 981020037320306 | E72: Tendinitis cronica pata derecha delantera.
A73: 8-JUNIO-2025 | B73: JCM | C73: HOLY SECRET | D73: 981020023691827 | E73: RH Condylar Fracture. (Guardia PRHOA. No se utilizó Beuthanasia).
A74: 9-JUNIO-2025 | B74: R RACING | C74: TOMA PUERTORRO | D74: 981020031379310 | E74: Múltiples fracturas en ambas rodillas.
A75: 10-JUNIO-2025 | B75: AYALA | C75: AYALAS | D75: 981020037322464 | E75: Fractura rodilla izquierda.
A76: 13-JUNIO-2025 | B76: G.C.A. | C76: LA CHICA LATERAL | D76: 981020027297777 | E76: Artritis severa en la rodilla izquierda (Intercarpal Joint).
A77: 14-JUNIO-2025 | B77: CLINTON | C77: PRICE TARGET 2023 | D77: 981020051154707 | E77: Fractura hombro derecho. (Se fue a la pista)
... A111: 3-AGOSTO-2025 | B111: M SANTIAGO | C111: ARABIAN MOON | D111: 981020041821530 | E111: Fractura rodilla izquierda (Guardia PRHOA)
A112: 3-AGOSTO-2025 | B112: JORMALY | C112: LA NIETA E JORGI C | D112: 981020049646207
A113: 4-AGOSTO-2025 | B113: SANTA RITA | C113: YERAI | D113: 981020037793810 | E113: Slab fracture L Knee
A114: 4-AGOSTO-2025 | B114: TARRATS NACC | C114: DIAMOND THE GOAT | D114: 981020037350442 | E114: RF base sesamoid fracture
A115: 4-AGOSTO-2025 | B115: VILLA REAL | C115: PERFECCIONISTA | D115: 981020045082634 | E115: L C3 Slab fracture.
A116: 9-AGOSTO-2025 | B116: SONATA | C116: VOLATILE DANCER | D116: 981020041787251 | E116: LF Breakdown injury.
A117: 11-AGOSTO-2025 | B117: POCOS PERO FIRMES | C117: ANFITRIONA | D117: 981020049649500 | E117: Fractura rodilla derecha.
A118: 13-AGOSTO-2025 | B118: JI DIAMOND | C118: PESCADOR DE SUEÑOS | D118: 900182001156510 | E118: Fractura rodilla derecha.
A119: 13-AGOSTO-2025 | B119: JI DIAMOND | C119: EL GALLOLFO | D119: 981020031323501 | E119: Laminitis en ambas manos/Múltiples fracturas en ambas rodillas L>R.
A120: 13-AGOSTO-2025 | B120: JI DIAMOND | C120: BLACK SILK | D120: 981020031322284 | E120: Fractura rodilla izquierda.
A121: 14-AGOSTO-2025 | B121: QUINTANA | C121: HARD TEN | D121: 981020033204080 | E121: Artritis severa menudillo derecho delantero.
A122: 18-AGOSTO-2025 | B122: RAMZ | C122: UCASTEO | D122: 981020051022595 | E122: Laminitis severa (sinker). (Referido PRHOA)
A123: 18-AGOSTO-2025 | B123: VMH | C123: EMILIA D | D123: 981020045146518 | E123: Múltiples fracturas en ambas rodillas L>R.
A124: 20-AGOSTO-2025 | B124: FLAMBOYÁN | C124: DULCE BISCUIT | D124: 981020023695438 | E124: Artritis en ambos menudillos delanteros. Historial previo de laminitis.
... A139: 25-SEPTIEMBRE-2025 | B139: SACO E SAL | C139: EL FERROCARRIL | D139: 981020033586337 | E139: Arthritis severe on both knees/Fracture L Knee (distal radius)
A140: 26-SEPTIEMBRE-2025 | B140: SACO E SAL | C140: RAFY Q | D140: AVID*835*533*594 | E140: LH chronic suspensory desmitis.
A141: 27-SEPTIEMBRE-2025 | B141: VETERANO | C141: FORTALECEDOR | D141: 981020037655891 | E141: RF Shin fracture spiral (Referido PRHOA)
A142: 27-SEPTIEMBRE-2025 | B142: SACO E SAL | C142: DAN'S LOYALTY | D142: 981020033118639 | E142: Artritis severa menudillo izquierdo delantero
A143: 27-SEPTIEMBRE-2025 | B143: RAJ | C143: TWO PRINCESSES | D143: 981020051124608 | E143: Ambas cañas fracturadas. Fracturas catastróficas de ambas cañas delanteras. Eutanizada en la pista.
A144: 28-SEPTIEMBRE-2025 | B144: THREE KINGS | C144: RIVAL ROYAL | D144: 981020037314843 | E144: Fracture and breakdown RF knee after race. (Referido PRHOA)
A145: 29-SEPTIEMBRE-2025 | B145: LIT | C145: EL RENEGADO | D145: 981020023697937 | E145: RF Suspensory desmitis/tendinitis.
A146: 1-OCTUBRE-2025 | B146: CASAN | C146: KEEP DANCING | D146: 981020023228908 | E146: ARTHRITIS SEVERA MENUDILLO IZQUIERDO DELANTERO
A147: 3-OCTUBRE-2025 | B147: SACO E SAL | C147: NICELY KLIM | D147: 981020037858741 | E147: Laminitis
A148: 6-OCTUBRE-2025 | B148: ESTRADA | C148: CAT ROAD | D148: 981020045089262 | E148: RF ankle severe DJD with fracture. (Referido PRHOA)
A149: 6-OCTUBRE-2025 | B149: SNIPER | C149: SHOW ME LOVE | D149: 981020031373166 | E149: Artritis ambos menudillos delanteros
A150: 13-OCTUBRE-2025 | B150: R & R | C150: CAUSADOR | D150: 900182001156508 | E150: Fractura C3.
A151: 13-OCTUBRE-2025 | B151: HCDA BASILISA | C151: EL GRAN MICKEY | D151: 981020023568425 | E151: Sepsis severa rodilla izquierda.
A152: 13-OCTUBRE-2025 | B152: RAMZ | C152: AND I KNOW | D152: 985141001398406 | E152: Desmitis ligamento suspensorio derecha trasera.
... A170: 11-NOVIEMBRE-2025 | B170: LA 010 | C170: MAGURO (UNAGI 2024) | D170: 981020051586531 | E170: Condición neurológica.
A171: 20-NOVIEMBRE-2025 | B171: LIT | C171: HOT PATOOTIE | D171: 981020031364500/ 981020041797429 | E171: Fractura rodilla derecha.
A172: 20-NOVIEMBRE-2025 | B172: RNT | C172: LONDON GHOST | D172: 981020033779774 | E172: Artritis en ambos menudillos delanteros.
A173: 20-NOVIEMBRE-2025 | B173: RAFANIL | C173: PRETTY PHILLY 2024 | D173: 981020051149871 | E173: Cólico y laminitis fulminante.
A174: 21-NOVIEMBRE-2025 | B174: INFINITE | C174: GIAN CARLOS R | D174: 981020049627447 | E174: Fractura hombro derecho.
A175: 22-NOVIEMBRE-2025 | B175: R.V.C. | C175: MAR TRANQUILO | D175: 981020049677158 | E175: Fractura rodilla derecha (C-3 slab).
A176: 24-NOVIEMBRE-2025 | B176: VILLA REAL | C176: ADELIN M | D176: 981020045085897 | E176: Severe DJD + fracture R radiocarpal joint.
A177: 24-NOVIEMBRE-2025 | B177: FABERY | C177: ASTACIO QUEEN | D177: 981020041803852 | E177: L front lateral apical sesamoid fracture.
A178: 26-NOVIEMBRE-2025 | B178: LIT | C178: EL COMERIEÑO | D178: 981020033600578 | E178: Fracturas sesamoides en ambos menudillos delanteros (fracturas viejas).
A179: 28-NOVIEMBRE-2025 | B179: NATCHA | C179: EL ENGREÍDO | D179: 981020049647346 | E179: Laminitis
A180: 28-NOVIEMBRE-2025 | B180: RÍO CAÑAS | C180: ANGEL'S COLLECTED | D180: 981020045108954 | E180: Cólico
A181: 1-DICIEMBRE-2025 | B181: SIACCA | C181: SMOOTH PLAYER | D181: 981020039137231 | E181: Artritis en ambos menudillos delanteros
A182: 4-DICIEMBRE-2025 | B182: ESTRADA | C182: SHARON'S HOPE | D182: 981020037558611 | E182: Trashing after lasix (8cc). (PRHOA)
A183: 5-DICIEMBRE-2025 | B183: FLAMBOYÁN | C183: FEDERAL CASE | D183: 981020021007884 | E183: Pobre condición física post-cólico.
... A199: 31-DICIEMBRE-2025 | B199: RAMZ | C199: JORGITO L | D199: 981020033596266 | E199: Chronic diarrea for 5 weeks duration. R hind limb cellulitis. (Referido PRHOA)

Sheet 2026
A1: EUTHANASIAS 2026
A2: FECHA | B2: ESTABLO | C2: CABALLO | D2: MICROCHIP | E2: RAZON
A3: 2-ENERO-2026 | B3: MA D CO | C3: C R NOMI | D3: 981020037309179 | E3: Severe carpal disease. (Referido PRHOA)
A4: 2-ENERO-2026 | B4: WILLIE | C4: JARAB DE ZAPETE | D4: 981020031389160 | E4: Fractura caña izquierda + múltiples fracturas rodilla derecha. (Referido PRHOA)
A5: 2-ENERO-2026 | B5: V.G.O. | C5: EXCLUSIVA | D5: 981020049702663 | E5: RF Suspensory Desmitis.
A6: 3-ENERO-2026 | B6: PRETTY H@RSE | C6: BLAZZING ARROW | D6: 981020045084422 | E6: RF C-3 Slab fracture. (Referido PRHOA)
A7: 5-ENERO-2026 | B7: G.R.C. | C7: YAHIR | D7: 981020037381563 | E7: LF artritis severa.

Sheet Sheet5
A1: Categoría | B1: Fractura ósea
A2: AVG Starts by year | B2: 9672 | D2: =B2/12 -> 806 | E2: =1000/12 -> 83.333333
B3: Years
B4: 2024 | C4: 2025
A5: Death Horses | B5: 0.54356846 | C5: 0.45643154
B7: 2025 | C7: 2024
A8: Death Horses | B8: 0.46 | C8: 0.54
B24: 2024 | D24: 2025
A25: Months | B25: Death Horses | C25: % Death Diff | D25: Death Horses
A26: Jan | B26: 0.083969466 | D26: 0.054545455
A27: Feb | B27: 0.053435115 | D27: 0.1
A28: Mar | B28: 0.061068702 | D28: 0.081818182
A29: Apr | B29: 0.083969466 | D29: 0.036363636
A30: May | B30: 0.13740458 | D30: 0.072727273
A31: Jun | B31: 0.076335878 | D31: 0.090909091
A32: Jul | B32: 0.15267176 | D32: 0.15454545
A33: Aug | B33: 0.06870229 | D33: 0.090909091
A34: Sep | B34: 0.083969466 | D34: 0.081818182
A35: Oct | B35: 0.045801527 | D35: 0.081818182
A36: Nov | B36: 0.045801527 | D36: 0.090909091
A37: Dec | B37: 0.10687023 | D37: 0.063636364

Sheet Sheet7
A1: Data returned for Count of CABALLO, Otras / No especificada (First 1000 rows).
A3: Range[FECHA] | B3: Range[día] | C3: Range[Mes] | D3: Range[Date] | E3: Range[ESTABLO] | F3: Range[CABALLO] | G3: Range[RAZON] | H3: Range[Categoría] | I3: Range[Tipo de fractura] | J3: Range[Fatal injury] | K3: Range[Date (Month)] | L3: Range[Date (Year)] | M3: Range[Date (Quarter)] | N3: Range[Date (Month Index)]
A4: 12-ENERO-2024 | B4: 12 | C4: ENERO | D4: 45303 | E4: ERV | F4: MILAGRITO | G4: SEPTIC JOINT RIGHT INTERCARPAL | H4: Otras / No especificada | I4: 0 | J4: Fatal injury | K4: Jan | L4: 2024 | M4: Qtr1 | N4: 1
A5: 12-ENERO-2024 | B5: 12 | C5: ENERO | D5: 45303 | E5: TORRES PAGAN | F5: CONCEPTUS | G5: LAMINITIS | H5: Otras / No especificada | I5: 0 | J5: No clasificado | K5: Jan | L5: 2024 | M5: Qtr1 | N5: 1
A6: 12-ENERO-2024 | B6: 12 | C6: ENERO | D6: 45303 | E6: WILLIAM ALVEIRO | F6: BANDIDO | G6: COLICO | H6: Otras / No especificada | I6: 0 | J6: No clasificado | K6: Jan | L6: 2024 | M6: Qtr1 | N6: 1
A7: 16-ENERO-2024 | B7: 16 | C7: ENERO | D7: 45307 | E7: LEGACY | F7: DIXIE CANDY | G7: FETLOCK BREAKDOWN INJURY BOTH HIND LEGS. | H7: Otras / No especificada | I7: 0 | J7: Fatal injury | K7: Jan | L7: 2024 | M7: Qtr1 | N7: 1
A8: 20-ENERO-2024 | B8: 20 | C8: ENERO | D8: 45311 | E8: ALEXIS CARTAGENA | F8: NEPTUNO | G8: COLICO | H8: Otras / No especificada | I8: 0 | J8: No clasificado | K8: Jan | L8: 2024 | M8: Qtr1 | N8: 1
A9: 26-ENERO-2024 | B9: 26 | C9: ENERO | D9: 45317 | E9: BROTHERS | F9: PRESENTADOR | G9: Laminitis cronica. | H9: Otras / No especificada | I9: 0 | J9: No clasificado | K9: Jan | L9: 2024 | M9: Qtr1 | N9: 1
A10: 7-FEBRERO-2024 | B10: 7 | C10: FEBRERO | D10: 45329 | E10: ROCHE KALIL | F10: ERNESTO M | G10: COLICO & POOR BODY CONDITION. | H10: Otras / No especificada | I10: 0 | J10: No clasificado | K10: Feb | L10: 2024 | M10: Qtr1 | N10: 2
A11: 16-FEBRERO-2024 | B11: 16 | C11: FEBRERO | D11: 45338 | E11: RAFANIL | F11: I'M YOUR LUV | G11: Aggressive eye cancer | H11: Otras / No especificada | I11: 0 | J11: No clasificado | K11: Feb | L11: 2024 | M11: Qtr1 | N11: 2
A12: 19-FEBRERO-2024 | B12: 19 | C12: FEBRERO | D12: 45341 | E12: STUD JUNIOR V | F12: DRA. ANA CAROLINA | G12: Tendón desgarrado pata izquierda trasera/ Laminitis pata derecha trasera | H12: Otras / No especificada | I12: 0 | J12: No clasificado | K12: Feb | L12: 2024 | M12: Qtr1 | N12: 2
A13: 23-FEBRERO-2024 | B13: 23 | C13: FEBRERO | D13: 45345 | E13: MANUEL GOMEZ | F13: ARTIFICAL INTELL | G13: Referido Drs. PRHOA. LF Front severe DID Knee and fetlock smooth rest. Cannot train. | H13: Otras / No especificada | I13: 0 | J13: Fatal injury | K13: Feb | L13: 2024 | M13: Qtr1 | N13: 2
A14: 24-FEBRERO-2024 | B14: 24 | C14: FEBRERO | D14: 45346 | E14: ARECIBO | F14: QUALITY STRIKE | G14: Cólico | H14: Otras / No especificada | I14: 0 | J14: No clasificado | K14: Feb | L14: 2024 | M14: Qtr1 | N14: 2
A15: 27-FEBRERO-2024 | B15: 27 | C15: FEBRERO | D15: 45349 | E15: FARO DE LUZ | F15: E.R.V. ENTERPISES | G15: Referido Drs. PRHOA. R Carpus. | H15: Otras / No especificada | I15: 0 | J15: No clasificado | K15: Feb | L15: 2024 | M15: Qtr1 | N15: 2
... A131: 31-DICIEMBRE-2025 | B131: 31 | C131: DICIEMBRE | D131: 46022 | E131: RAMZ | F131: JORGITO L | G131: Chronic diarrea for 5 weeks duration. R hind limb cellulitis. (Referido PRHOA) | H131: Otras / No especificada | I131: 0 | J131: No fatal injury (chronic/medical) | K131: Dec | L131: 2025 | M131: Qtr4 | N131: 12

Sheet Sheet6
A3: Row Labels | B3: Count of CABALLO
A4: Enfermedad degenerativa articular | B4: 57
A5: Fractura ósea | B5: 241
A6: Lesión de ligamentos/tendones | B6: 15
A7: Otras / No especificada
A8: Aggressive eye cancer | B8: 1
A9: Bilateral front fetlock palmar metacarpal disease. Unresolved lameness. (Referido PRHOA) | B9: 1
A10: Bilateral front limb tendinitis | B10: 1
A11: Bilateral front limbs tendinitis/desmitis with excessive dorsiflexion of fetlock joints. | B11: 1
A12: Bilateral laminitis. Fetlock severe OA. (Referido PRHOA) | B12: 1
A13: Bilateral pleuropneumonia. | B13: 1
A14: Breakdown injury both front limbs. Referido PRHOA. | B14: 1
A15: Breakdown injury LF (menudillo izquierdo delantero) | B15: 1
A16: Breakdown injury LF fetlock | B16: 1
A17: Breakdown injury LF Knee. (Guardia PRHOA-PM) | B17: 1
A18: Breakdown injury LF leg with tissue necrosy. Referido Dr. García Blanco. | B18: 1
A19: Catastrophic breakdown injury left fetlock | B19: 1
... A122: Grand Total | B122: 441

Sheet Sheet8
A1: Categoría | B1: Fractura ósea
A3: Count of CABALLO | B3: Column Labels
A4: Row Labels | B4: 2024 | C4: 2025 | D4: Grand Total
A5: Jan
A6: Caña / Cannon bone | B6: 1 | D6: 1
A7: Condylar | B7: 1 | C7: 1 | D7: 2
A8: No especificado | B8: 2 | C8: 1 | D8: 3
A9: Rodilla / Carpal | B9: 5 | C9: 3 | D9: 8
A10: Sesamoideo | B10: 1 | C10: 1 | D10: 2
A11: Slab | B11: 1 | D11: 1
A12: Jan Total | B12: 11 | C12: 6 | D12: 17
A13: Feb
A14: No especificado | C14: 7 | D14: 7
A15: Rodilla / Carpal | B15: 4 | C15: 2 | D15: 6
A16: Sesamoideo | B16: 3 | C16: 1 | D16: 4
A17: Slab | C17: 1 | D17: 1
A18: Feb Total | B18: 7 | C18: 11 | D18: 18
A19: Mar
A20: Caña / Cannon bone | B20: 3 | D20: 3
A21: No especificado | B21: 1 | C21: 3 | D21: 4
A22: Rodilla / Carpal | B22: 2 | C22: 2 | D22: 4
A23: Sesamoideo | B23: 1 | C23: 1 | D23: 2
A24: Slab | B24: 1 | C24: 2 | D24: 3
A25: Splint | C25: 1 | D25: 1
A26: Mar Total | B26: 8 | C26: 9 | D26: 17
A27: Apr
A28: Caña / Cannon bone | B28: 1 | D28: 1
A29: No especificado | B29: 1 | C29: 2 | D29: 3
A30: Rodilla / Carpal | B30: 7 | C30: 1 | D30: 8
A31: Sesamoideo | B31: 1 | D31: 1
A32: Slab | B32: 1 | C32: 1 | D32: 2
A33: Apr Total | B33: 11 | C33: 4 | D33: 15
A34: May
A35: Caña / Cannon bone | B35: 2 | C35: 1 | D35: 3
A36: No especificado | B36: 6 | C36: 2 | D36: 8
A37: Rodilla / Carpal | B37: 7 | C37: 1 | D37: 8
A38: Sesamoideo | B38: 3 | C38: 2 | D38: 5
A39: Slab | C39: 2 | D39: 2
A40: May Total | B40: 18 | C40: 8 | D40: 26
A41: Jun
A42: Condylar | C42: 1 | D42: 1
A43: No especificado | B43: 2 | C43: 2 | D43: 4
A44: Rodilla / Carpal | B44: 3 | C44: 3 | D44: 6
A45: Sesamoideo | B45: 3 | C45: 4 | D45: 7
A46: Slab | B46: 2 | D46: 2
A47: Jun Total | B47: 10 | C47: 10 | D47: 20
A48: Jul
A49: Caña / Cannon bone | C49: 1 | D49: 1
A50: Fetlock | C50: 1 | D50: 1
A51: No especificado | B51: 3 | C51: 2 | D51: 5
A52: Rodilla / Carpal | B52: 8 | C52: 5 | D52: 13
A53: Sesamoideo | B53: 7 | C53: 3 | D53: 10
A54: Slab | B54: 2 | C54: 4 | D54: 6
A55: Splint | C55: 1 | D55: 1
A56: Jul Total | B56: 20 | C56: 17 | D56: 37
A57: Aug
A58: Caña / Cannon bone | C58: 1 | D58: 1
A59: No especificado | B59: 3 | D59: 3
A60: Rodilla / Carpal | B60: 3 | C60: 6 | D60: 9
A61: Sesamoideo | B61: 2 | C61: 1 | D61: 3
A62: Slab | B62: 1 | C62: 2 | D62: 3
A63: Aug Total | B63: 9 | C63: 10 | D63: 19
A64: Sep
A65: Caña / Cannon bone | C65: 1 | D65: 1
A66: Fetlock | B66: 1 | D66: 1
A67: No especificado | B67: 2 | C67: 4 | D67: 6
A68: Rodilla / Carpal | B68: 6 | C68: 3 | D68: 9
A69: Sesamoideo | C69: 1 | D69: 1
A70: Slab | B70: 2 | D70: 2
A71: Sep Total | B71: 11 | C71: 9 | D71: 20
A72: Oct
A73: Caña / Cannon bone | B73: 3 | C73: 1 | D73: 4
A74: No especificado | C74: 2 | D74: 2
A75: Rodilla / Carpal | C75: 5 | D75: 5
A76: Slab | B76: 3 | C76: 1 | D76: 4
A77: Oct Total | B77: 6 | C77: 9 | D77: 15
A78: Nov
A79: Fetlock | B79: 1 | D79: 1
A80: No especificado | B80: 1 | C80: 3 | D80: 4
A81: Rodilla / Carpal | B81: 3 | C81: 4 | D81: 7
A82: Sesamoideo | C82: 2 | D82: 2
A83: Slab | B83: 1 | C83: 1 | D83: 2
A84: Nov Total | B84: 6 | C84: 10 | D84: 16
A85: Dec
A86: Caña / Cannon bone | B86: 2 | C86: 1 | D86: 3
A87: No especificado | B87: 5 | D87: 5
A88: Rodilla / Carpal | B88: 4 | C88: 1 | D88: 5
A89: Sesamoideo | B89: 2 | D89: 2
A90: Slab | C90: 4 | D90: 4
A91: Splint | B91: 1 | C91: 1 | D91: 2
A92: Dec Total | B92: 14 | C92: 7 | D92: 21
A93: Grand Total | B93: 131 | C93: 110 | D93: 241

Sheet Toda la data
A1: FECHA | B1: día | C1: Mes | D1: Date | E1: ESTABLO | F1: CABALLO | G1: RAZON | H1: Categoría | I1: Tipo de fractura | J1: Fatal injury
A2: 2-ENERO-2024 | B2: =LEFT(A2,FIND("-",A2)-1) -> 2 | C2: =MID(A2,FIND("-",A2)+1,FIND("-",A2,FIND("-",A2)+1)-FIND("-",A2)-1) -> ENERO | D2: 45293 | E2: GARCIA | F2: LA PATRONA G | H2: =_xlfn.XLOOKUP($G2,RazónMuerte!$A:$A,RazónMuerte!B:B,"",0) -> 0 | I2: =_xlfn.XLOOKUP($G2,RazónMuerte!$A:$A,RazónMuerte!C:C,"",0) -> 0 | J2: =_xlfn.XLOOKUP($G2,RazónMuerte!$A:$A,RazónMuerte!D:D,"",0) -> 0
A3: 3-ENERO-2024 | B3: =LEFT(A3,FIND("-",A3)-1) -> 3 | C3: =MID(A3,FIND("-",A3)+1,FIND("-",A3,FIND("-",A3)+1)-FIND("-",A3)-1) -> ENERO | D3: 45294 | E3: AQUINO | F3: PROSPECT PROJECT | G3: END STAGE ARTHRITIS RF FETLOCK | H3: =_xlfn.XLOOKUP($G3,RazónMuerte!$A:$A,RazónMuerte!B:B,"",0) -> Enfermedad degenerativa articular | I3: =_xlfn.XLOOKUP($G3,RazónMuerte!$A:$A,RazónMuerte!C:C,"",0) -> 0 | J3: =_xlfn.XLOOKUP($G3,RazónMuerte!$A:$A,RazónMuerte!D:D,"",0) -> Fatal injury
A4: 4-ENERO-2024 | B4: =LEFT(A4,FIND("-",A4)-1) -> 4 | C4: =MID(A4,FIND("-",A4)+1,FIND("-",A4,FIND("-",A4)+1)-FIND("-",A4)-1) -> ENERO | D4: 45295 | E4: GCA | F4: CONVINCENTE | G4: FRACTURA RODILLA IZQUIERDA | H4: =_xlfn.XLOOKUP($G4,RazónMuerte!$A:$A,RazónMuerte!B:B,"",0) -> Fractura ósea | I4: =_xlfn.XLOOKUP($G4,RazónMuerte!$A:$A,RazónMuerte!C:C,"",0) -> Rodilla / Carpal | J4: =_xlfn.XLOOKUP($G4,RazónMuerte!$A:$A,RazónMuerte!D:D,"",0) -> Fatal injury
A5: 5-ENERO-2024 | B5: =LEFT(A5,FIND("-",A5)-1) -> 5 | C5: =MID(A5,FIND("-",A5)+1,FIND("-",A5,FIND("-",A5)+1)-FIND("-",A5)-1) -> ENERO | D5: 45296 | E5: LANCARA | F5: BEEMERS BOY | G5: CONDYLAR FRACTURE | H5: =_xlfn.XLOOKUP($G5,RazónMuerte!$A:$A,RazónMuerte!B:B,"",0) -> Fractura ósea | I5: =_xlfn.XLOOKUP($G5,RazónMuerte!$A:$A,RazónMuerte!C:C,"",0) -> Condylar | J5: =_xlfn.XLOOKUP($G5,RazónMuerte!$A:$A,RazónMuerte!D:D,"",0) -> Fatal injury
A6: 5-ENERO-2024 | B6: =LEFT(A6,FIND("-",A6)-1) -> 5 | C6: =MID(A6,FIND("-",A6)+1,FIND("-",A6,FIND("-",A6)+1)-FIND("-",A6)-1) -> ENERO | D6: 45296 | E6: FANTASTIC 4 | F6: MENTIROSO | G6: SEVERE DJD BOTH ANKLES / SEVERE LIGAMENT INJURY WITH BROKEN SPLINT BONES | H6: =_xlfn.XLOOKUP($G6,RazónMuerte!$A:$A,RazónMuerte!B:B,"",0) -> Enfermedad degenerativa articular | I6: =_xlfn.XLOOKUP($G6,RazónMuerte!$A:$A,RazónMuerte!C:C,"",0) -> 0 | J6: =_xlfn.XLOOKUP($G6,RazónMuerte!$A:$A,RazónMuerte!D:D,"",0) -> No fatal injury (chronic/medical)
A7: 5-ENERO-2024 | B7: =LEFT(A7,FIND("-",A7)-1) -> 5 | C7: =MID(A7,FIND("-",A7)+1,FIND("-",A7,FIND("-",A7)+1)-FIND("-",A7)-1) -> ENERO | D7: 45296 | E7: MARQUEZ | F7: PEQUENO ADRIAN | G7: FRACTURA DE LA CANA IZQUIERDA DELANTERA | H7: =_xlfn.XLOOKUP($G7,RazónMuerte!$A:$A,RazónMuerte!B:B,"",0) -> Fractura ósea | I7: =_xlfn.XLOOKUP($G7,RazónMuerte!$A:$A,RazónMuerte!C:C,"",0) -> Caña / Cannon bone | J7: =_xlfn.XLOOKUP($G7,RazónMuerte!$A:$A,RazónMuerte!D:D,"",0) -> Fatal injury
A8: 7-ENERO-2024 | B8: =LEFT(A8,FIND("-",A8)-1) -> 7 | C8: =MID(A8,FIND("-",A8)+1,FIND("-",A8,FIND("-",A8)+1)-FIND("-",A8)-1) -> ENERO | D8: 45298 | E8: SANCHEZ | F8: EVERY DAY CAPI | H8: =_xlfn.XLOOKUP($G8,RazónMuerte!$A:$A,RazónMuerte!B:B,"",0) -> 0 | I8: =_xlfn.XLOOKUP($G8,RazónMuerte!$A:$A,RazónMuerte!C:C,"",0) -> 0 | J8: =_xlfn.XLOOKUP($G8,RazónMuerte!$A:$A,RazónMuerte!D:D,"",0) -> 0
A9: 8-ENERO-2024 | B9: =LEFT(A9,FIND("-",A9)-1) -> 8 | C9: =MID(A9,FIND("-",A9)+1,FIND("-",A9,FIND("-",A9)+1)-FIND("-",A9)-1) -> ENERO | D9: 45299 | E9: MAJESTUOSO (1,000) | F9: VALECAT | H9: =_xlfn.XLOOKUP($G9,RazónMuerte!$A:$A,RazónMuerte!B:B,"",0) -> 0 | I9: =_xlfn.XLOOKUP($G9,RazónMuerte!$A:$A,RazónMuerte!C:C,"",0) -> 0 | J9: =_xlfn.XLOOKUP($G9,RazónMuerte!$A:$A,RazónMuerte!D:D,"",0) -> 0
A10: 11-ENERO-2024 | B10: =LEFT(A10,FIND("-",A10)-1) -> 11 | C10: =MID(A10,FIND("-",A10)+1,FIND("-",A10,FIND("-",A10)+1)-FIND("-",A10)-1) -> ENERO | D10: 45302 | E10: DC | F10: GREY HEART | G10: COMMINUTED SLAB FRACTURE OF RIGHT CIII | H10: =_xlfn.XLOOKUP($G10,RazónMuerte!$A:$A,RazónMuerte!B:B,"",0) -> Fractura ósea | I10: =_xlfn.XLOOKUP($G10,RazónMuerte!$A:$A,RazónMuerte!C:C,"",0) -> Slab | J10: =_xlfn.XLOOKUP($G10,RazónMuerte!$A:$A,RazónMuerte!D:D,"",0) -> Fatal injury
A11: 12-ENERO-2024 | B11: =LEFT(A11,FIND("-",A11)-1) -> 12 | C11: =MID(A11,FIND("-",A11)+1,FIND("-",A11,FIND("-",A11)+1)-FIND("-",A11)-1) -> ENERO | D11: 45303 | E11: ERV | F11: MILAGRITO | G11: SEPTIC JOINT RIGHT INTERCARPAL | H11: =_xlfn.XLOOKUP($G11,RazónMuerte!$A:$A,RazónMuerte!B:B,"",0) -> Otras / No especificada | I11: =_xlfn.XLOOKUP($G11,RazónMuerte!$A:$A,RazónMuerte!C:C,"",0) -> 0 | J11: =_xlfn.XLOOKUP($G11,RazónMuerte!$A:$A,RazónMuerte!D:D,"",0) -> Fatal injury
A12: 12-ENERO-2024 | B12: =LEFT(A12,FIND("-",A12)-1) -> 12 | C12: =MID(A12,FIND("-",A12)+1,FIND("-",A12,FIND("-",A12)+1)-FIND("-",A12)-1) -> ENERO | D12: 45303 | E12: TORRES PAGAN | F12: CONCEPTUS | G12: LAMINITIS | H12: =_xlfn.XLOOKUP($G12,RazónMuerte!$A:$A,RazónMuerte!B:B,"",0) -> Otras / No especificada | I12: =_xlfn.XLOOKUP($G12,RazónMuerte!$A:$A,RazónMuerte!C:C,"",0) -> 0 | J12: =_xlfn.XLOOKUP($G12,RazónMuerte!$A:$A,RazónMuerte!D:D,"",0) -> No clasificado
A13: 12-ENERO-2024 | B13: =LEFT(A13,FIND("-",A13)-1) -> 12 | C13: =MID(A13,FIND("-",A13)+1,FIND("-",A13,FIND("-",A13)+1)-FIND("-",A13)-1) -> ENERO | D13: 45303 | E13: WILLIAM ALVEIRO | F13: BANDIDO | G13: COLICO | H13: =_xlfn.XLOOKUP($G13,RazónMuerte!$A:$A,RazónMuerte!B:B,"",0) -> Otras / No especificada | I13: =_xlfn.XLOOKUP($G13,RazónMuerte!$A:$A,RazónMuerte!C:C,"",0) -> 0 | J13: =_xlfn.XLOOKUP($G13,RazónMuerte!$A:$A,RazónMuerte!D:D,"",0) -> No clasificado
A14: 13-ENERO-2024 | B14: =LEFT(A14,FIND("-",A14)-1) -> 13 | C14: =MID(A14,FIND("-",A14)+1,FIND("-",A14,FIND("-",A14)+1)-FIND("-",A14)-1) -> ENERO | D14: 45304 | E14: LEGACY | F14: KUMANDRA | G14: TENDONITIS SEVERA IZQUIERDA DELANTERA | H14: =_xlfn.XLOOKUP($G14,RazónMuerte!$A:$A,RazónMuerte!B:B,"",0) -> Lesión de ligamentos/tendones | I14: =_xlfn.XLOOKUP($G14,RazónMuerte!$A:$A,RazónMuerte!C:C,"",0) -> 0 | J14: =_xlfn.XLOOKUP($G14,RazónMuerte!$A:$A,RazónMuerte!D:D,"",0) -> No clasificado
A15: 13-ENERO-2024 | B15: =LEFT(A15,FIND("-",A15)-1) -> 13 | C15: =MID(A15,FIND("-",A15)+1,FIND("-",A15,FIND("-",A15)+1)-FIND("-",A15)-1) -> ENERO | D15: 45304 | E15: VILLA REAL | F15: ORGULLOSO | G15: FRACTURA AMBAS RODILLAS | H15: =_xlfn.XLOOKUP($G15,RazónMuerte!$A:$A,RazónMuerte!B:B,"",0) -> Fractura ósea | I15: =_xlfn.XLOOKUP($G15,RazónMuerte!$A:$A,RazónMuerte!C:C,"",0) -> Rodilla / Carpal | J15: =_xlfn.XLOOKUP($G15,RazónMuerte!$A:$A,RazónMuerte!D:D,"",0) -> Fatal injury
A16: 14-ENERO-2024 | B16: =LEFT(A16,FIND("-",A16)-1) -> 14 | C16: =MID(A16,FIND("-",A16)+1,FIND("-",A16,FIND("-",A16)+1)-FIND("-",A16)-1) -> ENERO | D16: 45305 | E16: ERA RACING | F16: MRS KITCHEN | G16: FRACTURA HOMBRO IZQUIERDO | H16: =_xlfn.XLOOKUP($G16,RazónMuerte!$A:$A,RazónMuerte!B:B,"",0) -> Fractura ósea | I16: =_xlfn.XLOOKUP($G16,RazónMuerte!$A:$A,RazónMuerte!C:C,"",0) -> No especificado | J16: =_xlfn.XLOOKUP($G16,RazónMuerte!$A:$A,RazónMuerte!D:D,"",0) -> Fatal injury
A17: 15-ENERO-2024 | B17: =LEFT(A17,FIND("-",A17)-1) -> 15 | C17: =MID(A17,FIND("-",A17)+1,FIND("-",A17,FIND("-",A17)+1)-FIND("-",A17)-1) -> ENERO | D17: 45306 | E17: THREE KINGS | F17: ST. ANDRES | H17: =_xlfn.XLOOKUP($G17,RazónMuerte!$A:$A,RazónMuerte!B:B,"",0) -> 0 | I17: =_xlfn.XLOOKUP($G17,RazónMuerte!$A:$A,RazónMuerte!C:C,"",0) -> 0 | J17: =_xlfn.XLOOKUP($G17,RazónMuerte!$A:$A,RazónMuerte!D:D,"",0) -> 0
A18: 16-ENERO-2024 | B18: =LEFT(A18,FIND("-",A18)-1) -> 16 | C18: =MID(A18,FIND("-",A18)+1,FIND("-",A18,FIND("-",A18)+1)-FIND("-",A18)-1) -> ENERO | D18: 45307 | E18: L & D THOROUGHBRED | F18: JAZHARA | G18: FRACTURA RODILLA DERECHA | H18: =_xlfn.XLOOKUP($G18,RazónMuerte!$A:$A,RazónMuerte!B:B,"",0) -> Fractura ósea | I18: =_xlfn.XLOOKUP($G18,RazónMuerte!$A:$A,RazónMuerte!C:C,"",0) -> Rodilla / Carpal | J18: =_xlfn.XLOOKUP($G18,RazónMuerte!$A:$A,RazónMuerte!D:D,"",0) -> Fatal injury
A19: 16-ENERO-2024 | B19: =LEFT(A19,FIND("-",A19)-1) -> 16 | C19: =MID(A19,FIND("-",A19)+1,FIND("-",A19,FIND("-",A19)+1)-FIND("-",A19)-1) -> ENERO | D19: 45307 | E19: LEGACY | F19: DIXIE CANDY | G19: FETLOCK BREAKDOWN INJURY BOTH HIND LEGS. | H19: =_xlfn.XLOOKUP($G19,RazónMuerte!$A:$A,RazónMuerte!B:B,"",0) -> Otras / No especificada | I19: =_xlfn.XLOOKUP($G19,RazónMuerte!$A:$A,RazónMuerte!C:C,"",0) -> 0 | J19: =_xlfn.XLOOKUP($G19,RazónMuerte!$A:$A,RazónMuerte!D:D,"",0) -> Fatal injury
A20: 19-ENERO-2024 | B20: =LEFT(A20,FIND("-",A20)-1) -> 19 | C20: =MID(A20,FIND("-",A20)+1,FIND("-",A20,FIND("-",A20)+1)-FIND("-",A20)-1) -> ENERO | D20: 45310 | E20: EL DURAKO | F20: EL BUFFALO | G20: Fractura rodilla derecha | H20: =_xlfn.XLOOKUP($G20,RazónMuerte!$A:$A,RazónMuerte!B:B,"",0) -> Fractura ósea | I20: =_xlfn.XLOOKUP($G20,RazónMuerte!$A:$A,RazónMuerte!C:C,"",0) -> Rodilla / Carpal | J20: =_xlfn.XLOOKUP($G20,RazónMuerte!$A:$A,RazónMuerte!D:D,"",0) -> Fatal injury
A21: 19-ENERO-2024 | B21: =LEFT(A21,FIND("-",A21)-1) -> 19 | C21: =MID(A21,FIND("-",A21)+1,FIND("-",A21,FIND("-",A21)+1)-FIND("-",A21)-1) -> ENERO | D21: 45310 | E21: KEANCA | F21: MY MAGICAL MAN | G21: Artritis severa menudillo izquierdo delantero | H21: =_xlfn.XLOOKUP($G21,RazónMuerte!$A:$A,RazónMuerte!B:B,"",0) -> Enfermedad degenerativa articular | I21: =_xlfn.XLOOKUP($G21,RazónMuerte!$A:$A,RazónMuerte!C:C,"",0) -> 0 | J21: =_xlfn.XLOOKUP($G21,RazónMuerte!$A:$A,RazónMuerte!D:D,"",0) -> No fatal injury (chronic/medical)
A22: 20-ENERO-2024 | B22: =LEFT(A22,FIND("-",A22)-1) -> 20 | C22: =MID(A22,FIND("-",A22)+1,FIND("-",A22,FIND("-",A22)+1)-FIND("-",A22)-1) -> ENERO | D22: 45311 | E22: ALEXIS CARTAGENA | F22: NEPTUNO | G22: Colico | H22: =_xlfn.XLOOKUP($G22,RazónMuerte!$A:$A,RazónMuerte!B:B,"",0) -> Otras / No especificada | I22: =_xlfn.XLOOKUP($G22,RazónMuerte!$A:$A,RazónMuerte!C:C,"",0) -> 0 | J22: =_xlfn.XLOOKUP($G22,RazónMuerte!$A:$A,RazónMuerte!D:D,"",0) -> No clasificado
A23: 22-ENERO-2024 | B23: =LEFT(A23,FIND("-",A23)-1) -> 22 | C23: =MID(A23,FIND("-",A23)+1,FIND("-",A23,FIND("-",A23)+1)-FIND("-",A23)-1) -> ENERO | D23: 45313 | E23: SML | F23: MY WAY OR ELSE | G23: Artritis septica (menudillo derecho delantero) | H23: =_xlfn.XLOOKUP($G23,RazónMuerte!$A:$A,RazónMuerte!B:B,"",0) -> Enfermedad degenerativa articular | I23: =_xlfn.XLOOKUP($G23,RazónMuerte!$A:$A,RazónMuerte!C:C,"",0) -> 0 | J23: =_xlfn.XLOOKUP($G23,RazónMuerte!$A:$A,RazónMuerte!D:D,"",0) -> No fatal injury (chronic/medical)
A24: 22-ENERO-2024 | B24: =LEFT(A24,FIND("-",A24)-1) -> 22 | C24: =MID(A24,FIND("-",A24)+1,FIND("-",A24,FIND("-",A24)+1)-FIND("-",A24)-1) -> ENERO | D24: 45313 | E24: SJ FARM | F24: NOICATTIRO | G24: Right front ankle fracture sesamoid. Laminitis of both hands can't walk or train. | H24: =_xlfn.XLOOKUP($G24,RazónMuerte!$A:$A,RazónMuerte!B:B,"",0) -> Fractura ósea | I24: =_xlfn.XLOOKUP($G24,RazónMuerte!$A:$A,RazónMuerte!C:C,"",0) -> Sesamoideo | J24: =_xlfn.XLOOKUP($G24,RazónMuerte!$A:$A,RazónMuerte!D:D,"",0) -> Fatal injury
A25: 22-ENERO-2024 | B25: =LEFT(A25,FIND("-",A25)-1) -> 22 | C25: =MID(A25,FIND("-",A25)+1,FIND("-",A25,FIND("-",A25)+1)-FIND("-",A25)-1) -> ENERO | D25: 45313 | E25: SACO E SAL | F25: REGINA ISABEL | G25: Fractura rodilla derecha | H25: =_xlfn.XLOOKUP($G25,RazónMuerte!$A:$A,RazónMuerte!B:B,"",0) -> Fractura ósea | I25: =_xlfn.XLOOKUP($G25,RazónMuerte!$A:$A,RazónMuerte!C:C,"",0) -> Rodilla / Carpal | J25: =_xlfn.XLOOKUP($G25,RazónMuerte!$A:$A,RazónMuerte!D:D,"",0) -> Fatal injury
A26: 26-ENERO-2024 | B26: =LEFT(A26,FIND("-",A26)-1) -> 26 | C26: =MID(A26,FIND("-",A26)+1,FIND("-",A26,FIND("-",A26)+1)-FIND("-",A26)-1) -> ENERO | D26: 45317 | E26: BROTHERS | F26: PRESENTADOR | G26: Laminitis cronica. | H26: =_xlfn.XLOOKUP($G26,RazónMuerte!$A:$A,RazónMuerte!B:B,"",0) -> Otras / No especificada | I26: =_xlfn.XLOOKUP($G26,RazónMuerte!$A:$A,RazónMuerte!C:C,"",0) -> 0 | J26: =_xlfn.XLOOKUP($G26,RazónMuerte!$A:$A,RazónMuerte!D:D,"",0) -> No clasificado
A27: 31-ENERO-2024 | B27: =LEFT(A27,FIND("-",A27)-1) -> 31 | C27: =MID(A27,FIND("-",A27)+1,FIND("-",A27,FIND("-",A27)+1)-FIND("-",A27)-1) -> ENERO | D27: 45322 | E27: JF | F27: MISTER PILOT | G27: Fractura Húmero | H27: =_xlfn.XLOOKUP($G27,RazónMuerte!$A:$A,RazónMuerte!B:B,"",0) -> Fractura ósea | I27: =_xlfn.XLOOKUP($G27,RazónMuerte!$A:$A,RazónMuerte!C:C,"",0) -> No especificado | J27: =_xlfn.XLOOKUP($G27,RazónMuerte!$A:$A,RazónMuerte!D:D,"",0) -> Fatal injury
A28: 2-FEBRERO-2024 | B28: =LEFT(A28,FIND("-",A28)-1) -> 2 | C28: =MID(A28,FIND("-",A28)+1,FIND("-",A28,FIND("-",A28)+1)-FIND("-",A28)-1) -> FEBRERO | D28: 45324 | E28: N Y N | F28: UNIFIED CONQUEST | G28: HERIDA PARTE POSTERIOR DEL MENUDILLO, CUARTILLA IZQUIERDA DELANTERA INCLUYENDO LA VAINA DEL TENDON | H28: =_xlfn.XLOOKUP($G28,RazónMuerte!$A:$A,RazónMuerte!B:B,"",0) -> Lesión de ligamentos/tendones | I28: =_xlfn.XLOOKUP($G28,RazónMuerte!$A:$A,RazónMuerte!C:C,"",0) -> 0 | J28: =_xlfn.XLOOKUP($G28,RazónMuerte!$A:$A,RazónMuerte!D:D,"",0) -> No clasificado
A29: 5-FEBRERO-2024 | B29: =LEFT(A29,FIND("-",A29)-1) -> 5 | C29: =MID(A29,FIND("-",A29)+1,FIND("-",A29,FIND("-",A29)+1)-FIND("-",A29)-1) -> FEBRERO | D29: 45327 | E29: ANGEL CALDERON | F29: CYBERICA | G29: ARTRITIS SEVERA EN MENUDILLO DELANTERO. | H29: =_xlfn.XLOOKUP($G29,RazónMuerte!$A:$A,RazónMuerte!B:B,"",0) -> Enfermedad degenerativa articular | I29: =_xlfn.XLOOKUP($G29,RazónMuerte!$A:$A,RazónMuerte!C:C,"",0) -> 0 | J29: =_xlfn.XLOOKUP($G29,RazónMuerte!$A:$A,RazónMuerte!D:D,"",0) -> No fatal injury (chronic/medical)
... A359: 3-AGOSTO-2025 | B359: =LEFT(A359,FIND("-",A359)-1) -> 3 | C359: =MID(A359,FIND("-",A359)+1,FIND("-",A359,FIND("-",A359)+1)-FIND("-",A359)-1) -> AGOSTO | D359: 45872 | E359: M SANTIAGO | F359: ARABIAN MOON | G359: Fractura rodilla izquierda (Guardia PRHOA) | H359: =_xlfn.XLOOKUP($G359,RazónMuerte!$A:$A,RazónMuerte!B:B,"",0) -> Fractura ósea | I359: =_xlfn.XLOOKUP($G359,RazónMuerte!$A:$A,RazónMuerte!C:C,"",0) -> Rodilla / Carpal | J359: =_xlfn.XLOOKUP($G359,RazónMuerte!$A:$A,RazónMuerte!D:D,"",0) -> Fatal injury
A360: 3-AGOSTO-2025 | B360: =LEFT(A360,FIND("-",A360)-1) -> 3 | C360: =MID(A360,FIND("-",A360)+1,FIND("-",A360,FIND("-",A360)+1)-FIND("-",A360)-1) -> AGOSTO | D360: 45872 | E360: JORMALY | F360: LA NIETA E JORGI C | H360: =_xlfn.XLOOKUP($G360,RazónMuerte!$A:$A,RazónMuerte!B:B,"",0) -> 0 | I360: =_xlfn.XLOOKUP($G360,RazónMuerte!$A:$A,RazónMuerte!C:C,"",0) -> 0 | J360: =_xlfn.XLOOKUP($G360,RazónMuerte!$A:$A,RazónMuerte!D:D,"",0) -> 0
A361: 4-AGOSTO-2025 | B361: =LEFT(A361,FIND("-",A361)-1) -> 4 | C361: =MID(A361,FIND("-",A361)+1,FIND("-",A361,FIND("-",A361)+1)-FIND("-",A361)-1) -> AGOSTO | D361: 45873 | E361: SANTA RITA | F361: YERAI | G361: Slab fracture L Knee | H361: =_xlfn.XLOOKUP($G361,RazónMuerte!$A:$A,RazónMuerte!B:B,"",0) -> Fractura ósea | I361: =_xlfn.XLOOKUP($G361,RazónMuerte!$A:$A,RazónMuerte!C:C,"",0) -> Slab | J361: =_xlfn.XLOOKUP($G361,RazónMuerte!$A:$A,RazónMuerte!D:D,"",0) -> Fatal injury
A362: 4-AGOSTO-2025 | B362: =LEFT(A362,FIND("-",A362)-1) -> 4 | C362: =MID(A362,FIND("-",A362)+1,FIND("-",A362,FIND("-",A362)+1)-FIND("-",A362)-1) -> AGOSTO | D362: 45873 | E362: TARRATS NACC | F362: DIAMOND THE GOAT | G362: RF base sesamoid fracture | H362: =_xlfn.XLOOKUP($G362,RazónMuerte!$A:$A,RazónMuerte!B:B,"",0) -> Fractura ósea | I362: =_xlfn.XLOOKUP($G362,RazónMuerte!$A:$A,RazónMuerte!C:C,"",0) -> Sesamoideo | J362: =_xlfn.XLOOKUP($G362,RazónMuerte!$A:$A,RazónMuerte!D:D,"",0) -> Fatal injury
A363: 4-AGOSTO-2025 | B363: =LEFT(A363,FIND("-",A363)-1) -> 4 | C363: =MID(A363,FIND("-",A363)+1,FIND("-",A363,FIND("-",A363)+1)-FIND("-",A363)-1) -> AGOSTO | D363: 45873 | E363: VILLA REAL | F363: PERFECCIONISTA | G363: L C3 Slab fracture. | H363: =_xlfn.XLOOKUP($G363,RazónMuerte!$A:$A,RazónMuerte!B:B,"",0) -> Fractura ósea | I363: =_xlfn.XLOOKUP($G363,RazónMuerte!$A:$A,RazónMuerte!C:C,"",0) -> Slab | J363: =_xlfn.XLOOKUP($G363,RazónMuerte!$A:$A,RazónMuerte!D:D,"",0) -> Fatal injury
A364: 9-AGOSTO-2025 | B364: =LEFT(A364,FIND("-",A364)-1) -> 9 | C364: =MID(A364,FIND("-",A364)+1,FIND("-",A364,FIND("-",A364)+1)-FIND("-",A364)-1) -> AGOSTO | D364: 45878 | E364: SONATA | F364: VOLATILE DANCER | G364: LF Breakdown injury. | H364: =_xlfn.XLOOKUP($G364,RazónMuerte!$A:$A,RazónMuerte!B:B,"",0) -> Otras / No especificada | I364: =_xlfn.XLOOKUP($G364,RazónMuerte!$A:$A,RazónMuerte!C:C,"",0) -> 0 | J364: =_xlfn.XLOOKUP($G364,RazónMuerte!$A:$A,RazónMuerte!D:D,"",0) -> No clasificado
A365: 11-AGOSTO-2025 | B365: =LEFT(A365,FIND("-",A365)-1) -> 11 | C365: =MID(A365,FIND("-",A365)+1,FIND("-",A365,FIND("-",A365)+1)-FIND("-",A365)-1) -> AGOSTO | D365: 45880 | E365: POCOS PERO FIRMES | F365: ANFITRIONA | G365: Fractura rodilla derecha. | H365: =_xlfn.XLOOKUP($G365,RazónMuerte!$A:$A,RazónMuerte!B:B,"",0) -> Fractura ósea | I365: =_xlfn.XLOOKUP($G365,RazónMuerte!$A:$A,RazónMuerte!C:C,"",0) -> Rodilla / Carpal | J365: =_xlfn.XLOOKUP($G365,RazónMuerte!$A:$A,RazónMuerte!D:D,"",0) -> Fatal injury
A366: 13-AGOSTO-2025 | B366: =LEFT(A366,FIND("-",A366)-1) -> 13 | C366: =MID(A366,FIND("-",A366)+1,FIND("-",A366,FIND("-",A366)+1)-FIND("-",A366)-1) -> AGOSTO | D366: 45882 | E366: JI DIAMOND | F366: PESCADOR DE SUEÑOS | G366: Fractura rodilla derecha. | H366: =_xlfn.XLOOKUP($G366,RazónMuerte!$A:$A,RazónMuerte!B:B,"",0) -> Fractura ósea | I366: =_xlfn.XLOOKUP($G366,RazónMuerte!$A:$A,RazónMuerte!C:C,"",0) -> Rodilla / Carpal | J366: =_xlfn.XLOOKUP($G366,RazónMuerte!$A:$A,RazónMuerte!D:D,"",0) -> Fatal injury
A367: 13-AGOSTO-2025 | B367: =LEFT(A367,FIND("-",A367)-1) -> 13 | C367: =MID(A367,FIND("-",A367)+1,FIND("-",A367,FIND("-",A367)+1)-FIND("-",A367)-1) -> AGOSTO | D367: 45882 | E367: JI DIAMOND | F367: EL GALLOLFO | G367: Laminitis en ambas manos/Múltiples fracturas en ambas rodillas L>R. | H367: =_xlfn.XLOOKUP($G367,RazónMuerte!$A:$A,RazónMuerte!B:B,"",0) -> Fractura ósea | I367: =_xlfn.XLOOKUP($G367,RazónMuerte!$A:$A,RazónMuerte!C:C,"",0) -> Rodilla / Carpal | J367: =_xlfn.XLOOKUP($G367,RazónMuerte!$A:$A,RazónMuerte!D:D,"",0) -> Fatal injury
A368: 13-AGOSTO-2025 | B368: =LEFT(A368,FIND("-",A368)-1) -> 13 | C368: =MID(A368,FIND("-",A368)+1,FIND("-",A368,FIND("-",A368)+1)-FIND("-",A368)-1) -> AGOSTO | D368: 45882 | E368: JI DIAMOND | F368: BLACK SILK | G368: Fractura rodilla izquierda. | H368: =_xlfn.XLOOKUP($G368,RazónMuerte!$A:$A,RazónMuerte!B:B,"",0) -> Fractura ósea | I368: =_xlfn.XLOOKUP($G368,RazónMuerte!$A:$A,RazónMuerte!C:C,"",0) -> Rodilla / Carpal | J368: =_xlfn.XLOOKUP($G368,RazónMuerte!$A:$A,RazónMuerte!D:D,"",0) -> Fatal injury
A369: 14-AGOSTO-2025 | B369: =LEFT(A369,FIND("-",A369)-1) -> 14 | C369: =MID(A369,FIND("-",A369)+1,FIND("-",A369,FIND("-",A369)+1)-FIND("-",A369)-1) -> AGOSTO | D369: 45883 | E369: QUINTANA | F369: HARD TEN | G369: Artritis severa menudillo derecho delantero. | H369: =_xlfn.XLOOKUP($G369,RazónMuerte!$A:$A,RazónMuerte!B:B,"",0) -> Enfermedad degenerativa articular | I369: =_xlfn.XLOOKUP($G369,RazónMuerte!$A:$A,RazónMuerte!C:C,"",0) -> 0 | J369: =_xlfn.XLOOKUP($G369,RazónMuerte!$A:$A,RazónMuerte!D:D,"",0) -> No fatal injury (chronic/medical)
A370: 18-AGOSTO-2025 | B370: =LEFT(A370,FIND("-",A370)-1) -> 18 | C370: =MID(A370,FIND("-",A370)+1,FIND("-",A370,FIND("-",A370)+1)-FIND("-",A370)-1) -> AGOSTO | D370: 45887 | E370: RAMZ | F370: UCASTEO | G370: Laminitis severa (sinker). (Referido PRHOA) | H370: =_xlfn.XLOOKUP($G370,RazónMuerte!$A:$A,RazónMuerte!B:B,"",0) -> Otras / No especificada | I370: =_xlfn.XLOOKUP($G370,RazónMuerte!$A:$A,RazónMuerte!C:C,"",0) -> 0 | J370: =_xlfn.XLOOKUP($G370,RazónMuerte!$A:$A,RazónMuerte!D:D,"",0) -> No clasificado
A371: 18-AGOSTO-2025 | B371: =LEFT(A371,FIND("-",A371)-1) -> 18 | C371: =MID(A371,FIND("-",A371)+1,FIND("-",A371,FIND("-",A371)+1)-FIND("-",A371)-1) -> AGOSTO | D371: 45887 | E371: VMH | F371: EMILIA D | G371: Múltiples fracturas en ambas rodillas L>R. | H371: =_xlfn.XLOOKUP($G371,RazónMuerte!$A:$A,RazónMuerte!B:B,"",0) -> Fractura ósea | I371: =_xlfn.XLOOKUP($G371,RazónMuerte!$A:$A,RazónMuerte!C:C,"",0) -> Rodilla / Carpal | J371: =_xlfn.XLOOKUP($G371,RazónMuerte!$A:$A,RazónMuerte!D:D,"",0) -> Fatal injury
A372: 20-AGOSTO-2025 | B372: =LEFT(A372,FIND("-",A372)-1) -> 20 | C372: =MID(A372,FIND("-",A372)+1,FIND("-",A372,FIND("-",A372)+1)-FIND("-",A372)-1) -> AGOSTO | D372: 45889 | E372: FLAMBOYÁN | F372: DULCE BISCUIT | G372: Artritis en ambos menudillos delanteros. Historial previo de laminitis. | H372: =_xlfn.XLOOKUP($G372,RazónMuerte!$A:$A,RazónMuerte!B:B,"",0) -> Enfermedad degenerativa articular | I372: =_xlfn.XLOOKUP($G372,RazónMuerte!$A:$A,RazónMuerte!C:C,"",0) -> 0 | J372: =_xlfn.XLOOKUP($G372,RazónMuerte!$A:$A,RazónMuerte!D:D,"",0) -> No fatal injury (chronic/medical)
... A447: 31-DICIEMBRE-2025 | B447: =LEFT(A447,FIND("-",A447)-1) -> 31 | C447: =MID(A447,FIND("-",A447)+1,FIND("-",A447,FIND("-",A447)+1)-FIND("-",A447)-1) -> DICIEMBRE | D447: 46022 | E447: RAMZ | F447: JORGITO L | G447: Chronic diarrea for 5 weeks duration. R hind limb cellulitis. (Referido PRHOA) | H447: =_xlfn.XLOOKUP($G447,RazónMuerte!$A:$A,RazónMuerte!B:B,"",0) -> Otras / No especificada | I447: =_xlfn.XLOOKUP($G447,RazónMuerte!$A:$A,RazónMuerte!C:C,"",0) -> 0 | J447: =_xlfn.XLOOKUP($G447,RazónMuerte!$A:$A,RazónMuerte!D:D,"",0) -> No fatal injury (chronic/medical)

Sheet 2024 data
A1: FECHA | B1: día | C1: Mes | D1: Last Race Date (desde Equibase) | E1: Death Date | F1: ESTABLO | G1: Horas transcurridas | H1: CABALLO | I1: RAZON | J1: Categoría | K1: Tipo de fractura | L1: Fatal injury | M1: Registrado/Compitió?
A2: 2-ENERO-2024 | B2: =LEFT(A2,FIND("-",A2)-1) -> 2 | C2: =MID(A2,FIND("-",A2)+1,FIND("-",A2,FIND("-",A2)+1)-FIND("-",A2)-1) -> ENERO | D2: 45282 | E2: 45293 | F2: GARCIA | G2: =(E2-D2)*24 -> 264 | H2: LA PATRONA G | J2: =_xlfn.XLOOKUP($I2,RazónMuerte!$A:$A,RazónMuerte!B:B,"",0) -> 0 | K2: =_xlfn.XLOOKUP($I2,RazónMuerte!$A:$A,RazónMuerte!C:C,"",0) -> 0 | L2: =_xlfn.XLOOKUP($I2,RazónMuerte!$A:$A,RazónMuerte!D:D,"",0) -> 0
A3: 3-ENERO-2024 | B3: =LEFT(A3,FIND("-",A3)-1) -> 3 | C3: =MID(A3,FIND("-",A3)+1,FIND("-",A3,FIND("-",A3)+1)-FIND("-",A3)-1) -> ENERO | D3: 45106 | E3: 45294 | F3: AQUINO | G3: =(E3-D3)*24 -> 4512 | H3: PROSPECT PROJECT | I3: END STAGE ARTHRITIS RF FETLOCK | J3: =_xlfn.XLOOKUP($I3,RazónMuerte!$A:$A,RazónMuerte!B:B,"",0) -> Enfermedad degenerativa articular | K3: =_xlfn.XLOOKUP($I3,RazónMuerte!$A:$A,RazónMuerte!C:C,"",0) -> 0 | L3: =_xlfn.XLOOKUP($I3,RazónMuerte!$A:$A,RazónMuerte!D:D,"",0) -> Fatal injury
A4: 4-ENERO-2024 | B4: =LEFT(A4,FIND("-",A4)-1) -> 4 | C4: =MID(A4,FIND("-",A4)+1,FIND("-",A4,FIND("-",A4)+1)-FIND("-",A4)-1) -> ENERO | D4: 45221 | E4: 45295 | F4: GCA | G4: =(E4-D4)*24 -> 1776 | H4: CONVINCENTE | I4: FRACTURA RODILLA IZQUIERDA | J4: =_xlfn.XLOOKUP($I4,RazónMuerte!$A:$A,RazónMuerte!B:B,"",0) -> Fractura ósea | K4: =_xlfn.XLOOKUP($I4,RazónMuerte!$A:$A,RazónMuerte!C:C,"",0) -> Rodilla / Carpal | L4: =_xlfn.XLOOKUP($I4,RazónMuerte!$A:$A,RazónMuerte!D:D,"",0) -> Fatal injury
A5: 5-ENERO-2024 | B5: =LEFT(A5,FIND("-",A5)-1) -> 5 | C5: =MID(A5,FIND("-",A5)+1,FIND("-",A5,FIND("-",A5)+1)-FIND("-",A5)-1) -> ENERO | D5: 45274 | E5: 45296 | F5: LANCARA | G5: =(E5-D5)*24 -> 528 | H5: BEEMERS BOY | I5: CONDYLAR FRACTURE | J5: =_xlfn.XLOOKUP($I5,RazónMuerte!$A:$A,RazónMuerte!B:B,"",0) -> Fractura ósea | K5: =_xlfn.XLOOKUP($I5,RazónMuerte!$A:$A,RazónMuerte!C:C,"",0) -> Condylar | L5: =_xlfn.XLOOKUP($I5,RazónMuerte!$A:$A,RazónMuerte!D:D,"",0) -> Fatal injury
A6: 5-ENERO-2024 | B6: =LEFT(A6,FIND("-",A6)-1) -> 5 | C6: =MID(A6,FIND("-",A6)+1,FIND("-",A6,FIND("-",A6)+1)-FIND("-",A6)-1) -> ENERO | D6: 45277 | E6: 45296 | F6: FANTASTIC 4 | G6: =(E6-D6)*24 -> 456 | H6: MENTIROSO | I6: SEVERE DJD BOTH ANKLES / SEVERE LIGAMENT INJURY WITH BROKEN SPLINT BONES | J6: =_xlfn.XLOOKUP($I6,RazónMuerte!$A:$A,RazónMuerte!B:B,"",0) -> Enfermedad degenerativa articular | K6: =_xlfn.XLOOKUP($I6,RazónMuerte!$A:$A,RazónMuerte!C:C,"",0) -> 0 | L6: =_xlfn.XLOOKUP($I6,RazónMuerte!$A:$A,RazónMuerte!D:D,"",0) -> No fatal injury (chronic/medical)
A7: 5-ENERO-2024 | B7: =LEFT(A7,FIND("-",A7)-1) -> 5 | C7: =MID(A7,FIND("-",A7)+1,FIND("-",A7,FIND("-",A7)+1)-FIND("-",A7)-1) -> ENERO | D7: 45282 | E7: 45296 | F7: MARQUEZ | G7: =(E7-D7)*24 -> 336 | H7: PEQUENO ADRIAN | I7: FRACTURA DE LA CANA IZQUIERDA DELANTERA | J7: =_xlfn.XLOOKUP($I7,RazónMuerte!$A:$A,RazónMuerte!B:B,"",0) -> Fractura ósea | K7: =_xlfn.XLOOKUP($I7,RazónMuerte!$A:$A,RazónMuerte!C:C,"",0) -> Caña / Cannon bone | L7: =_xlfn.XLOOKUP($I7,RazónMuerte!$A:$A,RazónMuerte!D:D,"",0) -> Fatal injury
A8: 7-ENERO-2024 | B8: =LEFT(A8,FIND("-",A8)-1) -> 7 | C8: =MID(A8,FIND("-",A8)+1,FIND("-",A8,FIND("-",A8)+1)-FIND("-",A8)-1) -> ENERO | D8: 45298 | E8: 45298 | F8: SANCHEZ | G8: =(E8-D8)*24 -> 0 | H8: EVERY DAY CAPI | J8: =_xlfn.XLOOKUP($I8,RazónMuerte!$A:$A,RazónMuerte!B:B,"",0) -> 0 | K8: =_xlfn.XLOOKUP($I8,RazónMuerte!$A:$A,RazónMuerte!C:C,"",0) -> 0 | L8: =_xlfn.XLOOKUP($I8,RazónMuerte!$A:$A,RazónMuerte!D:D,"",0) -> 0
A9: 8-ENERO-2024 | B9: =LEFT(A9,FIND("-",A9)-1) -> 8 | C9: =MID(A9,FIND("-",A9)+1,FIND("-",A9,FIND("-",A9)+1)-FIND("-",A9)-1) -> ENERO | D9: 45277 | E9: 45299 | F9: MAJESTUOSO (1,000) | G9: =(E9-D9)*24 -> 528 | H9: VALECAT | J9: =_xlfn.XLOOKUP($I9,RazónMuerte!$A:$A,RazónMuerte!B:B,"",0) -> 0 | K9: =_xlfn.XLOOKUP($I9,RazónMuerte!$A:$A,RazónMuerte!C:C,"",0) -> 0 | L9: =_xlfn.XLOOKUP($I9,RazónMuerte!$A:$A,RazónMuerte!D:D,"",0) -> 0
A10: 11-ENERO-2024 | B10: =LEFT(A10,FIND("-",A10)-1) -> 11 | C10: =MID(A10,FIND("-",A10)+1,FIND("-",A10,FIND("-",A10)+1)-FIND("-",A10)-1) -> ENERO | E10: 45302 | F10: DC | G10: =(E10-D10)*24 -> 1087248 | H10: GREY HEART | I10: COMMINUTED SLAB FRACTURE OF RIGHT CIII | J10: =_xlfn.XLOOKUP($I10,RazónMuerte!$A:$A,RazónMuerte!B:B,"",0) -> Fractura ósea | K10: =_xlfn.XLOOKUP($I10,RazónMuerte!$A:$A,RazónMuerte!C:C,"",0) -> Slab | L10: =_xlfn.XLOOKUP($I10,RazónMuerte!$A:$A,RazónMuerte!D:D,"",0) -> Fatal injury
A11: 12-ENERO-2024 | B11: =LEFT(A11,FIND("-",A11)-1) -> 12 | C11: =MID(A11,FIND("-",A11)+1,FIND("-",A11,FIND("-",A11)+1)-FIND("-",A11)-1) -> ENERO | E11: 45303 | F11: ERV | G11: =(E11-D11)*24 -> 1087272 | H11: MILAGRITO | I11: SEPTIC JOINT RIGHT INTERCARPAL | J11: =_xlfn.XLOOKUP($I11,RazónMuerte!$A:$A,RazónMuerte!B:B,"",0) -> Otras / No especificada | K11: =_xlfn.XLOOKUP($I11,RazónMuerte!$A:$A,RazónMuerte!C:C,"",0) -> 0 | L11: =_xlfn.XLOOKUP($I11,RazónMuerte!$A:$A,RazónMuerte!D:D,"",0) -> Fatal injury
A12: 12-ENERO-2024 | B12: =LEFT(A12,FIND("-",A12)-1) -> 12 | C12: =MID(A12,FIND("-",A12)+1,FIND("-",A12,FIND("-",A12)+1)-FIND("-",A12)-1) -> ENERO | D12: 45275 | E12: 45303 | F12: TORRES PAGAN | G12: =(E12-D12)*24 -> 672 | H12: CONCEPTUS | I12: LAMINITIS | J12: =_xlfn.XLOOKUP($I12,RazónMuerte!$A:$A,RazónMuerte!B:B,"",0) -> Otras / No especificada | K12: =_xlfn.XLOOKUP($I12,RazónMuerte!$A:$A,RazónMuerte!C:C,"",0) -> 0 | L12: =_xlfn.XLOOKUP($I12,RazónMuerte!$A:$A,RazónMuerte!D:D,"",0) -> No clasificado
A13: 12-ENERO-2024 | B13: =LEFT(A13,FIND("-",A13)-1) -> 12 | C13: =MID(A13,FIND("-",A13)+1,FIND("-",A13,FIND("-",A13)+1)-FIND("-",A13)-1) -> ENERO | E13: 45303 | F13: WILLIAM ALVEIRO | G13: =(E13-D13)*24 -> 1087272 | H13: BANDIDO | I13: COLICO | J13: =_xlfn.XLOOKUP($I13,RazónMuerte!$A:$A,RazónMuerte!B:B,"",0) -> Otras / No especificada | K13: =_xlfn.XLOOKUP($I13,RazónMuerte!$A:$A,RazónMuerte!C:C,"",0) -> 0 | L13: =_xlfn.XLOOKUP($I13,RazónMuerte!$A:$A,RazónMuerte!D:D,"",0) -> No clasificado
A14: 13-ENERO-2024 | B14: =LEFT(A14,FIND("-",A14)-1) -> 13 | C14: =MID(A14,FIND("-",A14)+1,FIND("-",A14,FIND("-",A14)+1)-FIND("-",A14)-1) -> ENERO | D14: 44946 | E14: 45304 | F14: LEGACY | G14: =(E14-D14)*24 -> 8592 | H14: KUMANDRA | I14: TENDONITIS SEVERA IZQUIERDA DELANTERA | J14: =_xlfn.XLOOKUP($I14,RazónMuerte!$A:$A,RazónMuerte!B:B,"",0) -> Lesión de ligamentos/tendones | K14: =_xlfn.XLOOKUP($I14,RazónMuerte!$A:$A,RazónMuerte!C:C,"",0) -> 0 | L14: =_xlfn.XLOOKUP($I14,RazónMuerte!$A:$A,RazónMuerte!D:D,"",0) -> No clasificado
A15: 13-ENERO-2024 | B15: =LEFT(A15,FIND("-",A15)-1) -> 13 | C15: =MID(A15,FIND("-",A15)+1,FIND("-",A15,FIND("-",A15)+1)-FIND("-",A15)-1) -> ENERO | D15: 45296 | E15: 45304 | F15: VILLA REAL | G15: =(E15-D15)*24 -> 192 | H15: ORGULLOSO | I15: FRACTURA AMBAS RODILLAS | J15: =_xlfn.XLOOKUP($I15,RazónMuerte!$A:$A,RazónMuerte!B:B,"",0) -> Fractura ósea | K15: =_xlfn.XLOOKUP($I15,RazónMuerte!$A:$A,RazónMuerte!C:C,"",0) -> Rodilla / Carpal | L15: =_xlfn.XLOOKUP($I15,RazónMuerte!$A:$A,RazónMuerte!D:D,"",0) -> Fatal injury
A16: 14-ENERO-2024 | B16: =LEFT(A16,FIND("-",A16)-1) -> 14 | C16: =MID(A16,FIND("-",A16)+1,FIND("-",A16,FIND("-",A16)+1)-FIND("-",A16)-1) -> ENERO | E16: 45305 | F16: ERA RACING | G16: =(E16-D16)*24 -> 1087320 | H16: MRS KITCHEN | I16: FRACTURA HOMBRO IZQUIERDO | J16: =_xlfn.XLOOKUP($I16,RazónMuerte!$A:$A,RazónMuerte!B:B,"",0) -> Fractura ósea | K16: =_xlfn.XLOOKUP($I16,RazónMuerte!$A:$A,RazónMuerte!C:C,"",0) -> No especificado | L16: =_xlfn.XLOOKUP($I16,RazónMuerte!$A:$A,RazónMuerte!D:D,"",0) -> Fatal injury
A17: 15-ENERO-2024 | B17: =LEFT(A17,FIND("-",A17)-1) -> 15 | C17: =MID(A17,FIND("-",A17)+1,FIND("-",A17,FIND("-",A17)+1)-FIND("-",A17)-1) -> ENERO | D17: 45305 | E17: 45306 | F17: THREE KINGS | G17: =(E17-D17)*24 -> 24 | H17: ST. ANDRES | J17: =_xlfn.XLOOKUP($I17,RazónMuerte!$A:$A,RazónMuerte!B:B,"",0) -> 0 | K17: =_xlfn.XLOOKUP($I17,RazónMuerte!$A:$A,RazónMuerte!C:C,"",0) -> 0 | L17: =_xlfn.XLOOKUP($I17,RazónMuerte!$A:$A,RazónMuerte!D:D,"",0) -> 0
A18: 16-ENERO-2024 | B18: =LEFT(A18,FIND("-",A18)-1) -> 16 | C18: =MID(A18,FIND("-",A18)+1,FIND("-",A18,FIND("-",A18)+1)-FIND("-",A18)-1) -> ENERO | D18: 45306 | E18: 45307 | F18: L & D THOROUGHBRED | G18: =(E18-D18)*24 -> 24 | H18: JAZHARA | I18: FRACTURA RODILLA DERECHA | J18: =_xlfn.XLOOKUP($I18,RazónMuerte!$A:$A,RazónMuerte!B:B,"",0) -> Fractura ósea | K18: =_xlfn.XLOOKUP($I18,RazónMuerte!$A:$A,RazónMuerte!C:C,"",0) -> Rodilla / Carpal | L18: =_xlfn.XLOOKUP($I18,RazónMuerte!$A:$A,RazónMuerte!D:D,"",0) -> Fatal injury
A19: 16-ENERO-2024 | B19: =LEFT(A19,FIND("-",A19)-1) -> 16 | C19: =MID(A19,FIND("-",A19)+1,FIND("-",A19,FIND("-",A19)+1)-FIND("-",A19)-1) -> ENERO | D19: 44764 | E19: 45307 | F19: LEGACY | G19: =(E19-D19)*24 -> 13032 | H19: DIXIE CANDY | I19: FETLOCK BREAKDOWN INJURY BOTH HIND LEGS. | J19: =_xlfn.XLOOKUP($I19,RazónMuerte!$A:$A,RazónMuerte!B:B,"",0) -> Otras / No especificada | K19: =_xlfn.XLOOKUP($I19,RazónMuerte!$A:$A,RazónMuerte!C:C,"",0) -> 0 | L19: =_xlfn.XLOOKUP($I19,RazónMuerte!$A:$A,RazónMuerte!D:D,"",0) -> Fatal injury
A20: 19-ENERO-2024 | B20: =LEFT(A20,FIND("-",A20)-1) -> 19 | C20: =MID(A20,FIND("-",A20)+1,FIND("-",A20,FIND("-",A20)+1)-FIND("-",A20)-1) -> ENERO | D20: 45275 | E20: 45310 | F20: EL DURAKO | G20: =(E20-D20)*24 -> 840 | H20: EL BUFFALO | I20: Fractura rodilla derecha | J20: =_xlfn.XLOOKUP($I20,RazónMuerte!$A:$A,RazónMuerte!B:B,"",0) -> Fractura ósea | K20: =_xlfn.XLOOKUP($I20,RazónMuerte!$A:$A,RazónMuerte!C:C,"",0) -> Rodilla / Carpal | L20: =_xlfn.XLOOKUP($I20,RazónMuerte!$A:$A,RazónMuerte!D:D,"",0) -> Fatal injury
A21: 19-ENERO-2024 | B21: =LEFT(A21,FIND("-",A21)-1) -> 19 | C21: =MID(A21,FIND("-",A21)+1,FIND("-",A21,FIND("-",A21)+1)-FIND("-",A21)-1) -> ENERO | D21: 45282 | E21: 45310 | F21: KEANCA | G21: =(E21-D21)*24 -> 672 | H21: MY MAGICAL MAN | I21: Artritis severa menudillo izquierdo delantero | J21: =_xlfn.XLOOKUP($I21,RazónMuerte!$A:$A,RazónMuerte!B:B,"",0) -> Enfermedad degenerativa articular | K21: =_xlfn.XLOOKUP($I21,RazónMuerte!$A:$A,RazónMuerte!C:C,"",0) -> 0 | L21: =_xlfn.XLOOKUP($I21,RazónMuerte!$A:$A,RazónMuerte!D:D,"",0) -> No fatal injury (chronic/medical)
A22: 20-ENERO-2024 | B22: =LEFT(A22,FIND("-",A22)-1) -> 20 | C22: =MID(A22,FIND("-",A22)+1,FIND("-",A22,FIND("-",A22)+1)-FIND("-",A22)-1) -> ENERO | E22: 45311 | F22: ALEXIS CARTAGENA | G22: =(E22-D22)*24 -> 1087464 | H22: NEPTUNO | I22: Colico | J22: =_xlfn.XLOOKUP($I22,RazónMuerte!$A:$A,RazónMuerte!B:B,"",0) -> Otras / No especificada | K22: =_xlfn.XLOOKUP($I22,RazónMuerte!$A:$A,RazónMuerte!C:C,"",0) -> 0 | L22: =_xlfn.XLOOKUP($I22,RazónMuerte!$A:$A,RazónMuerte!D:D,"",0) -> No clasificado
A23: 22-ENERO-2024 | B23: =LEFT(A23,FIND("-",A23)-1) -> 22 | C23: =MID(A23,FIND("-",A23)+1,FIND("-",A23,FIND("-",A23)+1)-FIND("-",A23)-1) -> ENERO | D23: 45240 | E23: 45313 | F23: SML | G23: =(E23-D23)*24 -> 1752 | H23: MY WAY OR ELSE | I23: Artritis septica (menudillo derecho delantero) | J23: =_xlfn.XLOOKUP($I23,RazónMuerte!$A:$A,RazónMuerte!B:B,"",0) -> Enfermedad degenerativa articular | K23: =_xlfn.XLOOKUP($I23,RazónMuerte!$A:$A,RazónMuerte!C:C,"",0) -> 0 | L23: =_xlfn.XLOOKUP($I23,RazónMuerte!$A:$A,RazónMuerte!D:D,"",0) -> No fatal injury (chronic/medical)
A24: 22-ENERO-2024 | B24: =LEFT(A24,FIND("-",A24)-1) -> 22 | C24: =MID(A24,FIND("-",A24)+1,FIND("-",A24,FIND("-",A24)+1)-FIND("-",A24)-1) -> ENERO | E24: 45313 | F24: SJ FARM | G24: =(E24-D24)*24 -> 1087512 | H24: NOICATTIRO | I24: Right front ankle fracture sesamoid. Laminitis of both hands can't walk or train. | J24: =_xlfn.XLOOKUP($I24,RazónMuerte!$A:$A,RazónMuerte!B:B,"",0) -> Fractura ósea | K24: =_xlfn.XLOOKUP($I24,RazónMuerte!$A:$A,RazónMuerte!C:C,"",0) -> Sesamoideo | L24: =_xlfn.XLOOKUP($I24,RazónMuerte!$A:$A,RazónMuerte!D:D,"",0) -> Fatal injury
A25: 22-ENERO-2024 | B25: =LEFT(A25,FIND("-",A25)-1) -> 22 | C25: =MID(A25,FIND("-",A25)+1,FIND("-",A25,FIND("-",A25)+1)-FIND("-",A25)-1) -> ENERO | D25: 45311 | E25: 45313 | F25: SACO E SAL | G25: =(E25-D25)*24 -> 48 | H25: REGINA ISABEL | I25: Fractura rodilla derecha | J25: =_xlfn.XLOOKUP($I25,RazónMuerte!$A:$A,RazónMuerte!B:B,"",0) -> Fractura ósea | K25: =_xlfn.XLOOKUP($I25,RazónMuerte!$A:$A,RazónMuerte!C:C,"",0) -> Rodilla / Carpal | L25: =_xlfn.XLOOKUP($I25,RazónMuerte!$A:$A,RazónMuerte!D:D,"",0) -> Fatal injury
A26: 26-ENERO-2024 | B26: =LEFT(A26,FIND("-",A26)-1) -> 26 | C26: =MID(A26,FIND("-",A26)+1,FIND("-",A26,FIND("-",A26)+1)-FIND("-",A26)-1) -> ENERO | D26: 45142 | E26: 45317 | F26: BROTHERS | G26: =(E26-D26)*24 -> 4200 | H26: PRESENTADOR | I26: Laminitis cronica. | J26: =_xlfn.XLOOKUP($I26,RazónMuerte!$A:$A,RazónMuerte!B:B,"",0) -> Otras / No especificada | K26: =_xlfn.XLOOKUP($I26,RazónMuerte!$A:$A,RazónMuerte!C:C,"",0) -> 0 | L26: =_xlfn.XLOOKUP($I26,RazónMuerte!$A:$A,RazónMuerte!D:D,"",0) -> No clasificado
A27: 31-ENERO-2024 | B27: =LEFT(A27,FIND("-",A27)-1) -> 31 | C27: =MID(A27,FIND("-",A27)+1,FIND("-",A27,FIND("-",A27)+1)-FIND("-",A27)-1) -> ENERO | D27: 45038 | E27: 45322 | F27: JF | G27: =(E27-D27)*24 -> 6816 | H27: MISTER PILOT | I27: Fractura Húmero | J27: =_xlfn.XLOOKUP($I27,RazónMuerte!$A:$A,RazónMuerte!B:B,"",0) -> Fractura ósea | K27: =_xlfn.XLOOKUP($I27,RazónMuerte!$A:$A,RazónMuerte!C:C,"",0) -> No especificado | L27: =_xlfn.XLOOKUP($I27,RazónMuerte!$A:$A,RazónMuerte!D:D,"",0) -> Fatal injury
A28: 2-FEBRERO-2024 | B28: =LEFT(A28,FIND("-",A28)-1) -> 2 | C28: =MID(A28,FIND("-",A28)+1,FIND("-",A28,FIND("-",A28)+1)-FIND("-",A28)-1) -> FEBRERO | D28: 45323 | E28: 45324 | F28: N Y N | G28: =(E28-D28)*24 -> 24 | H28: UNIFIED CONQUEST | I28: HERIDA PARTE POSTERIOR DEL MENUDILLO, CUARTILLA IZQUIERDA DELANTERA INCLUYENDO LA VAINA DEL TENDON | J28: =_xlfn.XLOOKUP($I28,RazónMuerte!$A:$A,RazónMuerte!B:B,"",0) -> Lesión de ligamentos/tendones | K28: =_xlfn.XLOOKUP($I28,RazónMuerte!$A:$A,RazónMuerte!C:C,"",0) -> 0 | L28: =_xlfn.XLOOKUP($I28,RazónMuerte!$A:$A,RazónMuerte!D:D,"",0) -> No clasificado
A29: 5-FEBRERO-2024 | B29: =LEFT(A29,FIND("-",A29)-1) -> 5 | C29: =MID(A29,FIND("-",A29)+1,FIND("-",A29,FIND("-",A29)+1)-FIND("-",A29)-1) -> FEBRERO | D29: 45130 | E29: 45327 | F29: ANGEL CALDERON | G29: =(E29-D29)*24 -> 4728 | H29: CYBERICA | I29: ARTRITIS SEVERA EN MENUDILLO DELANTERO. | J29: =_xlfn.XLOOKUP($I29,RazónMuerte!$A:$A,RazónMuerte!B:B,"",0) -> Enfermedad degenerativa articular | K29: =_xlfn.XLOOKUP($I29,RazónMuerte!$A:$A,RazónMuerte!C:C,"",0) -> 0 | L29: =_xlfn.XLOOKUP($I29,RazónMuerte!$A:$A,RazónMuerte!D:D,"",0) -> No fatal injury (chronic/medical)
A30: 7-FEBRERO-2024 | B30: =LEFT(A30,FIND("-",A30)-1) -> 7 | C30: =MID(A30,FIND("-",A30)+1,FIND("-",A30,FIND("-",A30)+1)-FIND("-",A30)-1) -> FEBRERO | D30: 45150 | E30: 45329 | F30: ROCHE KALIL | G30: =(E30-D30)*24 -> 4296 | H30: ERNESTO M | I30: COLICO & POOR BODY CONDITION. | J30: =_xlfn.XLOOKUP($I30,RazónMuerte!$A:$A,RazónMuerte!B:B,"",0) -> Otras / No especificada | K30: =_xlfn.XLOOKUP($I30,RazónMuerte!$A:$A,RazónMuerte!C:C,"",0) -> 0 | L30: =_xlfn.XLOOKUP($I30,RazónMuerte!$A:$A,RazónMuerte!D:D,"",0) -> No clasificado
A31: 7-FEBRERO-2024 | B31: =LEFT(A31,FIND("-",A31)-1) -> 7 | C31: =MID(A31,FIND("-",A31)+1,FIND("-",A31,FIND("-",A31)+1)-FIND("-",A31)-1) -> FEBRERO | D31: 45318 | E31: 45329 | F31: YORAM | G31: =(E31-D31)*24 -> 264 | H31: MINERA | I31: ARTRITIS SEVERA DERECHO DELANTERO | J31: =_xlfn.XLOOKUP($I31,RazónMuerte!$A:$A,RazónMuerte!B:B,"",0) -> Enfermedad degenerativa articular | K31: =_xlfn.XLOOKUP($I31,RazónMuerte!$A:$A,RazónMuerte!C:C,"",0) -> 0 | L31: =_xlfn.XLOOKUP($I31,RazónMuerte!$A:$A,RazónMuerte!D:D,"",0) -> No fatal injury (chronic/medical)
A32: 8-FEBRERO-2024 | B32: =LEFT(A32,FIND("-",A32)-1) -> 8 | C32: =MID(A32,FIND("-",A32)+1,FIND("-",A32,FIND("-",A32)+1)-FIND("-",A32)-1) -> FEBRERO | D32: 45325 | E32: 45330 | F32: CARMEN ANITA | G32: =(E32-D32)*24 -> 120 | H32: INDIAN SENSE | I32: ARTRITIS SEVERA | J32: =_xlfn.XLOOKUP($I32,RazónMuerte!$A:$A,RazónMuerte!B:B,"",0) -> Enfermedad degenerativa articular | K32: =_xlfn.XLOOKUP($I32,RazónMuerte!$A:$A,RazónMuerte!C:C,"",0) -> 0 | L32: =_xlfn.XLOOKUP($I32,RazónMuerte!$A:$A,RazónMuerte!D:D,"",0) -> No fatal injury (chronic/medical)
A33: 9-FEBRERO-2024 | B33: =LEFT(A33,FIND("-",A33)-1) -> 9 | C33: =MID(A33,FIND("-",A33)+1,FIND("-",A33,FIND("-",A33)+1)-FIND("-",A33)-1) -> FEBRERO | D33: 44896 | E33: 45331 | F33: LIDIEL | G33: =(E33-D33)*24 -> 10440 | H33: EL MONITOR | I33: Artritis severa menudillo izquierdo delantero | J33: =_xlfn.XLOOKUP($I33,RazónMuerte!$A:$A,RazónMuerte!B:B,"",0) -> Enfermedad degenerativa articular | K33: =_xlfn.XLOOKUP($I33,RazónMuerte!$A:$A,RazónMuerte!C:C,"",0) -> 0 | L33: =_xlfn.XLOOKUP($I33,RazónMuerte!$A:$A,RazónMuerte!D:D,"",0) -> No fatal injury (chronic/medical)
A34: 12-FEBRERO-2024 | B34: =LEFT(A34,FIND("-",A34)-1) -> 12 | C34: =MID(A34,FIND("-",A34)+1,FIND("-",A34,FIND("-",A34)+1)-FIND("-",A34)-1) -> FEBRERO | D34: 45332 | E34: 45334 | F34: V.G.O | G34: =(E34-D34)*24 -> 48 | H34: IAN P.R. | I34: FRACTURA AMBAS RODILLAS | J34: =_xlfn.XLOOKUP($I34,RazónMuerte!$A:$A,RazónMuerte!B:B,"",0) -> Fractura ósea | K34: =_xlfn.XLOOKUP($I34,RazónMuerte!$A:$A,RazónMuerte!C:C,"",0) -> Rodilla / Carpal | L34: =_xlfn.XLOOKUP($I34,RazónMuerte!$A:$A,RazónMuerte!D:D,"",0) -> Fatal injury
A35: 13-FEBRERO-2024 | B35: =LEFT(A35,FIND("-",A35)-1) -> 13 | C35: =MID(A35,FIND("-",A35)+1,FIND("-",A35,FIND("-",A35)+1)-FIND("-",A35)-1) -> FEBRERO | E35: 45335 | F35: CENTRAL | G35: =(E35-D35)*24 -> 1088040 | H35: EL TIO BOLO | I35: ARTRITIS SEVERA RODILLA IZQUIERDA | J35: =_xlfn.XLOOKUP($I35,RazónMuerte!$A:$A,RazónMuerte!B:B,"",0) -> Enfermedad degenerativa articular | K35: =_xlfn.XLOOKUP($I35,RazónMuerte!$A:$A,RazónMuerte!C:C,"",0) -> 0 | L35: =_xlfn.XLOOKUP($I35,RazónMuerte!$A:$A,RazónMuerte!D:D,"",0) -> Fatal injury
A36: 13-FEBRERO-2024 | B36: =LEFT(A36,FIND("-",A36)-1) -> 13 | C36: =MID(A36,FIND("-",A36)+1,FIND("-",A36,FIND("-",A36)+1)-FIND("-",A36)-1) -> FEBRERO | D36: 45324 | E36: 45335 | F36: DIVINO NINO | G36: =(E36-D36)*24 -> 264 | H36: EL MAPA | I36: TENDON BREAKDOWN RF LEG | J36: =_xlfn.XLOOKUP($I36,RazónMuerte!$A:$A,RazónMuerte!B:B,"",0) -> Lesión de ligamentos/tendones | K36: =_xlfn.XLOOKUP($I36,RazónMuerte!$A:$A,RazónMuerte!C:C,"",0) -> 0 | L36: =_xlfn.XLOOKUP($I36,RazónMuerte!$A:$A,RazónMuerte!D:D,"",0) -> No clasificado
A37: 13-FEBRERO-2024 | B37: =LEFT(A37,FIND("-",A37)-1) -> 13 | C37: =MID(A37,FIND("-",A37)+1,FIND("-",A37,FIND("-",A37)+1)-FIND("-",A37)-1) -> FEBRERO | D37: 45333 | E37: 45335 | F37: DESAFIO | G37: =(E37-D37)*24 -> 48 | H37: SPEEDY D | I37: FRACTURA SESAMOIDE PATA DERECHA DELANTERA | J37: =_xlfn.XLOOKUP($I37,RazónMuerte!$A:$A,RazónMuerte!B:B,"",0) -> Fractura ósea | K37: =_xlfn.XLOOKUP($I37,RazónMuerte!$A:$A,RazónMuerte!C:C,"",0) -> Sesamoideo | L37: =_xlfn.XLOOKUP($I37,RazónMuerte!$A:$A,RazónMuerte!D:D,"",0) -> Fatal injury
A38: 13-FEBRERO-2024 | B38: =LEFT(A38,FIND("-",A38)-1) -> 13 | C38: =MID(A38,FIND("-",A38)+1,FIND("-",A38,FIND("-",A38)+1)-FIND("-",A38)-1) -> FEBRERO | D38: 45292 | E38: 45335 | F38: ALAMO | G38: =(E38-D38)*24 -> 1032 | H38: CLEMENTE BORICUA | I38: FRACTURA AMBAS RODILLAS | J38: =_xlfn.XLOOKUP($I38,RazónMuerte!$A:$A,RazónMuerte!B:B,"",0) -> Fractura ósea | K38: =_xlfn.XLOOKUP($I38,RazónMuerte!$A:$A,RazónMuerte!C:C,"",0) -> Rodilla / Carpal | L38: =_xlfn.XLOOKUP($I38,RazónMuerte!$A:$A,RazónMuerte!D:D,"",0) -> Fatal injury
A39: 14-FEBRERO-2024 | B39: =LEFT(A39,FIND("-",A39)-1) -> 14 | C39: =MID(A39,FIND("-",A39)+1,FIND("-",A39,FIND("-",A39)+1)-FIND("-",A39)-1) -> FEBRERO | D39: 45305 | E39: 45336 | F39: SILENT | G39: =(E39-D39)*24 -> 744 | H39: RECOMPENSADO | I39: Artritis severa rodilla derecha | J39: =_xlfn.XLOOKUP($I39,RazónMuerte!$A:$A,RazónMuerte!B:B,"",0) -> Enfermedad degenerativa articular | K39: =_xlfn.XLOOKUP($I39,RazónMuerte!$A:$A,RazónMuerte!C:C,"",0) -> 0 | L39: =_xlfn.XLOOKUP($I39,RazónMuerte!$A:$A,RazónMuerte!D:D,"",0) -> Fatal injury
A40: 16-FEBRERO-2024 | B40: =LEFT(A40,FIND("-",A40)-1) -> 16 | C40: =MID(A40,FIND("-",A40)+1,FIND("-",A40,FIND("-",A40)+1)-FIND("-",A40)-1) -> FEBRERO | D40: 45337 | E40: 45338 | F40: DC | G40: =(E40-D40)*24 -> 24 | H40: EL DICTADOR | I40: Fractura sesamoide derecho delantero | J40: =_xlfn.XLOOKUP($I40,RazónMuerte!$A:$A,RazónMuerte!B:B,"",0) -> Fractura ósea | K40: =_xlfn.XLOOKUP($I40,RazónMuerte!$A:$A,RazónMuerte!C:C,"",0) -> Sesamoideo | L40: =_xlfn.XLOOKUP($I40,RazónMuerte!$A:$A,RazónMuerte!D:D,"",0) -> Fatal injury
A41: 16-FEBRERO-2024 | B41: =LEFT(A41,FIND("-",A41)-1) -> 16 | C41: =MID(A41,FIND("-",A41)+1,FIND("-",A41,FIND("-",A41)+1)-FIND("-",A41)-1) -> FEBRERO | E41: 45338 | F41: RAFANIL | G41: =(E41-D41)*24 -> 1088112 | H41: I'M YOUR LUV | I41: Aggressive eye cancer | J41: =_xlfn.XLOOKUP($I41,RazónMuerte!$A:$A,RazónMuerte!B:B,"",0) -> Otras / No especificada | K41: =_xlfn.XLOOKUP($I41,RazónMuerte!$A:$A,RazónMuerte!C:C,"",0) -> 0 | L41: =_xlfn.XLOOKUP($I41,RazónMuerte!$A:$A,RazónMuerte!D:D,"",0) -> No clasificado
A42: 19-FEBRERO-2024 | B42: =LEFT(A42,FIND("-",A42)-1) -> 19 | C42: =MID(A42,FIND("-",A42)+1,FIND("-",A42,FIND("-",A42)+1)-FIND("-",A42)-1) -> FEBRERO | D42: 45204 | E42: 45341 | F42: STUD JUNIOR V | G42: =(E42-D42)*24 -> 3288 | H42: DRA. ANA CAROLINA | I42: Tendón desgarrado pata izquierda trasera/ Laminitis pata derecha trasera | J42: =_xlfn.XLOOKUP($I42,RazónMuerte!$A:$A,RazónMuerte!B:B,"",0) -> Otras / No especificada | K42: =_xlfn.XLOOKUP($I42,RazónMuerte!$A:$A,RazónMuerte!C:C,"",0) -> 0 | L42: =_xlfn.XLOOKUP($I42,RazónMuerte!$A:$A,RazónMuerte!D:D,"",0) -> No clasificado
A43: 19-FEBRERO-2024 | B43: =LEFT(A43,FIND("-",A43)-1) -> 19 | C43: =MID(A43,FIND("-",A43)+1,FIND("-",A43,FIND("-",A43)+1)-FIND("-",A43)-1) -> FEBRERO | D43: 45241 | E43: 45341 | F43: HCDA BASILISA | G43: =(E43-D43)*24 -> 2400 | H43: CARTILLERO | I43: Fractura rodillas | J43: =_xlfn.XLOOKUP($I43,RazónMuerte!$A:$A,RazónMuerte!B:B,"",0) -> Fractura ósea | K43: =_xlfn.XLOOKUP($I43,RazónMuerte!$A:$A,RazónMuerte!C:C,"",0) -> Rodilla / Carpal | L43: =_xlfn.XLOOKUP($I43,RazónMuerte!$A:$A,RazónMuerte!D:D,"",0) -> Fatal injury
A44: 22-FEBRERO-2024 | B44: =LEFT(A44,FIND("-",A44)-1) -> 22 | C44: =MID(A44,FIND("-",A44)+1,FIND("-",A44,FIND("-",A44)+1)-FIND("-",A44)-1) -> FEBRERO | D44: 45318 | E44: 45344 | F44: R & R | G44: =(E44-D44)*24 -> 624 | H44: RAFA'S DREAM | I44: Fractura rodillas | J44: =_xlfn.XLOOKUP($I44,RazónMuerte!$A:$A,RazónMuerte!B:B,"",0) -> Fractura ósea | K44: =_xlfn.XLOOKUP($I44,RazónMuerte!$A:$A,RazónMuerte!C:C,"",0) -> Rodilla / Carpal | L44: =_xlfn.XLOOKUP($I44,RazónMuerte!$A:$A,RazónMuerte!D:D,"",0) -> Fatal injury
A45: 23-FEBRERO-2024 | B45: =LEFT(A45,FIND("-",A45)-1) -> 23 | C45: =MID(A45,FIND("-",A45)+1,FIND("-",A45,FIND("-",A45)+1)-FIND("-",A45)-1) -> FEBRERO | E45: 45345 | F45: MANUEL GOMEZ | G45: =(E45-D45)*24 -> 1088280 | H45: ARTIFICAL INTELL | I45: Referido Drs. PRHOA. LF Front severe DID Knee and fetlock smooth rest. Cannot train. | J45: =_xlfn.XLOOKUP($I45,RazónMuerte!$A:$A,RazónMuerte!B:B,"",0) -> Otras / No especificada | K45: =_xlfn.XLOOKUP($I45,RazónMuerte!$A:$A,RazónMuerte!C:C,"",0) -> 0 | L45: =_xlfn.XLOOKUP($I45,RazónMuerte!$A:$A,RazónMuerte!D:D,"",0) -> Fatal injury
A46: 24-FEBRERO-2024 | B46: =LEFT(A46,FIND("-",A46)-1) -> 24 | C46: =MID(A46,FIND("-",A46)+1,FIND("-",A46,FIND("-",A46)+1)-FIND("-",A46)-1) -> FEBRERO | D46: 45292 | E46: 45346 | F46: ARECIBO | G46: =(E46-D46)*24 -> 1296 | H46: QUALITY STRIKE | I46: Cólico | J46: =_xlfn.XLOOKUP($I46,RazónMuerte!$A:$A,RazónMuerte!B:B,"",0) -> Otras / No especificada | K46: =_xlfn.XLOOKUP($I46,RazónMuerte!$A:$A,RazónMuerte!C:C,"",0) -> 0 | L46: =_xlfn.XLOOKUP($I46,RazónMuerte!$A:$A,RazónMuerte!D:D,"",0) -> No clasificado
A47: 27-FEBRERO-2024 | B47: =LEFT(A47,FIND("-",A47)-1) -> 27 | C47: =MID(A47,FIND("-",A47)+1,FIND("-",A47,FIND("-",A47)+1)-FIND("-",A47)-1) -> FEBRERO | E47: 45349 | F47: FARO DE LUZ | G47: =(E47-D47)*24 -> 1088376 | H47: E.R.V. ENTERPISES | I47: Referido Drs. PRHOA. R Carpus. | J47: =_xlfn.XLOOKUP($I47,RazónMuerte!$A:$A,RazónMuerte!B:B,"",0) -> Otras / No especificada | K47: =_xlfn.XLOOKUP($I47,RazónMuerte!$A:$A,RazónMuerte!C:C,"",0) -> 0 | L47: =_xlfn.XLOOKUP($I47,RazónMuerte!$A:$A,RazónMuerte!D:D,"",0) -> No clasificado
A48: 27-FEBRERO-2024 | B48: =LEFT(A48,FIND("-",A48)-1) -> 27 | C48: =MID(A48,FIND("-",A48)+1,FIND("-",A48,FIND("-",A48)+1)-FIND("-",A48)-1) -> FEBRERO | E48: 45349 | F48: AQUINO | G48: =(E48-D48)*24 -> 1088376 | H48: ASANA 2022 | I48: Referido Drs. PRHOA. RF ankle fracture. Big piece of sesamoid with ligament. | J48: =_xlfn.XLOOKUP($I48,RazónMuerte!$A:$A,RazónMuerte!B:B,"",0) -> Fractura ósea | K48: =_xlfn.XLOOKUP($I48,RazónMuerte!$A:$A,RazónMuerte!C:C,"",0) -> Sesamoideo | L48: =_xlfn.XLOOKUP($I48,RazónMuerte!$A:$A,RazónMuerte!D:D,"",0) -> Fatal injury
A49: 1-MARZO-2024 | B49: =LEFT(A49,FIND("-",A49)-1) -> 1 | C49: =MID(A49,FIND("-",A49)+1,FIND("-",A49,FIND("-",A49)+1)-FIND("-",A49)-1) -> MARZO | D49: 45289 | E49: 45352 | F49: JAY'S | G49: =(E49-D49)*24 -> 1512 | H49: MARIO | I49: Referido Drs. PRHOA. Coyuntura infectada rodilla izquierda. | J49: =_xlfn.XLOOKUP($I49,RazónMuerte!$A:$A,RazónMuerte!B:B,"",0) -> Otras / No especificada | K49: =_xlfn.XLOOKUP($I49,RazónMuerte!$A:$A,RazónMuerte!C:C,"",0) -> 0 | L49: =_xlfn.XLOOKUP($I49,RazónMuerte!$A:$A,RazónMuerte!D:D,"",0) -> Fatal injury
A50: 4-MARZO-2024 | B50: =LEFT(A50,FIND("-",A50)-1) -> 4 | C50: =MID(A50,FIND("-",A50)+1,FIND("-",A50,FIND("-",A50)+1)-FIND("-",A50)-1) -> MARZO | D50: 45323 | E50: 45355 | F50: VALENTIN | G50: =(E50-D50)*24 -> 768 | H50: DAMA RADIANTE | I50: Fractura rodilla derecha. | J50: =_xlfn.XLOOKUP($I50,RazónMuerte!$A:$A,RazónMuerte!B:B,"",0) -> Fractura ósea | K50: =_xlfn.XLOOKUP($I50,RazónMuerte!$A:$A,RazónMuerte!C:C,"",0) -> Rodilla / Carpal | L50: =_xlfn.XLOOKUP($I50,RazónMuerte!$A:$A,RazónMuerte!D:D,"",0) -> Fatal injury
A51: 6-MARZO-2024 | B51: =LEFT(A51,FIND("-",A51)-1) -> 6 | C51: =MID(A51,FIND("-",A51)+1,FIND("-",A51,FIND("-",A51)+1)-FIND("-",A51)-1) -> MARZO | D51: 45330 | E51: 45357 | F51: ANTONELLA B | G51: =(E51-D51)*24 -> 648 | H51: DON PEDRO HG | I51: Referido Drs. PRHOA. Fractura sesamoide izquierdo delantero. | J51: =_xlfn.XLOOKUP($I51,RazónMuerte!$A:$A,RazónMuerte!B:B,"",0) -> Fractura ósea | K51: =_xlfn.XLOOKUP($I51,RazónMuerte!$A:$A,RazónMuerte!C:C,"",0) -> Sesamoideo | L51: =_xlfn.XLOOKUP($I51,RazónMuerte!$A:$A,RazónMuerte!D:D,"",0) -> Fatal injury
A52: 6-MARZO-2024 | B52: =LEFT(A52,FIND("-",A52)-1) -> 6 | C52: =MID(A52,FIND("-",A52)+1,FIND("-",A52,FIND("-",A52)+1)-FIND("-",A52)-1) -> MARZO | D52: 45186 | E52: 45357 | F52: SONATA | G52: =(E52-D52)*24 -> 4104 | H52: PURE SPEED | I52: Referido Drs. PRHOA. Cólico. | J52: =_xlfn.XLOOKUP($I52,RazónMuerte!$A:$A,RazónMuerte!B:B,"",0) -> Otras / No especificada | K52: =_xlfn.XLOOKUP($I52,RazónMuerte!$A:$A,RazónMuerte!C:C,"",0) -> 0 | L52: =_xlfn.XLOOKUP($I52,RazónMuerte!$A:$A,RazónMuerte!D:D,"",0) -> No clasificado
A53: 7-MARZO-2024 | B53: =LEFT(A53,FIND("-",A53)-1) -> 7 | C53: =MID(A53,FIND("-",A53)+1,FIND("-",A53,FIND("-",A53)+1)-FIND("-",A53)-1) -> MARZO | D53: 45150 | E53: 45358 | F53: RMV | G53: =(E53-D53)*24 -> 4992 | H53: MR. CORONEL | I53: Tendinitis crónica. | J53: =_xlfn.XLOOKUP($I53,RazónMuerte!$A:$A,RazónMuerte!B:B,"",0) -> Otras / No especificada | K53: =_xlfn.XLOOKUP($I53,RazónMuerte!$A:$A,RazónMuerte!C:C,"",0) -> 0 | L53: =_xlfn.XLOOKUP($I53,RazónMuerte!$A:$A,RazónMuerte!D:D,"",0) -> No clasificado
A54: 8-MARZO-2024 | B54: =LEFT(A54,FIND("-",A54)-1) -> 8 | C54: =MID(A54,FIND("-",A54)+1,FIND("-",A54,FIND("-",A54)+1)-FIND("-",A54)-1) -> MARZO | D54: 45347 | E54: 45359 | F54: LOS LLANOS | G54: =(E54-D54)*24 -> 288 | H54: ADVERSIDAD | I54: Degloving injury RH cannon bone. | J54: =_xlfn.XLOOKUP($I54,RazónMuerte!$A:$A,RazónMuerte!B:B,"",0) -> Otras / No especificada | K54: =_xlfn.XLOOKUP($I54,RazónMuerte!$A:$A,RazónMuerte!C:C,"",0) -> 0 | L54: =_xlfn.XLOOKUP($I54,RazónMuerte!$A:$A,RazónMuerte!D:D,"",0) -> Fatal injury
A55: 9-MARZO-2024 | B55: =LEFT(A55,FIND("-",A55)-1) -> 9 | C55: =MID(A55,FIND("-",A55)+1,FIND("-",A55,FIND("-",A55)+1)-FIND("-",A55)-1) -> MARZO | D55: 45345 | E55: 45360 | F55: JACKSON | G55: =(E55-D55)*24 -> 360 | H55: JOHNNY ON THE SPOT | I55: Fractura catastrófica caña derecha delantera. | J55: =_xlfn.XLOOKUP($I55,RazónMuerte!$A:$A,RazónMuerte!B:B,"",0) -> Fractura ósea | K55: =_xlfn.XLOOKUP($I55,RazónMuerte!$A:$A,RazónMuerte!C:C,"",0) -> Caña / Cannon bone | L55: =_xlfn.XLOOKUP($I55,RazónMuerte!$A:$A,RazónMuerte!D:D,"",0) -> Fatal injury
A56: 9-MARZO-2024 | B56: =LEFT(A56,FIND("-",A56)-1) -> 9 | C56: =MID(A56,FIND("-",A56)+1,FIND("-",A56,FIND("-",A56)+1)-FIND("-",A56)-1) -> MARZO | E56: 45360 | F56: DANSAI | G56: =(E56-D56)*24 -> 1088640 | H56: CHACORIN | I56: Fractura hombro izquierdo | J56: =_xlfn.XLOOKUP($I56,RazónMuerte!$A:$A,RazónMuerte!B:B,"",0) -> Fractura ósea | K56: =_xlfn.XLOOKUP($I56,RazónMuerte!$A:$A,RazónMuerte!C:C,"",0) -> No especificado | L56: =_xlfn.XLOOKUP($I56,RazónMuerte!$A:$A,RazónMuerte!D:D,"",0) -> Fatal injury
A57: 9-MARZO-2024 | B57: =LEFT(A57,FIND("-",A57)-1) -> 9 | C57: =MID(A57,FIND("-",A57)+1,FIND("-",A57,FIND("-",A57)+1)-FIND("-",A57)-1) -> MARZO | E57: 45360 | F57: RAMZ | G57: =(E57-D57)*24 -> 1088640 | H57: AMURALLADA | I57: Head Trauma | J57: =_xlfn.XLOOKUP($I57,RazónMuerte!$A:$A,RazónMuerte!B:B,"",0) -> Otras / No especificada | K57: =_xlfn.XLOOKUP($I57,RazónMuerte!$A:$A,RazónMuerte!C:C,"",0) -> 0 | L57: =_xlfn.XLOOKUP($I57,RazónMuerte!$A:$A,RazónMuerte!D:D,"",0) -> No clasificado
A58: 11-MARZO-2024 | B58: =LEFT(A58,FIND("-",A58)-1) -> 11 | C58: =MID(A58,FIND("-",A58)+1,FIND("-",A58,FIND("-",A58)+1)-FIND("-",A58)-1) -> MARZO | E58: 45362 | F58: ERV ENTERPRISES | G58: =(E58-D58)*24 -> 1088688 | H58: MIGHTY MISCHIEF | I58: Severe Laminitis | J58: =_xlfn.XLOOKUP($I58,RazónMuerte!$A:$A,RazónMuerte!B:B,"",0) -> Otras / No especificada | K58: =_xlfn.XLOOKUP($I58,RazónMuerte!$A:$A,RazónMuerte!C:C,"",0) -> 0 | L58: =_xlfn.XLOOKUP($I58,RazónMuerte!$A:$A,RazónMuerte!D:D,"",0) -> No clasificado
A59: 12-MARZO-2024 | B59: =LEFT(A59,FIND("-",A59)-1) -> 12 | C59: =MID(A59,FIND("-",A59)+1,FIND("-",A59,FIND("-",A59)+1)-FIND("-",A59)-1) -> MARZO | D59: 45360 | E59: 45363 | F59: CUMBA'S | G59: =(E59-D59)*24 -> 72 | H59: EL GRAN SEBAS | I59: Right Knee Slab Fracture | J59: =_xlfn.XLOOKUP($I59,RazónMuerte!$A:$A,RazónMuerte!B:B,"",0) -> Fractura ósea | K59: =_xlfn.XLOOKUP($I59,RazónMuerte!$A:$A,RazónMuerte!C:C,"",0) -> Slab | L59: =_xlfn.XLOOKUP($I59,RazónMuerte!$A:$A,RazónMuerte!D:D,"",0) -> Fatal injury
A60: 13-MARZO-2024 | B60: =LEFT(A60,FIND("-",A60)-1) -> 13 | C60: =MID(A60,FIND("-",A60)+1,FIND("-",A60,FIND("-",A60)+1)-FIND("-",A60)-1) -> MARZO | D60: 45359 | E60: 45364 | F60: THIAGO & YASIL | G60: =(E60-D60)*24 -> 120 | H60: EL TOPO | I60: Breakdown injury LF (menudillo izquierdo delantero) | J60: =_xlfn.XLOOKUP($I60,RazónMuerte!$A:$A,RazónMuerte!B:B,"",0) -> Otras / No especificada | K60: =_xlfn.XLOOKUP($I60,RazónMuerte!$A:$A,RazónMuerte!C:C,"",0) -> 0 | L60: =_xlfn.XLOOKUP($I60,RazónMuerte!$A:$A,RazónMuerte!D:D,"",0) -> No clasificado
A61: 15-MARZO-2024 | B61: =LEFT(A61,FIND("-",A61)-1) -> 15 | C61: =MID(A61,FIND("-",A61)+1,FIND("-",A61,FIND("-",A61)+1)-FIND("-",A61)-1) -> MARZO | D61: 45197 | E61: 45366 | F61: ERV ENTERPRISES | G61: =(E61-D61)*24 -> 4056 | H61: LADY ALEXANDRIA | I61: Dx Drs. PRHOA. Severe laminitis. | J61: =_xlfn.XLOOKUP($I61,RazónMuerte!$A:$A,RazónMuerte!B:B,"",0) -> Otras / No especificada | K61: =_xlfn.XLOOKUP($I61,RazónMuerte!$A:$A,RazónMuerte!C:C,"",0) -> 0 | L61: =_xlfn.XLOOKUP($I61,RazónMuerte!$A:$A,RazónMuerte!D:D,"",0) -> No clasificado
A62: 16-MARZO-2024 | B62: =LEFT(A62,FIND("-",A62)-1) -> 16 | C62: =MID(A62,FIND("-",A62)+1,FIND("-",A62,FIND("-",A62)+1)-FIND("-",A62)-1) -> MARZO | E62: 45367 | F62: BULLS FARM | G62: =(E62-D62)*24 -> 1088808 | H62: DREAMY | I62: Cólico | J62: =_xlfn.XLOOKUP($I62,RazónMuerte!$A:$A,RazónMuerte!B:B,"",0) -> Otras / No especificada | K62: =_xlfn.XLOOKUP($I62,RazónMuerte!$A:$A,RazónMuerte!C:C,"",0) -> 0 | L62: =_xlfn.XLOOKUP($I62,RazónMuerte!$A:$A,RazónMuerte!D:D,"",0) -> No clasificado
A63: 20-MARZO-2024 | B63: =LEFT(A63,FIND("-",A63)-1) -> 20 | C63: =MID(A63,FIND("-",A63)+1,FIND("-",A63,FIND("-",A63)+1)-FIND("-",A63)-1) -> MARZO | D63: 45368 | E63: 45371 | F63: VILLA REAL | G63: =(E63-D63)*24 -> 72 | H63: PRISIONERA | I63: Fractura caña izquierda delantera. Dueño rehusó tratamiento. | J63: =_xlfn.XLOOKUP($I63,RazónMuerte!$A:$A,RazónMuerte!B:B,"",0) -> Fractura ósea | K63: =_xlfn.XLOOKUP($I63,RazónMuerte!$A:$A,RazónMuerte!C:C,"",0) -> Caña / Cannon bone | L63: =_xlfn.XLOOKUP($I63,RazónMuerte!$A:$A,RazónMuerte!D:D,"",0) -> Fatal injury
A64: 27-MARZO-2024 | B64: =LEFT(A64,FIND("-",A64)-1) -> 27 | C64: =MID(A64,FIND("-",A64)+1,FIND("-",A64,FIND("-",A64)+1)-FIND("-",A64)-1) -> MARZO | D64: 45347 | E64: 45378 | F64: GRC | G64: =(E64-D64)*24 -> 744 | H64: WATER WAIKA | I64: Fractura rodilla izquierda. | J64: =_xlfn.XLOOKUP($I64,RazónMuerte!$A:$A,RazónMuerte!B:B,"",0) -> Fractura ósea | K64: =_xlfn.XLOOKUP($I64,RazónMuerte!$A:$A,RazónMuerte!C:C,"",0) -> Rodilla / Carpal | L64: =_xlfn.XLOOKUP($I64,RazónMuerte!$A:$A,RazónMuerte!D:D,"",0) -> Fatal injury
A65: 28-MARZO-2024 | B65: =LEFT(A65,FIND("-",A65)-1) -> 28 | C65: =MID(A65,FIND("-",A65)+1,FIND("-",A65,FIND("-",A65)+1)-FIND("-",A65)-1) -> MARZO | D65: 45365 | E65: 45379 | F65: UP | G65: =(E65-D65)*24 -> 336 | H65: HOLIS BRENDIS | I65: Fractura caña izquierda delantera. | J65: =_xlfn.XLOOKUP($I65,RazónMuerte!$A:$A,RazónMuerte!B:B,"",0) -> Fractura ósea | K65: =_xlfn.XLOOKUP($I65,RazónMuerte!$A:$A,RazónMuerte!C:C,"",0) -> Caña / Cannon bone | L65: =_xlfn.XLOOKUP($I65,RazónMuerte!$A:$A,RazónMuerte!D:D,"",0) -> Fatal injury
A66: 1-ABRIL-2024 | B66: =LEFT(A66,FIND("-",A66)-1) -> 1 | C66: =MID(A66,FIND("-",A66)+1,FIND("-",A66,FIND("-",A66)+1)-FIND("-",A66)-1) -> ABRIL | D66: 45341 | E66: 45383 | F66: HACIENDA DON KIKE | G66: =(E66-D66)*24 -> 1008 | H66: STRIKE LIGHT | I66: Fractura rodilla derecha (slab fracture of C3) | J66: =_xlfn.XLOOKUP($I66,RazónMuerte!$A:$A,RazónMuerte!B:B,"",0) -> Fractura ósea | K66: =_xlfn.XLOOKUP($I66,RazónMuerte!$A:$A,RazónMuerte!C:C,"",0) -> Slab | L66: =_xlfn.XLOOKUP($I66,RazónMuerte!$A:$A,RazónMuerte!D:D,"",0) -> Fatal injury
A67: 2-ABRIL-2024 | B67: =LEFT(A67,FIND("-",A67)-1) -> 2 | C67: =MID(A67,FIND("-",A67)+1,FIND("-",A67,FIND("-",A67)+1)-FIND("-",A67)-1) -> ABRIL | E67: 45384 | F67: UTUADO | G67: =(E67-D67)*24 -> 1089216 | H67: TENTADOR | I67: Fractura sesaomide y artritis menudillo derecho delantero | J67: =_xlfn.XLOOKUP($I67,RazónMuerte!$A:$A,RazónMuerte!B:B,"",0) -> Fractura ósea | K67: =_xlfn.XLOOKUP($I67,RazónMuerte!$A:$A,RazónMuerte!C:C,"",0) -> No especificado | L67: =_xlfn.XLOOKUP($I67,RazónMuerte!$A:$A,RazónMuerte!D:D,"",0) -> Fatal injury
A68: 2-ABRIL-2024 | B68: =LEFT(A68,FIND("-",A68)-1) -> 2 | C68: =MID(A68,FIND("-",A68)+1,FIND("-",A68,FIND("-",A68)+1)-FIND("-",A68)-1) -> ABRIL | E68: 45384 | F68: J.A.C. | G68: =(E68-D68)*24 -> 1089216 | H68: NIGHT PRINCESS 2022 | I68: Cólico severo (referido por Dr. Armand PRHOA) | J68: =_xlfn.XLOOKUP($I68,RazónMuerte!$A:$A,RazónMuerte!B:B,"",0) -> Otras / No especificada | K68: =_xlfn.XLOOKUP($I68,RazónMuerte!$A:$A,RazónMuerte!C:C,"",0) -> 0 | L68: =_xlfn.XLOOKUP($I68,RazónMuerte!$A:$A,RazónMuerte!D:D,"",0) -> No clasificado
A69: 2-ABRIL-2024 | B69: =LEFT(A69,FIND("-",A69)-1) -> 2 | C69: =MID(A69,FIND("-",A69)+1,FIND("-",A69,FIND("-",A69)+1)-FIND("-",A69)-1) -> ABRIL | D69: 45233 | E69: 45384 | F69: EL HERRERO | G69: =(E69-D69)*24 -> 3624 | H69: OUTFORARIDE | I69: Fractura y artritis de rodilla izquierda | J69: =_xlfn.XLOOKUP($I69,RazónMuerte!$A:$A,RazónMuerte!B:B,"",0) -> Fractura ósea | K69: =_xlfn.XLOOKUP($I69,RazónMuerte!$A:$A,RazónMuerte!C:C,"",0) -> Rodilla / Carpal | L69: =_xlfn.XLOOKUP($I69,RazónMuerte!$A:$A,RazónMuerte!D:D,"",0) -> Fatal injury
A70: 2-ABRIL-2024 | B70: =LEFT(A70,FIND("-",A70)-1) -> 2 | C70: =MID(A70,FIND("-",A70)+1,FIND("-",A70,FIND("-",A70)+1)-FIND("-",A70)-1) -> ABRIL | D70: 45381 | E70: 45384 | F70: RM | G70: =(E70-D70)*24 -> 72 | H70: EL BRAVO | I70: Fractura rodilla derecha | J70: =_xlfn.XLOOKUP($I70,RazónMuerte!$A:$A,RazónMuerte!B:B,"",0) -> Fractura ósea | K70: =_xlfn.XLOOKUP($I70,RazónMuerte!$A:$A,RazónMuerte!C:C,"",0) -> Rodilla / Carpal | L70: =_xlfn.XLOOKUP($I70,RazónMuerte!$A:$A,RazónMuerte!D:D,"",0) -> Fatal injury
A71: 2-ABRIL-2024 | B71: =LEFT(A71,FIND("-",A71)-1) -> 2 | C71: =MID(A71,FIND("-",A71)+1,FIND("-",A71,FIND("-",A71)+1)-FIND("-",A71)-1) -> ABRIL | E71: 45384 | F71: GARCIA | G71: =(E71-D71)*24 -> 1089216 | H71: INCLUDE ME | I71: Cólico (Nephrosplenic entrapment/Referido Dr. Armand PRHOA) | J71: =_xlfn.XLOOKUP($I71,RazónMuerte!$A:$A,RazónMuerte!B:B,"",0) -> Otras / No especificada | K71: =_xlfn.XLOOKUP($I71,RazónMuerte!$A:$A,RazónMuerte!C:C,"",0) -> 0 | L71: =_xlfn.XLOOKUP($I71,RazónMuerte!$A:$A,RazónMuerte!D:D,"",0) -> No clasificado
A72: 5-ABRIL-2024 | B72: =LEFT(A72,FIND("-",A72)-1) -> 5 | C72: =MID(A72,FIND("-",A72)+1,FIND("-",A72,FIND("-",A72)+1)-FIND("-",A72)-1) -> ABRIL | D72: 45296 | E72: 45387 | F72: VAGABUNDO | G72: =(E72-D72)*24 -> 2184 | H72: ALEGRIA ALEGRIA | I72: Múltiples fracturas rodillas + menudillos delanteros | J72: =_xlfn.XLOOKUP($I72,RazónMuerte!$A:$A,RazónMuerte!B:B,"",0) -> Fractura ósea | K72: =_xlfn.XLOOKUP($I72,RazónMuerte!$A:$A,RazónMuerte!C:C,"",0) -> Rodilla / Carpal | L72: =_xlfn.XLOOKUP($I72,RazónMuerte!$A:$A,RazónMuerte!D:D,"",0) -> Fatal injury
A73: 6-ABRIL-2024 | B73: =LEFT(A73,FIND("-",A73)-1) -> 6 | C73: =MID(A73,FIND("-",A73)+1,FIND("-",A73,FIND("-",A73)+1)-FIND("-",A73)-1) -> ABRIL | D73: 45388 | E73: 45388 | F73: NE | G73: =(E73-D73)*24 -> 0 | H73: CHOCO FACTOR | I73: RF Breakdown Injury. (PRHOA) | J73: =_xlfn.XLOOKUP($I73,RazónMuerte!$A:$A,RazónMuerte!B:B,"",0) -> Otras / No especificada | K73: =_xlfn.XLOOKUP($I73,RazónMuerte!$A:$A,RazónMuerte!C:C,"",0) -> 0 | L73: =_xlfn.XLOOKUP($I73,RazónMuerte!$A:$A,RazónMuerte!D:D,"",0) -> No clasificado
A74: 15-ABRIL-2024 | B74: =LEFT(A74,FIND("-",A74)-1) -> 15 | C74: =MID(A74,FIND("-",A74)+1,FIND("-",A74,FIND("-",A74)+1)-FIND("-",A74)-1) -> ABRIL | D74: 45394 | E74: 45397 | F74: RAMZ | G74: =(E74-D74)*24 -> 72 | H74: EMPRENDEDOR | I74: Fractura rodilla derecha | J74: =_xlfn.XLOOKUP($I74,RazónMuerte!$A:$A,RazónMuerte!B:B,"",0) -> Fractura ósea | K74: =_xlfn.XLOOKUP($I74,RazónMuerte!$A:$A,RazónMuerte!C:C,"",0) -> Rodilla / Carpal | L74: =_xlfn.XLOOKUP($I74,RazónMuerte!$A:$A,RazónMuerte!D:D,"",0) -> Fatal injury
A75: 19-ABRIL-2024 | B75: =LEFT(A75,FIND("-",A75)-1) -> 19 | C75: =MID(A75,FIND("-",A75)+1,FIND("-",A75,FIND("-",A75)+1)-FIND("-",A75)-1) -> ABRIL | D75: 45400 | E75: 45401 | F75: MATEO IGNACIO | G75: =(E75-D75)*24 -> 24 | H75: MR. ZACH | I75: Fractura caña izquierda delantera | J75: =_xlfn.XLOOKUP($I75,RazónMuerte!$A:$A,RazónMuerte!B:B,"",0) -> Fractura ósea | K75: =_xlfn.XLOOKUP($I75,RazónMuerte!$A:$A,RazónMuerte!C:C,"",0) -> Caña / Cannon bone | L75: =_xlfn.XLOOKUP($I75,RazónMuerte!$A:$A,RazónMuerte!D:D,"",0) -> Fatal injury
A76: 20-ABRIL-2024 | B76: =LEFT(A76,FIND("-",A76)-1) -> 20 | C76: =MID(A76,FIND("-",A76)+1,FIND("-",A76,FIND("-",A76)+1)-FIND("-",A76)-1) -> ABRIL | D76: 45136 | E76: 45402 | F76: JOSE LUIS | G76: =(E76-D76)*24 -> 6384 | H76: SR. EMMANUELLI | I76: Chronic tendinitis (both front limbs) | J76: =_xlfn.XLOOKUP($I76,RazónMuerte!$A:$A,RazónMuerte!B:B,"",0) -> Otras / No especificada | K76: =_xlfn.XLOOKUP($I76,RazónMuerte!$A:$A,RazónMuerte!C:C,"",0) -> 0 | L76: =_xlfn.XLOOKUP($I76,RazónMuerte!$A:$A,RazónMuerte!D:D,"",0) -> No fatal injury (chronic/medical)
A77: 23-ABRIL-2024 | B77: =LEFT(A77,FIND("-",A77)-1) -> 23 | C77: =MID(A77,FIND("-",A77)+1,FIND("-",A77,FIND("-",A77)+1)-FIND("-",A77)-1) -> ABRIL | D77: 45389 | E77: 45405 | F77: CRUZ FAMILY | G77: =(E77-D77)*24 -> 384 | H77: POKER COCO | I77: Chronic flexor tendinitis L front/R Carpal Fracture | J77: =_xlfn.XLOOKUP($I77,RazónMuerte!$A:$A,RazónMuerte!B:B,"",0) -> Fractura ósea | K77: =_xlfn.XLOOKUP($I77,RazónMuerte!$A:$A,RazónMuerte!C:C,"",0) -> Rodilla / Carpal | L77: =_xlfn.XLOOKUP($I77,RazónMuerte!$A:$A,RazónMuerte!D:D,"",0) -> Fatal injury
A78: 26-ABRIL-2024 | B78: =LEFT(A78,FIND("-",A78)-1) -> 26 | C78: =MID(A78,FIND("-",A78)+1,FIND("-",A78,FIND("-",A78)+1)-FIND("-",A78)-1) -> ABRIL | D78: 45351 | E78: 45408 | F78: R RACING | G78: =(E78-D78)*24 -> 1368 | H78: ORO NEGRO | I78: Fractura sesamoide izquierdo delantero y rodilla derecha | J78: =_xlfn.XLOOKUP($I78,RazónMuerte!$A:$A,RazónMuerte!B:B,"",0) -> Fractura ósea | K78: =_xlfn.XLOOKUP($I78,RazónMuerte!$A:$A,RazónMuerte!C:C,"",0) -> Rodilla / Carpal | L78: =_xlfn.XLOOKUP($I78,RazónMuerte!$A:$A,RazónMuerte!D:D,"",0) -> Fatal injury
A79: 27-ABRIL-2024 | B79: =LEFT(A79,FIND("-",A79)-1) -> 27 | C79: =MID(A79,FIND("-",A79)+1,FIND("-",A79,FIND("-",A79)+1)-FIND("-",A79)-1) -> ABRIL | D79: 45409 | E79: 45409 | F79: JBK | G79: =(E79-D79)*24 -> 0 | H79: HARLAN'S WAR | I79: Fractura sesamoide ambas patas delanteras durante la 3ra carrera. PRHOA. | J79: =_xlfn.XLOOKUP($I79,RazónMuerte!$A:$A,RazónMuerte!B:B,"",0) -> Fractura ósea | K79: =_xlfn.XLOOKUP($I79,RazónMuerte!$A:$A,RazónMuerte!C:C,"",0) -> Sesamoideo | L79: =_xlfn.XLOOKUP($I79,RazónMuerte!$A:$A,RazónMuerte!D:D,"",0) -> Fatal injury
A80: 29-ABRIL-2024 | B80: =LEFT(A80,FIND("-",A80)-1) -> 29 | C80: =MID(A80,FIND("-",A80)+1,FIND("-",A80,FIND("-",A80)+1)-FIND("-",A80)-1) -> ABRIL | E80: 45411 | F80: CUTTY | G80: =(E80-D80)*24 -> 1089864 | H80: BIG RINNIE | I80: Fractura rodilla derecha | J80: =_xlfn.XLOOKUP($I80,RazónMuerte!$A:$A,RazónMuerte!B:B,"",0) -> Fractura ósea | K80: =_xlfn.XLOOKUP($I80,RazónMuerte!$A:$A,RazónMuerte!C:C,"",0) -> Rodilla / Carpal | L80: =_xlfn.XLOOKUP($I80,RazónMuerte!$A:$A,RazónMuerte!D:D,"",0) -> Fatal injury
A81: 1-MAYO-2024 | B81: =LEFT(A81,FIND("-",A81)-1) -> 1 | C81: =MID(A81,FIND("-",A81)+1,FIND("-",A81,FIND("-",A81)+1)-FIND("-",A81)-1) -> MAYO | E81: 45413 | F81: SONATA | G81: =(E81-D81)*24 -> 1089912 | H81: ARGUMENTO | I81: Pleuroneumonía. Referido Drs PRHOA. | J81: =_xlfn.XLOOKUP($I81,RazónMuerte!$A:$A,RazónMuerte!B:B,"",0) -> Otras / No especificada | K81: =_xlfn.XLOOKUP($I81,RazónMuerte!$A:$A,RazónMuerte!C:C,"",0) -> 0 | L81: =_xlfn.XLOOKUP($I81,RazónMuerte!$A:$A,RazónMuerte!D:D,"",0) -> No clasificado
A82: 1-MAYO-2024 | B82: =LEFT(A82,FIND("-",A82)-1) -> 1 | C82: =MID(A82,FIND("-",A82)+1,FIND("-",A82,FIND("-",A82)+1)-FIND("-",A82)-1) -> MAYO | D82: 45396 | E82: 45413 | F82: LA CAMPIÑA | G82: =(E82-D82)*24 -> 408 | H82: RAIZ | I82: Fractura del húmero derecho. Accidente en la pista. | J82: =_xlfn.XLOOKUP($I82,RazónMuerte!$A:$A,RazónMuerte!B:B,"",0) -> Fractura ósea | K82: =_xlfn.XLOOKUP($I82,RazónMuerte!$A:$A,RazónMuerte!C:C,"",0) -> No especificado | L82: =_xlfn.XLOOKUP($I82,RazónMuerte!$A:$A,RazónMuerte!D:D,"",0) -> Fatal injury
A83: 1-MAYO-2024 | B83: =LEFT(A83,FIND("-",A83)-1) -> 1 | C83: =MID(A83,FIND("-",A83)+1,FIND("-",A83,FIND("-",A83)+1)-FIND("-",A83)-1) -> MAYO | D83: 45375 | E83: 45413 | F83: THE COACH | G83: =(E83-D83)*24 -> 912 | H83: VIDA REAL | I83: Fractura y artritis rodilla derecha derecha. Referido Drs PRHOA. | J83: =_xlfn.XLOOKUP($I83,RazónMuerte!$A:$A,RazónMuerte!B:B,"",0) -> Fractura ósea | K83: =_xlfn.XLOOKUP($I83,RazónMuerte!$A:$A,RazónMuerte!C:C,"",0) -> Rodilla / Carpal | L83: =_xlfn.XLOOKUP($I83,RazónMuerte!$A:$A,RazónMuerte!D:D,"",0) -> Fatal injury
A84: 3-MAYO-2024 | B84: =LEFT(A84,FIND("-",A84)-1) -> 3 | C84: =MID(A84,FIND("-",A84)+1,FIND("-",A84,FIND("-",A84)+1)-FIND("-",A84)-1) -> MAYO | D84: 45414 | E84: 45415 | F84: LOUISIANA | G84: =(E84-D84)*24 -> 24 | H84: COLISEO | I84: Tendinitis crónica en ambas patas delanteras. | J84: =_xlfn.XLOOKUP($I84,RazónMuerte!$A:$A,RazónMuerte!B:B,"",0) -> Otras / No especificada | K84: =_xlfn.XLOOKUP($I84,RazónMuerte!$A:$A,RazónMuerte!C:C,"",0) -> 0 | L84: =_xlfn.XLOOKUP($I84,RazónMuerte!$A:$A,RazónMuerte!D:D,"",0) -> No clasificado
A85: 4-MAYO-2024 | B85: =LEFT(A85,FIND("-",A85)-1) -> 4 | C85: =MID(A85,FIND("-",A85)+1,FIND("-",A85,FIND("-",A85)+1)-FIND("-",A85)-1) -> MAYO | D85: 45158 | E85: 45416 | F85: VALE-MAR | G85: =(E85-D85)*24 -> 6192 | H85: TABARDILLO | I85: Breakdown injury LF leg with tissue necrosy. Referido Dr. García Blanco. | J85: =_xlfn.XLOOKUP($I85,RazónMuerte!$A:$A,RazónMuerte!B:B,"",0) -> Otras / No especificada | K85: =_xlfn.XLOOKUP($I85,RazónMuerte!$A:$A,RazónMuerte!C:C,"",0) -> 0 | L85: =_xlfn.XLOOKUP($I85,RazónMuerte!$A:$A,RazónMuerte!D:D,"",0) -> No clasificado
A86: 6-MAYO-2024 | B86: =LEFT(A86,FIND("-",A86)-1) -> 6 | C86: =MID(A86,FIND("-",A86)+1,FIND("-",A86,FIND("-",A86)+1)-FIND("-",A86)-1) -> MAYO | E86: 45418 | F86: ERA RACING | G86: =(E86-D86)*24 -> 1090032 | H86: VUELVE RAY Q | I86: LF dorsal cortical MCIII fracture. Referido Drs. PRHOA. | J86: =_xlfn.XLOOKUP($I86,RazónMuerte!$A:$A,RazónMuerte!B:B,"",0) -> Fractura ósea | K86: =_xlfn.XLOOKUP($I86,RazónMuerte!$A:$A,RazónMuerte!C:C,"",0) -> No especificado | L86: =_xlfn.XLOOKUP($I86,RazónMuerte!$A:$A,RazónMuerte!D:D,"",0) -> Fatal injury
A87: 6-MAYO-2024 | B87: =LEFT(A87,FIND("-",A87)-1) -> 6 | C87: =MID(A87,FIND("-",A87)+1,FIND("-",A87,FIND("-",A87)+1)-FIND("-",A87)-1) -> MAYO | D87: 45401 | E87: 45418 | F87: GCA | G87: =(E87-D87)*24 -> 408 | H87: DULCE MELODIA | I87: Laminitis casco derecho/ Fractura rodilla derecha. | J87: =_xlfn.XLOOKUP($I87,RazónMuerte!$A:$A,RazónMuerte!B:B,"",0) -> Fractura ósea | K87: =_xlfn.XLOOKUP($I87,RazónMuerte!$A:$A,RazónMuerte!C:C,"",0) -> Rodilla / Carpal | L87: =_xlfn.XLOOKUP($I87,RazónMuerte!$A:$A,RazónMuerte!D:D,"",0) -> Fatal injury
A88: 7-MAYO-2024 | B88: =LEFT(A88,FIND("-",A88)-1) -> 7 | C88: =MID(A88,FIND("-",A88)+1,FIND("-",A88,FIND("-",A88)+1)-FIND("-",A88)-1) -> MAYO | D88: 45337 | E88: 45419 | F88: AJ DAVILA | G88: =(E88-D88)*24 -> 1968 | H88: JUVENILIA | I88: Artritis y coyuntura séptica (corvejón derecho) | J88: =_xlfn.XLOOKUP($I88,RazónMuerte!$A:$A,RazónMuerte!B:B,"",0) -> Enfermedad degenerativa articular | K88: =_xlfn.XLOOKUP($I88,RazónMuerte!$A:$A,RazónMuerte!C:C,"",0) -> 0 | L88: =_xlfn.XLOOKUP($I88,RazónMuerte!$A:$A,RazónMuerte!D:D,"",0) -> No fatal injury (chronic/medical)
A89: 7-MAYO-2024 | B89: =LEFT(A89,FIND("-",A89)-1) -> 7 | C89: =MID(A89,FIND("-",A89)+1,FIND("-",A89,FIND("-",A89)+1)-FIND("-",A89)-1) -> MAYO | D89: 45409 | E89: 45419 | F89: MATTA | G89: =(E89-D89)*24 -> 240 | H89: DREAM LEAPER | I89: Fractura ambas cañas delanteras | J89: =_xlfn.XLOOKUP($I89,RazónMuerte!$A:$A,RazónMuerte!B:B,"",0) -> Fractura ósea | K89: =_xlfn.XLOOKUP($I89,RazónMuerte!$A:$A,RazónMuerte!C:C,"",0) -> Caña / Cannon bone | L89: =_xlfn.XLOOKUP($I89,RazónMuerte!$A:$A,RazónMuerte!D:D,"",0) -> Fatal injury
A90: 7-MAYO-2024 | B90: =LEFT(A90,FIND("-",A90)-1) -> 7 | C90: =MID(A90,FIND("-",A90)+1,FIND("-",A90,FIND("-",A90)+1)-FIND("-",A90)-1) -> MAYO | D90: 45416 | E90: 45419 | F90: AMBERT L | G90: =(E90-D90)*24 -> 72 | H90: MISS RIOJA | I90: Artritis rodilla derecha | J90: =_xlfn.XLOOKUP($I90,RazónMuerte!$A:$A,RazónMuerte!B:B,"",0) -> Enfermedad degenerativa articular | K90: =_xlfn.XLOOKUP($I90,RazónMuerte!$A:$A,RazónMuerte!C:C,"",0) -> 0 | L90: =_xlfn.XLOOKUP($I90,RazónMuerte!$A:$A,RazónMuerte!D:D,"",0) -> Fatal injury
A91: 10-MAYO-2024 | B91: =LEFT(A91,FIND("-",A91)-1) -> 10 | C91: =MID(A91,FIND("-",A91)+1,FIND("-",A91,FIND("-",A91)+1)-FIND("-",A91)-1) -> MAYO | D91: 45416 | E91: 45422 | F91: FRANCHELY | G91: =(E91-D91)*24 -> 144 | H91: PROTOTIPO | I91: Breakdown injury (base sesamoid fracture). | J91: =_xlfn.XLOOKUP($I91,RazónMuerte!$A:$A,RazónMuerte!B:B,"",0) -> Fractura ósea | K91: =_xlfn.XLOOKUP($I91,RazónMuerte!$A:$A,RazónMuerte!C:C,"",0) -> Sesamoideo | L91: =_xlfn.XLOOKUP($I91,RazónMuerte!$A:$A,RazónMuerte!D:D,"",0) -> Fatal injury
A92: 10-MAYO-2024 | B92: =LEFT(A92,FIND("-",A92)-1) -> 10 | C92: =MID(A92,FIND("-",A92)+1,FIND("-",A92,FIND("-",A92)+1)-FIND("-",A92)-1) -> MAYO | D92: 45421 | E92: 45422 | F92: BELLEZA | G92: =(E92-D92)*24 -> 24 | H92: MAN ICE | I92: Fractura sesamoide pata izquierda delantera. | J92: =_xlfn.XLOOKUP($I92,RazónMuerte!$A:$A,RazónMuerte!B:B,"",0) -> Fractura ósea | K92: =_xlfn.XLOOKUP($I92,RazónMuerte!$A:$A,RazónMuerte!C:C,"",0) -> Sesamoideo | L92: =_xlfn.XLOOKUP($I92,RazónMuerte!$A:$A,RazónMuerte!D:D,"",0) -> Fatal injury
A93: 11-MAYO-2024 | B93: =LEFT(A93,FIND("-",A93)-1) -> 11 | C93: =MID(A93,FIND("-",A93)+1,FIND("-",A93,FIND("-",A93)+1)-FIND("-",A93)-1) -> MAYO | D93: 45421 | E93: 45423 | F93: FC | G93: =(E93-D93)*24 -> 48 | H93: CLEVER ALLIANCE | I93: Fractura rodilla derecha | J93: =_xlfn.XLOOKUP($I93,RazónMuerte!$A:$A,RazónMuerte!B:B,"",0) -> Fractura ósea | K93: =_xlfn.XLOOKUP($I93,RazónMuerte!$A:$A,RazónMuerte!C:C,"",0) -> Rodilla / Carpal | L93: =_xlfn.XLOOKUP($I93,RazónMuerte!$A:$A,RazónMuerte!D:D,"",0) -> Fatal injury
A94: 11-MAYO-2024 | B94: =LEFT(A94,FIND("-",A94)-1) -> 11 | C94: =MID(A94,FIND("-",A94)+1,FIND("-",A94,FIND("-",A94)+1)-FIND("-",A94)-1) -> MAYO | D94: 45422 | E94: 45423 | F94: GUILLERMO BERRIOS | G94: =(E94-D94)*24 -> 24 | H94: MY FAVORITE STAR | I94: Múltiples fracturas; DJD severo después de cirugía. No pudo terminar carrera. Referido Drs. PRHOA. | J94: =_xlfn.XLOOKUP($I94,RazónMuerte!$A:$A,RazónMuerte!B:B,"",0) -> Fractura ósea | K94: =_xlfn.XLOOKUP($I94,RazónMuerte!$A:$A,RazónMuerte!C:C,"",0) -> No especificado | L94: =_xlfn.XLOOKUP($I94,RazónMuerte!$A:$A,RazónMuerte!D:D,"",0) -> Fatal injury
A95: 11-MAYO-2024 | B95: =LEFT(A95,FIND("-",A95)-1) -> 11 | C95: =MID(A95,FIND("-",A95)+1,FIND("-",A95,FIND("-",A95)+1)-FIND("-",A95)-1) -> MAYO | D95: 45346 | E95: 45423 | F95: REAL STAR | G95: =(E95-D95)*24 -> 1848 | H95: HATCHET JACK | I95: Breakdown injury LF + bilateral sesamoid fractures. | J95: =_xlfn.XLOOKUP($I95,RazónMuerte!$A:$A,RazónMuerte!B:B,"",0) -> Fractura ósea | K95: =_xlfn.XLOOKUP($I95,RazónMuerte!$A:$A,RazónMuerte!C:C,"",0) -> Sesamoideo | L95: =_xlfn.XLOOKUP($I95,RazónMuerte!$A:$A,RazónMuerte!D:D,"",0) -> Fatal injury
A96: 15-MAYO-2024 | B96: =LEFT(A96,FIND("-",A96)-1) -> 15 | C96: =MID(A96,FIND("-",A96)+1,FIND("-",A96,FIND("-",A96)+1)-FIND("-",A96)-1) -> MAYO | D96: 45368 | E96: 45427 | F96: MI SUEÑO | G96: =(E96-D96)*24 -> 1416 | H96: MI QUERIDA FLACA | I96: Fractura rodilla derecha | J96: =_xlfn.XLOOKUP($I96,RazónMuerte!$A:$A,RazónMuerte!B:B,"",0) -> Fractura ósea | K96: =_xlfn.XLOOKUP($I96,RazónMuerte!$A:$A,RazónMuerte!C:C,"",0) -> Rodilla / Carpal | L96: =_xlfn.XLOOKUP($I96,RazónMuerte!$A:$A,RazónMuerte!D:D,"",0) -> Fatal injury
A97: 15-MAYO-2024 | B97: =LEFT(A97,FIND("-",A97)-1) -> 15 | C97: =MID(A97,FIND("-",A97)+1,FIND("-",A97,FIND("-",A97)+1)-FIND("-",A97)-1) -> MAYO | D97: 45262 | E97: 45427 | F97: HG | G97: =(E97-D97)*24 -> 3960 | H97: SURF SPA | I97: Multiple chip fractures intercarpal joint, severe DJD, 4/5 lameness, infected accesory carpal area. Referido Drs. PRHOA. | J97: =_xlfn.XLOOKUP($I97,RazónMuerte!$A:$A,RazónMuerte!B:B,"",0) -> Fractura ósea | K97: =_xlfn.XLOOKUP($I97,RazónMuerte!$A:$A,RazónMuerte!C:C,"",0) -> Rodilla / Carpal | L97: =_xlfn.XLOOKUP($I97,RazónMuerte!$A:$A,RazónMuerte!D:D,"",0) -> Fatal injury
A98: 17-MAYO-2024 | B98: =LEFT(A98,FIND("-",A98)-1) -> 17 | C98: =MID(A98,FIND("-",A98)+1,FIND("-",A98,FIND("-",A98)+1)-FIND("-",A98)-1) -> MAYO | D98: 45402 | E98: 45429 | F98: R RACING | G98: =(E98-D98)*24 -> 648 | H98: MI FASCINACION | I98: Sesamoide medial derecho delantero | J98: =_xlfn.XLOOKUP($I98,RazónMuerte!$A:$A,RazónMuerte!B:B,"",0) -> Otras / No especificada | K98: =_xlfn.XLOOKUP($I98,RazónMuerte!$A:$A,RazónMuerte!C:C,"",0) -> 0 | L98: =_xlfn.XLOOKUP($I98,RazónMuerte!$A:$A,RazónMuerte!D:D,"",0) -> Fatal injury
A99: 17-MAYO-2024 | B99: =LEFT(A99,FIND("-",A99)-1) -> 17 | C99: =MID(A99,FIND("-",A99)+1,FIND("-",A99,FIND("-",A99)+1)-FIND("-",A99)-1) -> MAYO | D99: 45407 | E99: 45429 | F99: ALAMO | G99: =(E99-D99)*24 -> 528 | H99: DON MARTIN DE LEON | I99: Fractura rodilla derecha | J99: =_xlfn.XLOOKUP($I99,RazónMuerte!$A:$A,RazónMuerte!B:B,"",0) -> Fractura ósea | K99: =_xlfn.XLOOKUP($I99,RazónMuerte!$A:$A,RazónMuerte!C:C,"",0) -> Rodilla / Carpal | L99: =_xlfn.XLOOKUP($I99,RazónMuerte!$A:$A,RazónMuerte!D:D,"",0) -> Fatal injury
A100: 17-MAYO-2024 | B100: =LEFT(A100,FIND("-",A100)-1) -> 17 | C100: =MID(A100,FIND("-",A100)+1,FIND("-",A100,FIND("-",A100)+1)-FIND("-",A100)-1) -> MAYO | E100: 45429 | F100: TORRES PAGAN | G100: =(E100-D100)*24 -> 1090296 | H100: ALUMINIO | I100: Laminitis (all four limbs) | J100: =_xlfn.XLOOKUP($I100,RazónMuerte!$A:$A,RazónMuerte!B:B,"",0) -> Otras / No especificada | K100: =_xlfn.XLOOKUP($I100,RazónMuerte!$A:$A,RazónMuerte!C:C,"",0) -> 0 | L100: =_xlfn.XLOOKUP($I100,RazónMuerte!$A:$A,RazónMuerte!D:D,"",0) -> No clasificado
...

Sheet 2025 data
A1: FECHA | B1: día | C1: Mes | D1: Last Race Date (desde Equibase) | E1: Death Date | F1: ESTABLO | G1: Horas transcurridas | H1: CABALLO | I1: RAZON | J1: Categoría | K1: Tipo de fractura | L1: Fatal injury | M1: Registrado/Compitió?
A2: 12-MARZO-2025 | B2: =LEFT(A2,FIND("-",A2)-1) -> 12 | C2: =MID(A2,FIND("-",A2)+1,FIND("-",A2,FIND("-",A2)+1)-FIND("-",A2)-1) -> MARZO | D2: 42910 | E2: 45728 | F2: CTA | G2: 67632 | H2: CRUISES CREEK | I2: Cólico. Colon desplazado. | J2: =_xlfn.XLOOKUP($I2,RazónMuerte!$A:$A,RazónMuerte!B:B,"",0) -> Otras / No especificada | K2: =_xlfn.XLOOKUP($I2,RazónMuerte!$A:$A,RazónMuerte!C:C,"",0) -> 0 | L2: =_xlfn.XLOOKUP($I2,RazónMuerte!$A:$A,RazónMuerte!D:D,"",0) -> No clasificado | M2: Si
A3: 31-OCTUBRE-2025 | B3: =LEFT(A3,FIND("-",A3)-1) -> 31 | C3: =MID(A3,FIND("-",A3)+1,FIND("-",A3,FIND("-",A3)+1)-FIND("-",A3)-1) -> OCTUBRE | D3: 45169 | E3: 45961 | F3: SONATA | G3: 19008 | H3: TEMPORERA | I3: LAMINITIS CRONICA | J3: =_xlfn.XLOOKUP($I3,RazónMuerte!$A:$A,RazónMuerte!B:B,"",0) -> Otras / No especificada | K3: =_xlfn.XLOOKUP($I3,RazónMuerte!$A:$A,RazónMuerte!C:C,"",0) -> 0 | L3: =_xlfn.XLOOKUP($I3,RazónMuerte!$A:$A,RazónMuerte!D:D,"",0) -> No clasificado | M3: Si
A4: 13-AGOSTO-2025 | B4: =LEFT(A4,FIND("-",A4)-1) -> 13 | C4: =MID(A4,FIND("-",A4)+1,FIND("-",A4,FIND("-",A4)+1)-FIND("-",A4)-1) -> AGOSTO | D4: 45227 | E4: 45882 | F4: JI DIAMOND | G4: 15720 | H4: EL GALLOLFO | I4: Laminitis en ambas manos/Múltiples fracturas en ambas rodillas L>R. | J4: =_xlfn.XLOOKUP($I4,RazónMuerte!$A:$A,RazónMuerte!B:B,"",0) -> Fractura ósea | K4: =_xlfn.XLOOKUP($I4,RazónMuerte!$A:$A,RazónMuerte!C:C,"",0) -> Rodilla / Carpal | L4: =_xlfn.XLOOKUP($I4,RazónMuerte!$A:$A,RazónMuerte!D:D,"",0) -> Fatal injury | M4: Si
A5: 15-SEPTIEMBRE-2025 | B5: =LEFT(A5,FIND("-",A5)-1) -> 15 | C5: =MID(A5,FIND("-",A5)+1,FIND("-",A5,FIND("-",A5)+1)-FIND("-",A5)-1) -> SEPTIEMBRE | D5: 45326 | E5: 45915 | F5: G.C.A. | G5: 14136 | H5: MASTERY ASHLEY JHU | I5: Chronic infected wound on medial aspect of L front fetlock. | J5: =_xlfn.XLOOKUP($I5,RazónMuerte!$A:$A,RazónMuerte!B:B,"",0) -> Otras / No especificada | K5: =_xlfn.XLOOKUP($I5,RazónMuerte!$A:$A,RazónMuerte!C:C,"",0) -> 0 | L5: =_xlfn.XLOOKUP($I5,RazónMuerte!$A:$A,RazónMuerte!D:D,"",0) -> Fatal injury | M5: Si
A6: 28-JULIO-2025 | B6: =LEFT(A6,FIND("-",A6)-1) -> 28 | C6: =MID(A6,FIND("-",A6)+1,FIND("-",A6,FIND("-",A6)+1)-FIND("-",A6)-1) -> JULIO | D6: 45345 | E6: 45866 | F6: CANITO | G6: 12504 | H6: CONSULADO | I6: Cólico. | J6: =_xlfn.XLOOKUP($I6,RazónMuerte!$A:$A,RazónMuerte!B:B,"",0) -> Otras / No especificada | K6: =_xlfn.XLOOKUP($I6,RazónMuerte!$A:$A,RazónMuerte!C:C,"",0) -> 0 | L6: =_xlfn.XLOOKUP($I6,RazónMuerte!$A:$A,RazónMuerte!D:D,"",0) -> No clasificado | M6: Si
A7: 15-JULIO-2025 | B7: =LEFT(A7,FIND("-",A7)-1) -> 15 | C7: =MID(A7,FIND("-",A7)+1,FIND("-",A7,FIND("-",A7)+1)-FIND("-",A7)-1) -> JULIO | D7: 45402 | E7: 45853 | F7: E.R.V. ENTERPRISES | G7: 10824 | H7: ÁGUILA BLANCA | I7: Severe tenosynovitis of RF limb (Referido PRHOA) | J7: =_xlfn.XLOOKUP($I7,RazónMuerte!$A:$A,RazónMuerte!B:B,"",0) -> Otras / No especificada | K7: =_xlfn.XLOOKUP($I7,RazónMuerte!$A:$A,RazónMuerte!C:C,"",0) -> 0 | L7: =_xlfn.XLOOKUP($I7,RazónMuerte!$A:$A,RazónMuerte!D:D,"",0) -> No clasificado | M7: Si
A8: 13-AGOSTO-2025 | B8: =LEFT(A8,FIND("-",A8)-1) -> 13 | C8: =MID(A8,FIND("-",A8)+1,FIND("-",A8,FIND("-",A8)+1)-FIND("-",A8)-1) -> AGOSTO | D8: 45416 | E8: 45882 | F8: JI DIAMOND | G8: 11184 | H8: BLACK SILK | I8: Fractura rodilla izquierda. | J8: =_xlfn.XLOOKUP($I8,RazónMuerte!$A:$A,RazónMuerte!B:B,"",0) -> Fractura ósea | K8: =_xlfn.XLOOKUP($I8,RazónMuerte!$A:$A,RazónMuerte!C:C,"",0) -> Rodilla / Carpal | L8: =_xlfn.XLOOKUP($I8,RazónMuerte!$A:$A,RazónMuerte!D:D,"",0) -> Fatal injury | M8: Si
A9: 18-FEBRERO-2025 | B9: =LEFT(A9,FIND("-",A9)-1) -> 18 | C9: =MID(A9,FIND("-",A9)+1,FIND("-",A9,FIND("-",A9)+1)-FIND("-",A9)-1) -> FEBRERO | D9: 45507 | E9: 45706 | F9: MRJP | G9: 4776 | H9: TWEET THIS | I9: Bilateral laminitis. Fetlock severe OA. (Referido PRHOA) | J9: =_xlfn.XLOOKUP($I9,RazónMuerte!$A:$A,RazónMuerte!B:B,"",0) -> Otras / No especificada | K9: =_xlfn.XLOOKUP($I9,RazónMuerte!$A:$A,RazónMuerte!C:C,"",0) -> 0 | L9: =_xlfn.XLOOKUP($I9,RazónMuerte!$A:$A,RazónMuerte!D:D,"",0) -> Fatal injury | M9: Si
A10: 24-JUNIO-2025 | B10: =LEFT(A10,FIND("-",A10)-1) -> 24 | C10: =MID(A10,FIND("-",A10)+1,FIND("-",A10,FIND("-",A10)+1)-FIND("-",A10)-1) -> JUNIO | D10: 45521 | E10: 45832 | F10: THIAGO & YASIL | G10: 7464 | H10: THIAGUITO A | I10: RF medial base sesamoid bone fracture + severe arthritis. | J10: =_xlfn.XLOOKUP($I10,RazónMuerte!$A:$A,RazónMuerte!B:B,"",0) -> Fractura ósea | K10: =_xlfn.XLOOKUP($I10,RazónMuerte!$A:$A,RazónMuerte!C:C,"",0) -> Sesamoideo | L10: =_xlfn.XLOOKUP($I10,RazónMuerte!$A:$A,RazónMuerte!D:D,"",0) -> Fatal injury | M10: Si
A11: 20-FEBRERO-2025 | B11: =LEFT(A11,FIND("-",A11)-1) -> 20 | C11: =MID(A11,FIND("-",A11)+1,FIND("-",A11,FIND("-",A11)+1)-FIND("-",A11)-1) -> FEBRERO | D11: 45550 | E11: 45708 | F11: EMT | G11: 3792 | H11: LIGHTS ON GIRL | I11: Exercise intolerance (tracheal collapse)/ Arthritis both front fetlocks. | J11: =_xlfn.XLOOKUP($I11,RazónMuerte!$A:$A,RazónMuerte!B:B,"",0) -> Enfermedad degenerativa articular | K11: =_xlfn.XLOOKUP($I11,RazónMuerte!$A:$A,RazónMuerte!C:C,"",0) -> 0 | L11: =_xlfn.XLOOKUP($I11,RazónMuerte!$A:$A,RazónMuerte!D:D,"",0) -> Fatal injury | M11: Si
A12: 6-MARZO-2025 | B12: =LEFT(A12,FIND("-",A12)-1) -> 6 | C12: =MID(A12,FIND("-",A12)+1,FIND("-",A12,FIND("-",A12)+1)-FIND("-",A12)-1) -> MARZO | D12: 45555 | E12: 45722 | F12: MALAVÉ | G12: 4008 | H12: ORIENTADO | I12: Tendinitis crónica con dorsiflexion excesiva del menudillo izquierdo delantero con subluxación de la cuartilla | J12: =_xlfn.XLOOKUP($I12,RazónMuerte!$A:$A,RazónMuerte!B:B,"",0) -> Otras / No especificada | K12: =_xlfn.XLOOKUP($I12,RazónMuerte!$A:$A,RazónMuerte!C:C,"",0) -> 0 | L12: =_xlfn.XLOOKUP($I12,RazónMuerte!$A:$A,RazónMuerte!D:D,"",0) -> No clasificado | M12: Si
A13: 28-ENERO-2025 | B13: =LEFT(A13,FIND("-",A13)-1) -> 28 | C13: =MID(A13,FIND("-",A13)+1,FIND("-",A13,FIND("-",A13)+1)-FIND("-",A13)-1) -> ENERO | D13: 45577 | E13: 45685 | F13: SILOE | G13: 2592 | H13: COBRADOR | I13: Fractura/artritis rodilla izquierda | J13: =_xlfn.XLOOKUP($I13,RazónMuerte!$A:$A,RazónMuerte!B:B,"",0) -> Fractura ósea | K13: =_xlfn.XLOOKUP($I13,RazónMuerte!$A:$A,RazónMuerte!C:C,"",0) -> Rodilla / Carpal | L13: =_xlfn.XLOOKUP($I13,RazónMuerte!$A:$A,RazónMuerte!D:D,"",0) -> Fatal injury | M13: Si
... A109: 3-AGOSTO-2025 | B109: =LEFT(A109,FIND("-",A109)-1) -> 3 | C109: =MID(A109,FIND("-",A109)+1,FIND("-",A109,FIND("-",A109)+1)-FIND("-",A109)-1) -> AGOSTO | D109: 45872 | E109: 45872 | F109: M SANTIAGO | G109: 0 | H109: ARABIAN MOON | I109: Fractura rodilla izquierda (Guardia PRHOA) | J109: =_xlfn.XLOOKUP($I109,RazónMuerte!$A:$A,RazónMuerte!B:B,"",0) -> Fractura ósea | K109: =_xlfn.XLOOKUP($I109,RazónMuerte!$A:$A,RazónMuerte!C:C,"",0) -> Rodilla / Carpal | L109: =_xlfn.XLOOKUP($I109,RazónMuerte!$A:$A,RazónMuerte!D:D,"",0) -> Fatal injury | M109: Si
A110: 3-AGOSTO-2025 | B110: =LEFT(A110,FIND("-",A110)-1) -> 3 | C110: =MID(A110,FIND("-",A110)+1,FIND("-",A110,FIND("-",A110)+1)-FIND("-",A110)-1) -> AGOSTO | D110: 45872 | E110: 45872 | F110: JORMALY | G110: 0 | H110: LA NIETA E JORGI C | J110: =_xlfn.XLOOKUP($I110,RazónMuerte!$A:$A,RazónMuerte!B:B,"",0) -> 0 | K110: =_xlfn.XLOOKUP($I110,RazónMuerte!$A:$A,RazónMuerte!C:C,"",0) -> 0 | L110: =_xlfn.XLOOKUP($I110,RazónMuerte!$A:$A,RazónMuerte!D:D,"",0) -> 0 | M110: Si
A111: 1-OCTUBRE-2025 | B111: =LEFT(A111,FIND("-",A111)-1) -> 1 | C111: =MID(A111,FIND("-",A111)+1,FIND("-",A111,FIND("-",A111)+1)-FIND("-",A111)-1) -> OCTUBRE | D111: 45872 | E111: 45931 | F111: CASAN | G111: 1416 | H111: KEEP DANCING | I111: ARTHRITIS SEVERA MENUDILLO IZQUIERDO DELANTERO | J111: =_xlfn.XLOOKUP($I111,RazónMuerte!$A:$A,RazónMuerte!B:B,"",0) -> Enfermedad degenerativa articular | K111: =_xlfn.XLOOKUP($I111,RazónMuerte!$A:$A,RazónMuerte!C:C,"",0) -> 0 | L111: =_xlfn.XLOOKUP($I111,RazónMuerte!$A:$A,RazónMuerte!D:D,"",0) -> No fatal injury (chronic/medical) | M111: Si
A112: 26-SEPTIEMBRE-2025 | B112: =LEFT(A112,FIND("-",A112)-1) -> 26 | C112: =MID(A112,FIND("-",A112)+1,FIND("-",A112,FIND("-",A112)+1)-FIND("-",A112)-1) -> SEPTIEMBRE | D112: 45876 | E112: 45926 | F112: SACO E SAL | G112: 1200 | H112: RAFY Q | I112: LH chronic suspensory desmitis. | J112: =_xlfn.XLOOKUP($I112,RazónMuerte!$A:$A,RazónMuerte!B:B,"",0) -> Lesión de ligamentos/tendones | K112: =_xlfn.XLOOKUP($I112,RazónMuerte!$A:$A,RazónMuerte!C:C,"",0) -> 0 | L112: =_xlfn.XLOOKUP($I112,RazónMuerte!$A:$A,RazónMuerte!D:D,"",0) -> No fatal injury (chronic/medical) | M112: Si
A113: 25-AGOSTO-2025 | B113: =LEFT(A113,FIND("-",A113)-1) -> 25 | C113: =MID(A113,FIND("-",A113)+1,FIND("-",A113,FIND("-",A113)+1)-FIND("-",A113)-1) -> AGOSTO | D113: 45877 | E113: 45894 | F113: HERNÁNDEZ | G113: 408 | H113: EL ZAFIRO | I113: Herida con laceración de tendón pata izquierda trasera. | J113: =_xlfn.XLOOKUP($I113,RazónMuerte!$A:$A,RazónMuerte!B:B,"",0) -> Otras / No especificada | K113: =_xlfn.XLOOKUP($I113,RazónMuerte!$A:$A,RazónMuerte!C:C,"",0) -> 0 | L113: =_xlfn.XLOOKUP($I113,RazónMuerte!$A:$A,RazónMuerte!D:D,"",0) -> No clasificado | M113: Si
A114: 19-SEPTIEMBRE-2025 | B114: =LEFT(A114,FIND("-",A114)-1) -> 19 | C114: =MID(A114,FIND("-",A114)+1,FIND("-",A114,FIND("-",A114)+1)-FIND("-",A114)-1) -> SEPTIEMBRE | D114: 45877 | E114: 45919 | F114: NATALIA | G114: 1008 | H114: AWESOME DISCOUNT | I114: Fractura sesamoide derecho delantero. | J114: =_xlfn.XLOOKUP($I114,RazónMuerte!$A:$A,RazónMuerte!B:B,"",0) -> Fractura ósea | K114: =_xlfn.XLOOKUP($I114,RazónMuerte!$A:$A,RazónMuerte!C:C,"",0) -> Sesamoideo | L114: =_xlfn.XLOOKUP($I114,RazónMuerte!$A:$A,RazónMuerte!D:D,"",0) -> Fatal injury | M114: Si
A115: 9-AGOSTO-2025 | B115: =LEFT(A115,FIND("-",A115)-1) -> 9 | C115: =MID(A115,FIND("-",A115)+1,FIND("-",A115,FIND("-",A115)+1)-FIND("-",A115)-1) -> AGOSTO | D115: 45878 | E115: 45878 | F115: SONATA | G115: 0 | H115: VOLATILE DANCER | I115: LF Breakdown injury. | J115: =_xlfn.XLOOKUP($I115,RazónMuerte!$A:$A,RazónMuerte!B:B,"",0) -> Otras / No especificada | K115: =_xlfn.XLOOKUP($I115,RazónMuerte!$A:$A,RazónMuerte!C:C,"",0) -> 0 | L115: =_xlfn.XLOOKUP($I115,RazónMuerte!$A:$A,RazónMuerte!D:D,"",0) -> No clasificado | M115: Si
A116: 20-AGOSTO-2025 | B116: =LEFT(A116,FIND("-",A116)-1) -> 20 | C116: =MID(A116,FIND("-",A116)+1,FIND("-",A116,FIND("-",A116)+1)-FIND("-",A116)-1) -> AGOSTO | D116: 45878 | E116: 45889 | F116: FLAMBOYÁN | G116: 264 | H116: DULCE BISCUIT | I116: Artritis en ambos menudillos delanteros. Historial previo de laminitis. | J116: =_xlfn.XLOOKUP($I116,RazónMuerte!$A:$A,RazónMuerte!B:B,"",0) -> Enfermedad degenerativa articular | K116: =_xlfn.XLOOKUP($I116,RazónMuerte!$A:$A,RazónMuerte!C:C,"",0) -> 0 | L116: =_xlfn.XLOOKUP($I116,RazónMuerte!$A:$A,RazónMuerte!D:D,"",0) -> No fatal injury (chronic/medical) | M116: Si
A117: 24-SEPTIEMBRE-2025 | B117: =LEFT(A117,FIND("-",A117)-1) -> 24 | C117: =MID(A117,FIND("-",A117)+1,FIND("-",A117,FIND("-",A117)+1)-FIND("-",A117)-1) -> SEPTIEMBRE | D117: 45879 | E117: 45924 | F117: LUZ EMILIA | G117: 1080 | H117: TRUE ATKA | I117: Artritis (menudillo izquierdo delantero) | J117: =_xlfn.XLOOKUP($I117,RazónMuerte!$A:$A,RazónMuerte!B:B,"",0) -> Enfermedad degenerativa articular | K117: =_xlfn.XLOOKUP($I117,RazónMuerte!$A:$A,RazónMuerte!C:C,"",0) -> 0 | L117: =_xlfn.XLOOKUP($I117,RazónMuerte!$A:$A,RazónMuerte!D:D,"",0) -> No fatal injury (chronic/medical) | M117: Si
A118: 21-OCTUBRE-2025 | B118: =LEFT(A118,FIND("-",A118)-1) -> 21 | C118: =MID(A118,FIND("-",A118)+1,FIND("-",A118,FIND("-",A118)+1)-FIND("-",A118)-1) -> OCTUBRE | D118: 45883 | E118: 45951 | F118: RÍO CARIBE | G118: 1632 | H118: CURAPA M | I118: Fractura rodilla derecha (C-3 slab). | J118: =_xlfn.XLOOKUP($I118,RazónMuerte!$A:$A,RazónMuerte!B:B,"",0) -> Fractura ósea | K118: =_xlfn.XLOOKUP($I118,RazónMuerte!$A:$A,RazónMuerte!C:C,"",0) -> Slab | L118: =_xlfn.XLOOKUP($I118,RazónMuerte!$A:$A,RazónMuerte!D:D,"",0) -> Fatal injury | M118: Si
A119: 4-SEPTIEMBRE-2025 | B119: =LEFT(A119,FIND("-",A119)-1) -> 4 | C119: =MID(A119,FIND("-",A119)+1,FIND("-",A119,FIND("-",A119)+1)-FIND("-",A119)-1) -> SEPTIEMBRE | D119: 45884 | E119: 45904 | F119: CENTRAL | G119: 480 | H119: ROYAL APPLAUD | I119: Fractura rodilla derecha. | J119: =_xlfn.XLOOKUP($I119,RazónMuerte!$A:$A,RazónMuerte!B:B,"",0) -> Fractura ósea | K119: =_xlfn.XLOOKUP($I119,RazónMuerte!$A:$A,RazónMuerte!C:C,"",0) -> Rodilla / Carpal | L119: =_xlfn.XLOOKUP($I119,RazónMuerte!$A:$A,RazónMuerte!D:D,"",0) -> Fatal injury | M119: Si
A120: 15-OCTUBRE-2025 | B120: =LEFT(A120,FIND("-",A120)-1) -> 15 | C120: =MID(A120,FIND("-",A120)+1,FIND("-",A120,FIND("-",A120)+1)-FIND("-",A120)-1) -> OCTUBRE | D120: 45884 | E120: 45945 | F120: SIACCA | G120: 1464 | H120: DETERMINADORA | I120: Fractura rodilla derecha. | J120: =_xlfn.XLOOKUP($I120,RazónMuerte!$A:$A,RazónMuerte!B:B,"",0) -> Fractura ósea | K120: =_xlfn.XLOOKUP($I120,RazónMuerte!$A:$A,RazónMuerte!C:C,"",0) -> Rodilla / Carpal | L120: =_xlfn.XLOOKUP($I120,RazónMuerte!$A:$A,RazónMuerte!D:D,"",0) -> Fatal injury | M120: Si
A121: 3-SEPTIEMBRE-2025 | B121: =LEFT(A121,FIND("-",A121)-1) -> 3 | C121: =MID(A121,FIND("-",A121)+1,FIND("-",A121,FIND("-",A121)+1)-FIND("-",A121)-1) -> SEPTIEMBRE | D121: 45885 | E121: 45903 | F121: MA D CO | G121: 432 | H121: ROSARIO BLUE | I121: Laminitis 4 patas. (Se fue a la cuadra PRHOA) | J121: =_xlfn.XLOOKUP($I121,RazónMuerte!$A:$A,RazónMuerte!B:B,"",0) -> Otras / No especificada | K121: =_xlfn.XLOOKUP($I121,RazónMuerte!$A:$A,RazónMuerte!C:C,"",0) -> 0 | L121: =_xlfn.XLOOKUP($I121,RazónMuerte!$A:$A,RazónMuerte!D:D,"",0) -> No clasificado | M121: Si
A122: 24-OCTUBRE-2025 | B122: =LEFT(A122,FIND("-",A122)-1) -> 24 | C122: =MID(A122,FIND("-",A122)+1,FIND("-",A122,FIND("-",A122)+1)-FIND("-",A122)-1) -> OCTUBRE | D122: 45886 | E122: 45954 | F122: JOSÉ LUIS | G122: 1632 | H122: JASMINE C | I122: Múltiples fracturas/DJD severo en ambas rodillas. | J122: =_xlfn.XLOOKUP($I122,RazónMuerte!$A:$A,RazónMuerte!B:B,"",0) -> Fractura ósea | K122: =_xlfn.XLOOKUP($I122,RazónMuerte!$A:$A,RazónMuerte!C:C,"",0) -> Rodilla / Carpal | L122: =_xlfn.XLOOKUP($I122,RazónMuerte!$A:$A,RazónMuerte!D:D,"",0) -> Fatal injury | M122: Si
... A164: 30-DICIEMBRE-2025 | B164: =LEFT(A164,FIND("-",A164)-1) -> 30 | C164: =MID(A164,FIND("-",A164)+1,FIND("-",A164,FIND("-",A164)+1)-FIND("-",A164)-1) -> DICIEMBRE | D164: 46010 | E164: 46021 | F164: AMBERLYS ADHARA | G164: 264 | H164: MONET NEVER | I164: Artritis severa, fractura splints, suspensory ligament desmitis. | J164: =_xlfn.XLOOKUP($I164,RazónMuerte!$A:$A,RazónMuerte!B:B,"",0) -> Fractura ósea | K164: =_xlfn.XLOOKUP($I164,RazónMuerte!$A:$A,RazónMuerte!C:C,"",0) -> Splint | L164: =_xlfn.XLOOKUP($I164,RazónMuerte!$A:$A,RazónMuerte!D:D,"",0) -> Fatal injury | M164: Si
A165: 11-FEBRERO-2025 | B165: =LEFT(A165,FIND("-",A165)-1) -> 11 | C165: =MID(A165,FIND("-",A165)+1,FIND("-",A165,FIND("-",A165)+1)-FIND("-",A165)-1) -> FEBRERO | E165: 45699 | F165: EURO | G165: 1096776 | H165: TECNÓLOGO | I165: Fractura de la escápula derecha. | J165: =_xlfn.XLOOKUP($I165,RazónMuerte!$A:$A,RazónMuerte!B:B,"",0) -> Fractura ósea | K165: =_xlfn.XLOOKUP($I165,RazónMuerte!$A:$A,RazónMuerte!C:C,"",0) -> No especificado | L165: =_xlfn.XLOOKUP($I165,RazónMuerte!$A:$A,RazónMuerte!D:D,"",0) -> Fatal injury | M165: No
A166: 18-FEBRERO-2025 | B166: =LEFT(A166,FIND("-",A166)-1) -> 18 | C166: =MID(A166,FIND("-",A166)+1,FIND("-",A166,FIND("-",A166)+1)-FIND("-",A166)-1) -> FEBRERO | E166: 45706 | F166: VILLA REAL | G166: 1096944 | H166: PERFILADOR | I166: Fractura escápula derecha. | J166: =_xlfn.XLOOKUP($I166,RazónMuerte!$A:$A,RazónMuerte!B:B,"",0) -> Fractura ósea | K166: =_xlfn.XLOOKUP($I166,RazónMuerte!$A:$A,RazónMuerte!C:C,"",0) -> No especificado | L166: =_xlfn.XLOOKUP($I166,RazónMuerte!$A:$A,RazónMuerte!D:D,"",0) -> Fatal injury | M166: No
A167: 1-MARZO-2025 | B167: =LEFT(A167,FIND("-",A167)-1) -> 1 | C167: =MID(A167,FIND("-",A167)+1,FIND("-",A167,FIND("-",A167)+1)-FIND("-",A167)-1) -> MARZO | E167: 45717 | F167: SONATA | G167: 1097208 | H167: PARTICULAR | I167: Sesamoid fracture LF ankle. (Referido PRHOA) | J167: =_xlfn.XLOOKUP($I167,RazónMuerte!$A:$A,RazónMuerte!B:B,"",0) -> Fractura ósea | K167: =_xlfn.XLOOKUP($I167,RazónMuerte!$A:$A,RazónMuerte!C:C,"",0) -> Sesamoideo | L167: =_xlfn.XLOOKUP($I167,RazónMuerte!$A:$A,RazónMuerte!D:D,"",0) -> Fatal injury | M167: No
A168: 1-MARZO-2025 | B168: =LEFT(A168,FIND("-",A168)-1) -> 1 | C168: =MID(A168,FIND("-",A168)+1,FIND("-",A168,FIND("-",A168)+1)-FIND("-",A168)-1) -> MARZO | E168: 45717 | F168: ERV ENTERPRISES | G168: 1097208 | H168: HARLAND STORM | I168: R & L Knee multiple fracture both RC and Medial Carpal Joint. (Referido PRHOA) | J168: =_xlfn.XLOOKUP($I168,RazónMuerte!$A:$A,RazónMuerte!B:B,"",0) -> Fractura ósea | K168: =_xlfn.XLOOKUP($I168,RazónMuerte!$A:$A,RazónMuerte!C:C,"",0) -> Rodilla / Carpal | L168: =_xlfn.XLOOKUP($I168,RazónMuerte!$A:$A,RazónMuerte!D:D,"",0) -> Fatal injury | M168: No
A169: 7-MARZO-2025 | B169: =LEFT(A169,FIND("-",A169)-1) -> 7 | C169: =MID(A169,FIND("-",A169)+1,FIND("-",A169,FIND("-",A169)+1)-FIND("-",A169)-1) -> MARZO | E169: 45723 | F169: RAFANIL | G169: 1097352 | H169: RIQUITO A | I169: Fractura tibia izquierda | J169: =_xlfn.XLOOKUP($I169,RazónMuerte!$A:$A,RazónMuerte!B:B,"",0) -> Fractura ósea | K169: =_xlfn.XLOOKUP($I169,RazónMuerte!$A:$A,RazónMuerte!C:C,"",0) -> No especificado | L169: =_xlfn.XLOOKUP($I169,RazónMuerte!$A:$A,RazónMuerte!D:D,"",0) -> Fatal injury | M169: No
A170: 22-MARZO-2025 | B170: =LEFT(A170,FIND("-",A170)-1) -> 22 | C170: =MID(A170,FIND("-",A170)+1,FIND("-",A170,FIND("-",A170)+1)-FIND("-",A170)-1) -> MARZO | E170: 45738 | F170: RAFANIL | G170: 1097712 | H170: CENTAURO | I170: Laminitis LF hoof | J170: =_xlfn.XLOOKUP($I170,RazónMuerte!$A:$A,RazónMuerte!B:B,"",0) -> Otras / No especificada | K170: =_xlfn.XLOOKUP($I170,RazónMuerte!$A:$A,RazónMuerte!C:C,"",0) -> 0 | L170: =_xlfn.XLOOKUP($I170,RazónMuerte!$A:$A,RazónMuerte!D:D,"",0) -> No clasificado | M170: No
A171: 8-ABRIL-2025 | B171: =LEFT(A171,FIND("-",A171)-1) -> 8 | C171: =MID(A171,FIND("-",A171)+1,FIND("-",A171,FIND("-",A171)+1)-FIND("-",A171)-1) -> ABRIL | E171: 45755 | F171: L&D THOROUGHBRED | G171: 1098120 | H171: DAMA DE HIERRO | I171: Fractura hombro derecho. (Se fue a la pista) | J171: =_xlfn.XLOOKUP($I171,RazónMuerte!$A:$A,RazónMuerte!B:B,"",0) -> Fractura ósea | K171: =_xlfn.XLOOKUP($I171,RazónMuerte!$A:$A,RazónMuerte!C:C,"",0) -> No especificado | L171: =_xlfn.XLOOKUP($I171,RazónMuerte!$A:$A,RazónMuerte!D:D,"",0) -> Fatal injury | M171: No
A172: 8-ABRIL-2025 | B172: =LEFT(A172,FIND("-",A172)-1) -> 8 | C172: =MID(A172,FIND("-",A172)+1,FIND("-",A172,FIND("-",A172)+1)-FIND("-",A172)-1) -> ABRIL | E172: 45755 | F172: ORIÓN | G172: 1098120 | H172: EL INTRÉPIDO | I172: Fractura rodilla izquierda (C-3 Slab). | J172: =_xlfn.XLOOKUP($I172,RazónMuerte!$A:$A,RazónMuerte!B:B,"",0) -> Fractura ósea | K172: =_xlfn.XLOOKUP($I172,RazónMuerte!$A:$A,RazónMuerte!C:C,"",0) -> Slab | L172: =_xlfn.XLOOKUP($I172,RazónMuerte!$A:$A,RazónMuerte!D:D,"",0) -> Fatal injury | M172: No
A173: 3-MAYO-2025 | B173: =LEFT(A173,FIND("-",A173)-1) -> 3 | C173: =MID(A173,FIND("-",A173)+1,FIND("-",A173,FIND("-",A173)+1)-FIND("-",A173)-1) -> MAYO | E173: 45780 | F173: DESAFÍO | G173: 1098720 | H173: MI AMADA CECILIA | I173: Fractura hombro derecho. (Se fue a la pista) | J173: =_xlfn.XLOOKUP($I173,RazónMuerte!$A:$A,RazónMuerte!B:B,"",0) -> Fractura ósea | K173: =_xlfn.XLOOKUP($I173,RazónMuerte!$A:$A,RazónMuerte!C:C,"",0) -> No especificado | L173: =_xlfn.XLOOKUP($I173,RazónMuerte!$A:$A,RazónMuerte!D:D,"",0) -> Fatal injury | M173: No
A174: 9-MAYO-2025 | B174: =LEFT(A174,FIND("-",A174)-1) -> 9 | C174: =MID(A174,FIND("-",A174)+1,FIND("-",A174,FIND("-",A174)+1)-FIND("-",A174)-1) -> MAYO | E174: 45786 | F174: ERV ENTERPRISES | G174: 1098864 | H174: TATIBIRI | I174: Left laryngeal hemoplasia with neurological signs. (Referido PRHOA) | J174: =_xlfn.XLOOKUP($I174,RazónMuerte!$A:$A,RazónMuerte!B:B,"",0) -> Otras / No especificada | K174: =_xlfn.XLOOKUP($I174,RazónMuerte!$A:$A,RazónMuerte!C:C,"",0) -> 0 | L174: =_xlfn.XLOOKUP($I174,RazónMuerte!$A:$A,RazónMuerte!D:D,"",0) -> No clasificado | M174: No
A175: 14-MAYO-2025 | B175: =LEFT(A175,FIND("-",A175)-1) -> 14 | C175: =MID(A175,FIND("-",A175)+1,FIND("-",A175,FIND("-",A175)+1)-FIND("-",A175)-1) -> MAYO | E175: 45791 | F175: ADLEKE | G175: 1098984 | H175: CODE OF TIME | I175: Fractura hombro derecho. | J175: =_xlfn.XLOOKUP($I175,RazónMuerte!$A:$A,RazónMuerte!B:B,"",0) -> Fractura ósea | K175: =_xlfn.XLOOKUP($I175,RazónMuerte!$A:$A,RazónMuerte!C:C,"",0) -> No especificado | L175: =_xlfn.XLOOKUP($I175,RazónMuerte!$A:$A,RazónMuerte!D:D,"",0) -> Fatal injury | M175: No
A176: 26-MAYO-2025 | B176: =LEFT(A176,FIND("-",A176)-1) -> 26 | C176: =MID(A176,FIND("-",A176)+1,FIND("-",A176,FIND("-",A176)+1)-FIND("-",A176)-1) -> MAYO | E176: 45803 | F176: HACIENDA EL SUEÑO | G176: 1099272 | H176: CHIQUILIN | I176: Tétano. | J176: =_xlfn.XLOOKUP($I176,RazónMuerte!$A:$A,RazónMuerte!B:B,"",0) -> Otras / No especificada | K176: =_xlfn.XLOOKUP($I176,RazónMuerte!$A:$A,RazónMuerte!C:C,"",0) -> 0 | L176: =_xlfn.XLOOKUP($I176,RazónMuerte!$A:$A,RazónMuerte!D:D,"",0) -> No clasificado | M176: No
... A198: 31-DICIEMBRE-2025 | B198: =LEFT(A198,FIND("-",A198)-1) -> 31 | C198: =MID(A198,FIND("-",A198)+1,FIND("-",A198,FIND("-",A198)+1)-FIND("-",A198)-1) -> DICIEMBRE | E198: 46022 | F198: DESAFÍO | G198: 1104528 | H198: YUCA BRAVA | I198: Fractura en la caña derecha delantera (Se fue a la pista) | J198: =_xlfn.XLOOKUP($I198,RazónMuerte!$A:$A,RazónMuerte!B:B,"",0) -> Fractura ósea | K198: =_xlfn.XLOOKUP($I198,RazónMuerte!$A:$A,RazónMuerte!C:C,"",0) -> Caña / Cannon bone | L198: =_xlfn.XLOOKUP($I198,RazónMuerte!$A:$A,RazónMuerte!D:D,"",0) -> Fatal injury | M198: No

Sheet Analisis Necropcia
A2: Registrado/Compitió? | B2: Si
A3: Death Date (Year) | B3: 2026
A4: Horas transcurridas | B4: (Multiple Items)
A6: Caballos | B6: Razón muerte
A7: Meses | B7: Enfermedad degenerativa articular | C7: Fractura ósea | D7: Lesión de ligamentos/tendones | E7: Otras / No especificada | F7: Grand Total
A8: Jan | C8: 2 | D8: 1 | F8: 3
A9: ADINERADA | C9: 1 | F9: 1
A10: ROAD SLEW | D10: 1 | F10: 1
A11: SOY DE LEE | C11: 1 | F11: 1
A12: Feb | C12: 2 | E12: 1 | F12: 3
A13: COMBAT METRA | C13: 1 | F13: 1
A14: CRYSTAL CRECENT | E14: 1 | F14: 1
A15: MY OWN DREAM | C15: 1 | F15: 1
A16: Mar | D16: 1 | F16: 1
A17: VUELVE JOU | D17: 1 | F17: 1
A18: Apr | C18: 1 | F18: 1
A19: ANDRÉS | C19: 1 | F19: 1
A20: May | B20: 9 | C20: 5 | E20: 5 | F20: 19
A21: BIG FIG | B21: 1 | F21: 1
A22: CERVECERA | C22: 1 | F22: 1
A23: CHIHUAHUA | C23: 1 | F23: 1
A24: CONSEJERO | B24: 1 | F24: 1
A25: DAY OF LOVE | B25: 1 | F25: 1
A26: DULCE INEA | B26: 1 | F26: 1
A27: EL GOLDY | B27: 1 | F27: 1
A28: EMPRENDEDORA | E28: 1 | F28: 1
A29: GO BIG BLUE | B29: 1 | F29: 1
A30: JOAQUIN ANDRES | B30: 1 | F30: 1
A31: LA INTOCABLE | C31: 1 | F31: 1
A32: LIBERTY QUEEN | B32: 1 | F32: 1
A33: LINDA CRISTY | E33: 1 | F33: 1
A34: MI NINA PONCENA | B34: 1 | F34: 1
A35: REGNATOR | E35: 1 | F35: 1
A36: REINA DE COPAS | C36: 1 | F36: 1
A37: SYRIANA MIA 2024 | E37: 1 | F37: 1
A38: THE UPPERCUT LADY | C38: 1 | F38: 1
A39: VERONICA D | E39: 1 | F39: 1
A40: Jun | B40: 1 | C40: 5 | D40: 2 | F40: 8
A41: CHINO BRAVO | D41: 1 | F41: 1
A42: COMMANDEER | B42: 1 | F42: 1
A43: CRIOLLO | C43: 1 | F43: 1
A44: DONA TITA N | C44: 1 | F44: 1
A45: LA VALEROSA | C45: 1 | F45: 1
A46: PUNTO CRUCIAL | C46: 1 | F46: 1
A47: SAME AS CASH | C47: 1 | F47: 1
A48: SKELLETOR | D48: 1 | F48: 1
A49: Grand Total | B49: 10 | C49: 15 | D49: 4 | E49: 6 | F49: 35

Sheet Fatal Injury AllData
A1: Año | B1: FECHA | C1: día | D1: Mes | E1: Last Race Date (desde Equibase) | F1: Death Date | G1: ESTABLO | H1: Horas transcurridas | I1: CABALLO | J1: RAZON | K1: Categoría | L1: Tipo de fractura | M1: Fatal injury | N1: Registrado/Compitió? | O1: Data Inconsistente
A2: 2024 | B2: 7/ENERO/2024 | C2: 7 | D2: ENERO | E2: 45298 | F2: 45298 | G2: SANCHEZ | H2: 0 | I2: EVERY DAY CAPI | K2: 0 | L2: 0 | M2: 0 | N2: Si
A3: 2024 | B3: 6/ABRIL/2024 | C3: 6 | D3: ABRIL | E3: 45388 | F3: 45388 | G3: NE | H3: 0 | I3: CHOCO FACTOR | J3: RF Breakdown Injury. (PRHOA) | K3: Otras / No especificada | L3: 0 | M3: No clasificado | N3: Si
A4: 2024 | B4: 27/ABRIL/2024 | C4: 27 | D4: ABRIL | E4: 45409 | F4: 45409 | G4: JBK | H4: 0 | I4: HARLAN'S WAR | J4: Fractura sesamoide ambas patas delanteras durante la 3ra carrera. PRHOA. | K4: Fractura ósea | L4: Sesamoideo | M4: Fatal injury | N4: Si
A5: 2024 | B5: 6/JULIO/2024 | C5: 6 | D5: JULIO | E5: 45479 | F5: 45479 | G5: CARLOS DAMIAN | H5: 0 | I5: SARA Y | J5: LF breakdown injury. Referido PRHOA. | K5: Otras / No especificada | L5: 0 | M5: No clasificado | N5: Si
A6: 2024 | B6: 7/JULIO/2024 | C6: 7 | D6: JULIO | E6: 45480 | F6: 45480 | G6: HNOS APONTE | H6: 0 | I6: ESTRELLITA | J6: Fractura hombro derecho. 6ta carrera. Referido PRHOA. | K6: Fractura ósea | L6: No especificado | M6: Fatal injury | N6: Si
A7: 2024 | B7: 19/JULIO/2024 | C7: 19 | D7: JULIO | E7: 45492 | F7: 45492 | G7: MAJESTUOSO | H7: 0 | I7: CAPRICHOSO | J7: Fractura rodilla derecha. PRHOA. | K7: Fractura ósea | L7: Rodilla / Carpal | M7: Fatal injury | N7: Si
A8: 2024 | B8: 20/JULIO/2024 | C8: 20 | D8: JULIO | E8: 45493 | F8: 45493 | G8: RM | H8: 0 | I8: AMAYA BESITO | J8: Beakdown injury with basilar sesamoid fracture | K8: Fractura ósea | L8: Sesamoideo | M8: Fatal injury | N8: Si
A9: 2024 | B9: 19/SEPTIEMBRE/2024 | C9: 19 | D9: SEPTIEMBRE | E9: 45554 | F9: 45554 | G9: CANITO | H9: 0 | I9: FROSTED ARCH | J9: Post/race 6:42pm | K9: Otras / No especificada | L9: 0 | M9: No clasificado | N9: Si
A10: 2024 | B10: 27/SEPTIEMBRE/2024 | C10: 27 | D10: SEPTIEMBRE | E10: 45562 | F10: 45562 | G10: STAR & STRIPES | H10: 0 | I10: CYRANO DE B | J10: RF Knee breakdown injury. (Guardia PRHOA) | K10: Otras / No especificada | L10: 0 | M10: No clasificado | N10: Si
A11: 2024 | B11: 10/NOVIEMBRE/2024 | C11: 10 | D11: NOVIEMBRE | E11: 45606 | F11: 45606 | G11: SONATA | H11: 0 | I11: HOP KAT | J11: LF Ankle breakdown injury during race. (Guardia PRHOA) | K11: Otras / No especificada | L11: 0 | M11: No clasificado | N11: Si
A12: 2024 | B12: 8/DICIEMBRE/2024 | C12: 8 | D12: DICIEMBRE | E12: 45634 | F12: 45634 | G12: MATTA | H12: 0 | I12: MR. BELLINGHAM | J12: Fractura rodilla izquierda | K12: Fractura ósea | L12: Rodilla / Carpal | M12: Fatal injury | N12: Si
A13: 2024 | B13: 15/ENERO/2024 | C13: 15 | D13: ENERO | E13: 45305 | F13: 45306 | G13: THREE KINGS | H13: 24 | I13: ST. ANDRES | K13: 0 | L13: 0 | M13: 0 | N13: Si
A14: 2024 | B14: 16/ENERO/2024 | C14: 16 | D14: ENERO | E14: 45306 | F14: 45307 | G14: L & D THOROUGHBRED | H14: 24 | I14: JAZHARA | J14: FRACTURA RODILLA DERECHA | K14: Fractura ósea | L14: Rodilla / Carpal | M14: Fatal injury | N14: Si
A15: 2024 | B15: 2/FEBRERO/2024 | C15: 2 | D15: FEBRERO | E15: 45323 | F15: 45324 | G15: N Y N | H15: 24 | I15: UNIFIED CONQUEST | J15: HERIDA PARTE POSTERIOR DEL MENUDILLO, CUARTILLA IZQUIERDA DELANTERA INCLUYENDO LA VAINA DEL TENDON | K15: Lesión de ligamentos/tendones | L15: 0 | M15: No clasificado | N15: Si
A16: 2024 | B16: 16/FEBRERO/2024 | C16: 16 | D16: FEBRERO | E16: 45337 | F16: 45338 | G16: DC | H16: 24 | I16: EL DICTADOR | J16: Fractura sesamoide derecho delantero | K16: Fractura ósea | L16: Sesamoideo | M16: Fatal injury | N16: Si
A17: 2024 | B17: 19/ABRIL/2024 | C17: 19 | D17: ABRIL | E17: 45400 | F17: 45401 | G17: MATEO IGNACIO | H17: 24 | I17: MR. ZACH | J17: Fractura caña izquierda delantera | K17: Fractura ósea | L17: Caña / Cannon bone | M17: Fatal injury | N17: Si
A18: 2024 | B18: 3/MAYO/2024 | C18: 3 | D18: MAYO | E18: 45414 | F18: 45415 | G18: LOUISIANA | H18: 24 | I18: COLISEO | J18: Tendinitis crónica en ambas patas delanteras. | K18: Otras / No especificada | L18: 0 | M18: No clasificado | N18: Si
A19: 2024 | B19: 10/MAYO/2024 | C19: 10 | D19: MAYO | E19: 45421 | F19: 45422 | G19: BELLEZA | H19: 24 | I19: MAN ICE | J19: Fractura sesamoide pata izquierda delantera. | K19: Fractura ósea | L19: Sesamoideo | M19: Fatal injury | N19: Si
A20: 2024 | B20: 11/MAYO/2024 | C20: 11 | D20: MAYO | E20: 45422 | F20: 45423 | G20: GUILLERMO BERRIOS | H20: 24 | I20: MY FAVORITE STAR | J20: Múltiples fracturas; DJD severo después de cirugía. No pudo terminar carrera. Referido Drs. PRHOA. | K20: Fractura ósea | L20: No especificado | M20: Fatal injury | N20: Si
A21: 2024 | B21: 21/JUNIO/2024 | C21: 21 | D21: JUNIO | E21: 45463 | F21: 45464 | G21: TWO J'S | H21: 24 | I21: FRANK ALONE | J21: Artritis menudillos delanteros. (Referido por Dra. Armand PRHOA) | K21: Enfermedad degenerativa articular | L21: 0 | M21: No fatal injury (chronic/medical) | N21: Si
A22: 2024 | B22: 5/JULIO/2024 | C22: 5 | D22: JULIO | E22: 45477 | F22: 45478 | G22: TORRES PAGAN | H22: 24 | I22: CORPULENTA | J22: Fractura rodilla derecha. | K22: Fractura ósea | L22: Rodilla / Carpal | M22: Fatal injury | N22: Si
A23: 2024 | B23: 8/JULIO/2024 | C23: 8 | D23: JULIO | E23: 45480 | F23: 45481 | G23: R RACING | H23: 24 | I23: DULCES LABIOS | J23: Fractura rodilla izquierda. | K23: Fractura ósea | L23: Rodilla / Carpal | M23: Fatal injury | N23: Si
A24: 2024 | B24: 22/JULIO/2024 | C24: 22 | D24: JULIO | E24: 45494 | F24: 45495 | G24: TONY GUZMAN | H24: 24 | I24: DUST DEVIL | J24: RF bReakdown Injury. (Referido PRHOA) | K24: Otras / No especificada | L24: 0 | M24: No clasificado | N24: Si
A25: 2024 | B25: 23/JULIO/2024 | C25: 23 | D25: JULIO | E25: 45495 | F25: 45496 | G25: VIRGEN DEL ROSARIO | H25: 24 | I25: NELL'S PRINCESS | J25: Sesamoide fracturado. | K25: Fractura ósea | L25: Sesamoideo | M25: Fatal injury | N25: Si
A26: 2024 | B26: 3/AGOSTO/2024 | C26: 3 | D26: AGOSTO | E26: 45506 | F26: 45507 | G26: VETERANO | H26: 24 | I26: SHE'S CLASSY | J26: Fractura sesamoide derecho. (Referido PRHOA) | K26: Fractura ósea | L26: Sesamoideo | M26: Fatal injury | N26: Si
A27: 2024 | B27: 17/AGOSTO/2024 | C27: 17 | D27: AGOSTO | E27: 45520 | F27: 45521 | G27: MI FAMILIA | H27: 24 | I27: SINDICATO | J27: Fracturas en ambas rodillas (Referido PRHOA) | K27: Fractura ósea | L27: Rodilla / Carpal | M27: Fatal injury | N27: Si
A28: 2024 | B28: 20/AGOSTO/2024 | C28: 20 | D28: AGOSTO | E28: 45523 | F28: 45524 | G28: VETERANO | H28: 24 | I28: LIANNE V | J28: Huge fractures on both knees. Sever DJD. Can't run. (Referido PRHOA) | K28: Fractura ósea | L28: No especificado | M28: Fatal injury | N28: Si
A29: 2024 | B29: 9/SEPTIEMBRE/2024 | C29: 9 | D29: SEPTIEMBRE | E29: 45543 | F29: 45544 | G29: SONATA | H29: 24 | I29: TAP MOON | J29: Referido PRHOA | K29: Otras / No especificada | L29: 0 | M29: No clasificado | N29: Si
A30: 2024 | B30: 30/SEPTIEMBRE/2024 | C30: 30 | D30: SEPTIEMBRE | E30: 45564 | F30: 45565 | G30: AQUINO | H30: 24 | I30: DIXIE DRAWL | J30: Breakdown injury LF fetlock | K30: Otras / No especificada | L30: 0 | M30: Fatal injury | N30: Si
A31: 2024 | B31: 5/OCTUBRE/2024 | C31: 5 | D31: OCTUBRE | E31: 45569 | F31: 45570 | G31: QUINTANA | H31: 24 | I31: TOWN PRIDE | J31: C/3 Slab fracture L Knee | K31: Fractura ósea | L31: Slab | M31: Fatal injury | N31: Si
A32: 2024 | B32: 16/NOVIEMBRE/2024 | C32: 16 | D32: NOVIEMBRE | E32: 45611 | F32: 45612 | G32: NINIMEL | H32: 24 | I32: ISABEL DEL MAR | J32: Fractura rodilla derecha | K32: Fractura ósea | L32: Rodilla / Carpal | M32: Fatal injury | N32: Si
A33: 2024 | B33: 18/NOVIEMBRE/2024 | C33: 18 | D33: NOVIEMBRE | E33: 45613 | F33: 45614 | G33: UTUADO | H33: 24 | I33: EL ROSKO | J33: Bilateral front limbs chronic suspensory desmitis | K33: Lesión de ligamentos/tendones | L33: 0 | M33: No fatal injury (chronic/medical) | N33: Si
A34: 2024 | B34: 23/DICIEMBRE/2024 | C34: 23 | D34: DICIEMBRE | E34: 45648 | F34: 45649 | G34: VETERANO | H34: 24 | I34: SUNDAY SPEIGHT | J34: LF Knee multiple fragments, severe reduce space with C3 fractures. (Referido PRHOA) | K34: Fractura ósea | L34: No especificado | M34: Fatal injury | N34: Si
A35: 2024 | B35: 28/DICIEMBRE/2024 | C35: 28 | D35: DICIEMBRE | E35: 45653 | F35: 45654 | G35: OSO POLAR | H35: 24 | I35: LA GORDA | J35: Carpal Bone Fracture | K35: Fractura ósea | L35: Rodilla / Carpal | M35: Fatal injury | N35: Si
A36: 2024 | B36: 22/ENERO/2024 | C36: 22 | D36: ENERO | E36: 45311 | F36: 45313 | G36: SACO E SAL | H36: 48 | I36: REGINA ISABEL | J36: Fractura rodilla derecha | K36: Fractura ósea | L36: Rodilla / Carpal | M36: Fatal injury | N36: Si
A37: 2024 | B37: 12/FEBRERO/2024 | C37: 12 | D37: FEBRERO | E37: 45332 | F37: 45334 | G37: V.G.O | H37: 48 | I37: IAN P.R. | J37: FRACTURA AMBAS RODILLAS | K37: Fractura ósea | L37: Rodilla / Carpal | M37: Fatal injury | N37: Si
A38: 2024 | B38: 13/FEBRERO/2024 | C38: 13 | D38: FEBRERO | E38: 45333 | F38: 45335 | G38: DESAFIO | H38: 48 | I38: SPEEDY D | J38: FRACTURA SESAMOIDE PATA DERECHA DELANTERA | K38: Fractura ósea | L38: Sesamoideo | M38: Fatal injury | N38: Si
A39: 2024 | B39: 11/MAYO/2024 | C39: 11 | D39: MAYO | E39: 45421 | F39: 45423 | G39: FC | H39: 48 | I39: CLEVER ALLIANCE | J39: Fractura rodilla derecha | K39: Fractura ósea | L39: Rodilla / Carpal | M39: Fatal injury | N39: Si
A40: 2024 | B40: 29/MAYO/2024 | C40: 29 | D40: MAYO | E40: 45439 | F40: 45441 | G40: R RACING | H40: 48 | I40: GRACIAN | J40: Fractura menudillo izquierdo delantero | K40: Fractura ósea | L40: No especificado | M40: Fatal injury | N40: Si
A41: 2024 | B41: 17/SEPTIEMBRE/2024 | C41: 17 | D41: SEPTIEMBRE | E41: 45550 | F41: 45552 | G41: MADECO (#1,000) | H41: 48 | I41: SWEET SEVENTY NINE | J41: R Knee multiple fragments with severe DJD. (Referido PRHOA) | K41: Enfermedad degenerativa articular | L41: 0 | M41: No fatal injury (chronic/medical) | N41: Si
A42: 2024 | B42: 11/NOVIEMBRE/2024 | C42: 11 | D42: NOVIEMBRE | E42: 45605 | F42: 45607 | G42: A REYES | H42: 48 | I42: CHEROKEE | J42: Laminitis crónica casco derecho delantero/Subepiglottic fold granuloma. | K42: Otras / No especificada | L42: 0 | M42: No clasificado | N42: Si
A43: 2024 | B43: 30/DICIEMBRE/2024 | C43: 30 | D43: DICIEMBRE | E43: 45654 | F43: 45656 | G43: E.R.V. ENTERPRISES | H43: 48 | I43: SABROSON | J43: Fractura rodilla izquierda | K43: Fractura ósea | L43: Rodilla / Carpal | M43: Fatal injury | N43: Si
A44: 2024 | B44: 31/DICIEMBRE/2024 | C44: 31 | D44: DICIEMBRE | E44: 45655 | F44: 45657 | G44: RAMZ | H44: 48 | I44: SOY AUTENTICO | J44: Fractura de ambas caños delanteras. (Referido PRHOA) | K44: Fractura ósea | L44: No especificado | M44: Fatal injury | N44: Si
A45: 2024 | B45: 12/MARZO/2024 | C45: 12 | D45: MARZO | E45: 45360 | F45: 45363 | G45: CUMBA'S | H45: 72 | I45: EL GRAN SEBAS | J45: Right Knee Slab Fracture | K45: Fractura ósea | L45: Slab | M45: Fatal injury | N45: Si
A46: 2024 | B46: 20/MARZO/2024 | C46: 20 | D46: MARZO | E46: 45368 | F46: 45371 | G46: VILLA REAL | H46: 72 | I46: PRISIONERA | J46: Fractura caña izquierda delantera. Dueño rehusó tratamiento. | K46: Fractura ósea | L46: Caña / Cannon bone | M46: Fatal injury | N46: Si
A47: 2024 | B47: 2/ABRIL/2024 | C47: 2 | D47: ABRIL | E47: 45381 | F47: 45384 | G47: RM | H47: 72 | I47: EL BRAVO | J47: Fractura rodilla derecha | K47: Fractura ósea | L47: Rodilla / Carpal | M47: Fatal injury | N47: Si
A48: 2024 | B48: 15/ABRIL/2024 | C48: 15 | D48: ABRIL | E48: 45394 | F48: 45397 | G48: RAMZ | H48: 72 | I48: EMPRENDEDOR | J48: Fractura rodilla derecha | K48: Fractura ósea | L48: Rodilla / Carpal | M48: Fatal injury | N48: Si
A49: 2024 | B49: 7/MAYO/2024 | C49: 7 | D49: MAYO | E49: 45416 | F49: 45419 | G49: AMBERT L | H49: 72 | I49: MISS RIOJA | J49: Artritis rodilla derecha | K49: Enfermedad degenerativa articular | L49: 0 | M49: Fatal injury | N49: Si
A50: 2024 | B50: 10/JULIO/2024 | C50: 10 | D50: JULIO | E50: 45480 | F50: 45483 | G50: NINIMEL | H50: 72 | I50: EVA LUNA | J50: Radiocarpal joint sepsis. LF peritendinous abscess. | K50: Otras / No especificada | L50: 0 | M50: Fatal injury | N50: Si
A51: 2024 | B51: 28/AGOSTO/2024 | C51: 28 | D51: AGOSTO | E51: 45529 | F51: 45532 | G51: ARELIZ S | H51: 72 | I51: NAHIALYHA | J51: Múltiples fracturas en la rodilla izquierda | K51: Fractura ósea | L51: Rodilla / Carpal | M51: Fatal injury | N51: Si
A52: 2024 | B52: 3/SEPTIEMBRE/2024 | C52: 3 | D52: SEPTIEMBRE | E52: 45535 | F52: 45538 | G52: RAFANIL | H52: 72 | I52: SUGAR MOM | J52: Fractura rodilla izquierda. | K52: Fractura ósea | L52: Rodilla / Carpal | M52: Fatal injury | N52: Si
A53: 2024 | B53: 5/SEPTIEMBRE/2024 | C53: 5 | D53: SEPTIEMBRE | E53: 45537 | F53: 45540 | G53: JOE BURGOS SPEED | H53: 72 | I53: RELOJ SUIZO | J53: Artritis severa menudillo izquierdo delantero con múltiples fracturas. | K53: Fractura ósea | L53: No especificado | M53: Fatal injury | N53: Si
A54: 2024 | B54: 23/SEPTIEMBRE/2024 | C54: 23 | D54: SEPTIEMBRE | E54: 45555 | F54: 45558 | G54: FLORIDA | H54: 72 | I54: FAVISUS REAL | J54: C/3 Slab fracture L Knee | K54: Fractura ósea | L54: Slab | M54: Fatal injury | N54: Si
A55: 2024 | B55: 4/NOVIEMBRE/2024 | C55: 4 | D55: NOVIEMBRE | E55: 45597 | F55: 45600 | G55: BROTHERS | H55: 72 | I55: CHICA BELLA | J55: LF fetlock severe arthritis. | K55: Enfermedad degenerativa articular | L55: 0 | M55: Fatal injury | N55: Si
A56: 2024 | B56: 12/NOVIEMBRE/2024 | C56: 12 | D56: NOVIEMBRE | E56: 45605 | F56: 45608 | G56: AQUINO | H56: 72 | I56: ADELYNN ROSE | J56: L C/3 Slab fracture. (Referido PRHOA) | K56: Fractura ósea | L56: Slab | M56: Fatal injury | N56: Si
A57: 2024 | B57: 11/DICIEMBRE/2024 | C57: 11 | D57: DICIEMBRE | E57: 45634 | F57: 45637 | G57: MATTA | H57: 72 | I57: REINA ESTER | J57: Fractura caña y tendón infectado | K57: Fractura ósea | L57: Caña / Cannon bone | M57: Fatal injury | N57: Si
A58: 2024 | B58: 27/MAYO/2024 | C58: 27 | D58: MAYO | E58: 45435 | F58: 45439 | G58: SECRET | H58: 96 | I58: CHILD MEMORIES | J58: Posible lesión de meniscos y/o ligamentos cruzados de stifle izquierdo. Laminitis/desprendimiento del casco derecho trasero. | K58: Lesión de ligamentos/tendones | L58: 0 | M58: No clasificado | N58: Si
A59: 2024 | B59: 3/JULIO/2024 | C59: 3 | D59: JULIO | E59: 45472 | F59: 45476 | G59: CENTRAL | H59: 96 | I59: BROOKS N BAND | J59: Artritis ambos menudillos. Fractura rodilla izquierda. | K59: Fractura ósea | L59: Rodilla / Carpal | M59: Fatal injury | N59: Si
A60: 2024 | B60: 29/JULIO/2024 | C60: 29 | D60: JULIO | E60: 45498 | F60: 45502 | G60: PAPA ÑAO | H60: 96 | I60: CHAVITOS | J60: Fractura rodilla derecha | K60: Fractura ósea | L60: Rodilla / Carpal | M60: Fatal injury | N60: Si
A61: 2024 | B61: 13/AGOSTO/2024 | C61: 13 | D61: AGOSTO | E61: 45513 | F61: 45517 | G61: BORIKEN | H61: 96 | I61: GUERRERA BORICUA | J61: Fractura rodilla izquierda | K61: Fractura ósea | L61: Rodilla / Carpal | M61: Fatal injury | N61: Si
A62: 2024 | B62: 6/SEPTIEMBRE/2024 | C62: 6 | D62: SEPTIEMBRE | E62: 45537 | F62: 45541 | G62: CASTRO | H62: 96 | I62: ESCARAMUZA | J62: Fractura + artritis R Radiocarpal/Dropped down LF Fetlock. | K62: Fractura ósea | L62: Fetlock | M62: Fatal injury | N62: Si
A63: 2024 | B63: 17/SEPTIEMBRE/2024 | C63: 17 | D63: SEPTIEMBRE | E63: 45548 | F63: 45552 | G63: V.G.O | H63: 96 | I63: AGUASBONENSE | J63: Múltiples fracturas rodillas izquierda. | K63: Fractura ósea | L63: Rodilla / Carpal | M63: Fatal injury | N63: Si
A64: 2024 | B64: 8/FEBRERO/2024 | C64: 8 | D64: FEBRERO | E64: 45325 | F64: 45330 | G64: CARMEN ANITA | H64: 120 | I64: INDIAN SENSE | J64: ARTRITIS SEVERA | K64: Enfermedad degenerativa articular | L64: 0 | M64: No fatal injury (chronic/medical) | N64: Si
A65: 2024 | B65: 13/MARZO/2024 | C65: 13 | D65: MARZO | E65: 45359 | F65: 45364 | G65: THIAGO & YASIL | H65: 120 | I65: EL TOPO | J65: Breakdown injury LF (menudillo izquierdo delantero) | K65: Otras / No especificada | L65: 0 | M65: No clasificado | N65: Si
A66: 2024 | B66: 2/AGOSTO/2024 | C66: 2 | D66: AGOSTO | E66: 45501 | F66: 45506 | G66: RMJA | H66: 120 | I66: JARHEEL'S JOY | J66: Multiple chips in both knees. (Referido PRHOA) | K66: Otras / No especificada | L66: 0 | M66: No clasificado | N66: Si
A67: 2024 | B67: 8/AGOSTO/2024 | C67: 8 | D67: AGOSTO | E67: 45507 | F67: 45512 | G67: VIOLETA | H67: 120 | I67: HEXAGON | J67: Fractura rodilla derecha (slab fracture of C3) (Referido Dr. Bozzo/Se fue a la cuadra) | K67: Fractura ósea | L67: Slab | M67: Fatal injury | N67: Si
A68: 2024 | B68: 3/OCTUBRE/2024 | C68: 3 | D68: OCTUBRE | E68: 45563 | F68: 45568 | G68: MOROVIS | H68: 120 | I68: STRIKE LIGHTNING | J68: RF breakdown injury | K68: Otras / No especificada | L68: 0 | M68: No clasificado | N68: Si
A69: 2024 | B69: 25/OCTUBRE/2024 | C69: 25 | D69: OCTUBRE | E69: 45585 | F69: 45590 | G69: TARRATS NACC | H69: 120 | I69: PROBADOR | J69: L C/3 Slab fracture | K69: Fractura ósea | L69: Slab | M69: Fatal injury | N69: Si
A70: 2024 | B70: 10/MAYO/2024 | C70: 10 | D70: MAYO | E70: 45416 | F70: 45422 | G70: FRANCHELY | H70: 144 | I70: PROTOTIPO | J70: Breakdown injury (base sesamoid fracture). | K70: Fractura ósea | L70: Sesamoideo | M70: Fatal injury | N70: Si
A71: 2024 | B71: 14/JUNIO/2024 | C71: 14 | D71: JUNIO | E71: 45451 | F71: 45457 | G71: LOUISIANA | H71: 144 | I71: MR. CHAMP | J71: Sesamoide medial derecho trasero partido/Artritis severa en corvejón derecho trasero | K71: Enfermedad degenerativa articular | L71: 0 | M71: Fatal injury | N71: Si
A72: 2024 | B72: 22/JUNIO/2024 | C72: 22 | D72: JUNIO | E72: 45459 | F72: 45465 | G72: POR MI PADRE | H72: 144 | I72: HARLAN FREE | J72: Fractura rodilla derecha | K72: Fractura ósea | L72: Rodilla / Carpal | M72: Fatal injury | N72: Si
A73: 2024 | B73: 13/ENERO/2024 | C73: 13 | D73: ENERO | E73: 45296 | F73: 45304 | G73: VILLA REAL | H73: 192 | I73: ORGULLOSO | J73: FRACTURA AMBAS RODILLAS | K73: Fractura ósea | L73: Rodilla / Carpal | M73: Fatal injury | N73: Si
A74: 2024 | B74: 26/JULIO/2024 | C74: 26 | D74: JULIO | E74: 45491 | F74: 45499 | G74: JGR | H74: 192 | I74: SUPERDOTADO | J74: Fractura sesamoide izquierdo delantero. | K74: Fractura ósea | L74: Sesamoideo | M74: Fatal injury | N74: Si
A75: 2024 | B75: 23/DICIEMBRE/2024 | C75: 23 | D75: DICIEMBRE | E75: 45641 | F75: 45649 | G75: E RAMOS | H75: 192 | I75: JUSTICE JEWELL | J75: Fractura caña derecha delantera | K75: Fractura ósea | L75: Caña / Cannon bone | M75: Fatal injury | N75: Si
A76: 2024 | B76: 10/JUNIO/2024 | C76: 10 | D76: JUNIO | E76: 45444 | F76: 45453 | G76: ERA RACING | H76: 216 | I76: LA CHICA DE LA FINCA | J76: R Knee huge fragment radiocarpal bone. Cannot run. Referido PRHOA. | K76: Otras / No especificada | L76: 0 | M76: Fatal injury | N76: Si
A77: 2024 | B77: 17/JUNIO/2024 | C77: 17 | D77: JUNIO | E77: 45451 | F77: 45460 | G77: COMERIO | H77: 216 | I77: PICU SPEED | J77: Fractura rodilla derecha. | K77: Fractura ósea | L77: Rodilla / Carpal | M77: Fatal injury | N77: Si
A78: 2024 | B78: 7/MAYO/2024 | C78: 7 | D78: MAYO | E78: 45409 | F78: 45419 | G78: MATTA | H78: 240 | I78: DREAM LEAPER | J78: Fractura ambas cañas delanteras | K78: Fractura ósea | L78: Caña / Cannon bone | M78: Fatal injury | N78: Si
A79: 2024 | B79: 15/JULIO/2024 | C79: 15 | D79: JULIO | E79: 45478 | F79: 45488 | G79: ERV ENTERPRISES | H79: 240 | I79: MI ABUELA ZORY | J79: Partial slab fracture R Knee. Dueño no quiso operar. Referido PRHOA | K79: Fractura ósea | L79: Slab | M79: Fatal injury | N79: Si
A80: 2024 | B80: 2/ENERO/2024 | C80: 2 | D80: ENERO | E80: 45282 | F80: 45293 | G80: GARCIA | H80: 264 | I80: LA PATRONA G | K80: 0 | L80: 0 | M80: 0 | N80: Si
A81: 2024 | B81: 7/FEBRERO/2024 | C81: 7 | D81: FEBRERO | E81: 45318 | F81: 45329 | G81: YORAM | H81: 264 | I81: MINERA | J81: ARTRITIS SEVERA DERECHO DELANTERO | K81: Enfermedad degenerativa articular | L81: 0 | M81: No fatal injury (chronic/medical) | N81: Si
A82: 2024 | B82: 13/FEBRERO/2024 | C82: 13 | D82: FEBRERO | E82: 45324 | F82: 45335 | G82: DIVINO NINO | H82: 264 | I82: EL MAPA | J82: TENDON BREAKDOWN RF LEG | K82: Lesión de ligamentos/tendones | L82: 0 | M82: No clasificado | N82: Si
A83: 2024 | B83: 11/JULIO/2024 | C83: 11 | D83: JULIO | E83: 45473 | F83: 45484 | G83: FANTASTIC 4 | H83: 264 | I83: EMMA LUNA S | J83: Polysinovitis/Laminitis. Referido PRHOA. | K83: Otras / No especificada | L83: 0 | M83: No clasificado | N83: Si
A84: 2024 | B84: 10/SEPTIEMBRE/2024 | C84: 10 | D84: SEPTIEMBRE | E84: 45534 | F84: 45545 | G84: GUILLERMO RODRIGUEZ | H84: 264 | I84: PICK ONE REMI | J84: Artritis en ambos menudillos delanteros. | K84: Enfermedad degenerativa articular | L84: 0 | M84: No fatal injury (chronic/medical) | N84: Si
A85: 2024 | B85: 18/SEPTIEMBRE/2024 | C85: 18 | D85: SEPTIEMBRE | E85: 45542 | F85: 45553 | G85: SONATA | H85: 264 | I85: CHARGE ACCOUNT | J85: Cólico (thromboembolic cecum) | K85: Otras / No especificada | L85: 0 | M85: No clasificado | N85: Si
A86: 2024 | B86: 21/OCTUBRE/2024 | C86: 21 | D86: OCTUBRE | E86: 45575 | F86: 45586 | G86: AM | H86: 264 | I86: DIVING NINA | J86: Fractura catastrófica caña derecha delantera. | K86: Fractura ósea | L86: Caña / Cannon bone | M86: Fatal injury | N86: Si
A87: 2024 | B87: 8/MARZO/2024 | C87: 8 | D87: MARZO | E87: 45347 | F87: 45359 | G87: LOS LLANOS | H87: 288 | I87: ADVERSIDAD | J87: Degloving injury RH cannon bone. | K87: Otras / No especificada | L87: 0 | M87: Fatal injury | N87: Si
A88: 2024 | B88: 29/MAYO/2024 | C88: 29 | D88: MAYO | E88: 45429 | F88: 45441 | G88: MADECO | H88: 288 | I88: MADECO VALUE | J88: Referido Drs PRHOA. Right front fracture of C3. | K88: Fractura ósea | L88: No especificado | M88: Fatal injury | N88: Si
A89: 2024 | B89: 31/JULIO/2024 | C89: 31 | D89: JULIO | E89: 45492 | F89: 45504 | G89: ADORNO | H89: 288 | I89: PHILIP SNOW | J89: LH medial sesamoid fracture. | K89: Fractura ósea | L89: Sesamoideo | M89: Fatal injury | N89: Si
A90: 2024 | B90: 5/SEPTIEMBRE/2024 | C90: 5 | D90: SEPTIEMBRE | E90: 45528 | F90: 45540 | G90: CHAD | H90: 288 | I90: PLATO | J90: Artritis severa en ambos menudillos delanteros. | K90: Enfermedad degenerativa articular | L90: 0 | M90: No fatal injury (chronic/medical) | N90: Si
A91: 2024 | B91: 31/AGOSTO/2024 | C91: 31 | D91: AGOSTO | E91: 45522 | F91: 45535 | G91: TARRATS NACC | H91: 312 | I91: AZONDRA | J91: Trauma en la cabeza, signos neurológicos. | K91: Otras / No especificada | L91: 0 | M91: No clasificado | N91: Si
A92: 2024 | B92: 5/ENERO/2024 | C92: 5 | D92: ENERO | E92: 45282 | F92: 45296 | G92: MARQUEZ | H92: 336 | I92: PEQUENO ADRIAN | J92: FRACTURA DE LA CANA IZQUIERDA DELANTERA | K92: Fractura ósea | L92: Caña / Cannon bone | M92: Fatal injury | N92: Si
A93: 2024 | B93: 28/MARZO/2024 | C93: 28 | D93: MARZO | E93: 45365 | F93: 45379 | G93: UP | H93: 336 | I93: HOLIS BRENDIS | J93: Fractura caña izquierda delantera. | K93: Fractura ósea | L93: Caña / Cannon bone | M93: Fatal injury | N93: Si
A94: 2024 | B94: 27/SEPTIEMBRE/2024 | C94: 27 | D94: SEPTIEMBRE | E94: 45548 | F94: 45562 | G94: LA 010 | H94: 336 | I94: VINCENZA M | J94: LF Knee C/3 fracture with multiple big fragments both joints. Can't train. (Referido PRHOA) | K94: Fractura ósea | L94: No especificado | M94: Fatal injury | N94: Si
A95: 2024 | B95: 9/MARZO/2024 | C95: 9 | D95: MARZO | E95: 45345 | F95: 45360 | G95: JACKSON | H95: 360 | I95: JOHNNY ON THE SPOT | J95: Fractura catastrófica caña derecha delantera. | K95: Fractura ósea | L95: Caña / Cannon bone | M95: Fatal injury | N95: Si
A96: 2024 | B96: 17/SEPTIEMBRE/2024 | C96: 17 | D96: SEPTIEMBRE | E96: 45537 | F96: 45552 | G96: ALAMO | H96: 360 | I96: ANULADA | J96: L C/3 Slab fracture. | K96: Fractura ósea | L96: Slab | M96: Fatal injury | N96: Si
A97: 2024 | B97: 23/ABRIL/2024 | C97: 23 | D97: ABRIL | E97: 45389 | F97: 45405 | G97: CRUZ FAMILY | H97: 384 | I97: POKER COCO | J97: Chronic flexor tendinitis L front/R Carpal Fracture | K97: Fractura ósea | L97: Rodilla / Carpal | M97: Fatal injury | N97: Si
A98: 2024 | B98: 14/DICIEMBRE/2024 | C98: 14 | D98: DICIEMBRE | E98: 45624 | F98: 45640 | G98: GUILLERMO BERRIOS | H98: 384 | I98: RUN FOR FREEDOM | J98: Severe chronic tendonitis (Referido PRHOA) | K98: Lesión de ligamentos/tendones | L98: 0 | M98: No fatal injury (chronic/medical) | N98: Si
A99: 2024 | B99: 1/MAYO/2024 | C99: 1 | D99: MAYO | E99: 45396 | F99: 45413 | G99: LA CAMPIÑA | H99: 408 | I99: RAIZ | J99: Fractura del húmero derecho. Accidente en la pista. | K99: Fractura ósea | L99: No especificado | M99: Fatal injury | N99: Si
A100: 2024 | B100: 6/MAYO/2024 | C100: 6 | D100: MAYO | E100: 45401 | F100: 45418 | G100: GCA | H100: 408 | I100: DULCE MELODIA | J100: Laminitis casco derecho/ Fractura rodilla derecha. | K100: Fractura ósea | L100: Rodilla / Carpal | M100: Fatal injury | N100: Si
...

Sheet 2026 data
A1: FECHA | B1: día | C1: Mes | D1: Last Race Date (desde Equibase) | E1: Death Date | F1: ESTABLO | G1: Horas transcurridas | H1: CABALLO | I1: RAZON | J1: Categoría | K1: Tipo de fractura | L1: Fatal injury | M1: Registrado/Compitió? | N1: MICROCHIP
A2: 2-ENERO-2026 | B2: =LEFT(A2,FIND("-",A2)-1) -> 2 | C2: =MID(A2,FIND("-",A2)+1,FIND("-",A2,FIND("-",A2)+1)-FIND("-",A2)-1) -> ENERO | D2: 46011 | E2: 46024 | F2: MA D CO | G2: =IFERROR(IF(D2=0,0,(E2-D2)*24),0) -> 312 | H2: C R NOMI | I2: Severe carpal disease. (Referido PRHOA) | J2: =_xlfn.XLOOKUP($I2,RazónMuerte!$A:$A,RazónMuerte!B:B,"",0) -> Enfermedad degenerativa articular | K2: =_xlfn.XLOOKUP($I2,RazónMuerte!$A:$A,RazónMuerte!C:C,"",0) -> 0 | L2: =_xlfn.XLOOKUP($I2,RazónMuerte!$A:$A,RazónMuerte!D:D,"",0) -> No fatal injury (chronic/medical) | N2: 981020037309179
A3: 2-ENERO-2026 | B3: =LEFT(A3,FIND("-",A3)-1) -> 2 | C3: =MID(A3,FIND("-",A3)+1,FIND("-",A3,FIND("-",A3)+1)-FIND("-",A3)-1) -> ENERO | D3: 0 | E3: 46024 | F3: WILLIE | G3: =IFERROR(IF(D3=0,0,(E3-D3)*24),0) -> 0 | H3: JARABE DE ZAPETE | I3: Fractura caña izquierda + múltiples fracturas rodilla derecha. (Referido PRHOA) | J3: =_xlfn.XLOOKUP($I3,RazónMuerte!$A:$A,RazónMuerte!B:B,"",0) -> Fractura ósea | K3: =_xlfn.XLOOKUP($I3,RazónMuerte!$A:$A,RazónMuerte!C:C,"",0) -> Caña / Cannon bone | L3: =_xlfn.XLOOKUP($I3,RazónMuerte!$A:$A,RazónMuerte!D:D,"",0) -> Fatal injury | N3: 981020031389160
A4: 2-ENERO-2026 | B4: =LEFT(A4,FIND("-",A4)-1) -> 2 | C4: =MID(A4,FIND("-",A4)+1,FIND("-",A4,FIND("-",A4)+1)-FIND("-",A4)-1) -> ENERO | D4: 46012 | E4: 46024 | F4: V.G.O. | G4: =IFERROR(IF(D4=0,0,(E4-D4)*24),0) -> 288 | H4: EXCLUSIVA | I4: RF Suspensory Desmitis. | J4: =_xlfn.XLOOKUP($I4,RazónMuerte!$A:$A,RazónMuerte!B:B,"",0) -> Lesión de ligamentos/tendones | K4: =_xlfn.XLOOKUP($I4,RazónMuerte!$A:$A,RazónMuerte!C:C,"",0) -> 0 | L4: =_xlfn.XLOOKUP($I4,RazónMuerte!$A:$A,RazónMuerte!D:D,"",0) -> No clasificado | N4: 981020049702663
A5: 3-ENERO-2026 | B5: =LEFT(A5,FIND("-",A5)-1) -> 3 | C5: =MID(A5,FIND("-",A5)+1,FIND("-",A5,FIND("-",A5)+1)-FIND("-",A5)-1) -> ENERO | D5: 46005 | E5: 46025 | F5: PRETTY H@RSE | G5: =IFERROR(IF(D5=0,0,(E5-D5)*24),0) -> 480 | H5: BLAZZING ARROW | I5: RF C-3 Slab fracture. (Referido PRHOA) | J5: =_xlfn.XLOOKUP($I5,RazónMuerte!$A:$A,RazónMuerte!B:B,"",0) -> Fractura ósea | K5: =_xlfn.XLOOKUP($I5,RazónMuerte!$A:$A,RazónMuerte!C:C,"",0) -> Slab | L5: =_xlfn.XLOOKUP($I5,RazónMuerte!$A:$A,RazónMuerte!D:D,"",0) -> Fatal injury | N5: 981020045084422
A6: 5-ENERO-2026 | B6: =LEFT(A6,FIND("-",A6)-1) -> 5 | C6: =MID(A6,FIND("-",A6)+1,FIND("-",A6,FIND("-",A6)+1)-FIND("-",A6)-1) -> ENERO | D6: 45988 | E6: 46027 | F6: G.R.C. | G6: =IFERROR(IF(D6=0,0,(E6-D6)*24),0) -> 936 | H6: YAHIR | I6: LF artritis severa. | J6: =_xlfn.XLOOKUP($I6,RazónMuerte!$A:$A,RazónMuerte!B:B,"",0) -> Enfermedad degenerativa articular | K6: =_xlfn.XLOOKUP($I6,RazónMuerte!$A:$A,RazónMuerte!C:C,"",0) -> 0 | L6: =_xlfn.XLOOKUP($I6,RazónMuerte!$A:$A,RazónMuerte!D:D,"",0) -> No fatal injury (chronic/medical) | N6: 981020037381563
A7: 12-ENERO-2026 | B7: =LEFT(A7,FIND("-",A7)-1) -> 12 | C7: =MID(A7,FIND("-",A7)+1,FIND("-",A7,FIND("-",A7)+1)-FIND("-",A7)-1) -> ENERO | D7: 45963 | E7: 46034 | F7: HG | G7: =IFERROR(IF(D7=0,0,(E7-D7)*24),0) -> 1704 | H7: GLASS BEACH | I7: Severe arthritis. Menudillos delanteros. | J7: =_xlfn.XLOOKUP($I7,RazónMuerte!$A:$A,RazónMuerte!B:B,"",0) -> Enfermedad degenerativa articular | K7: =_xlfn.XLOOKUP($I7,RazónMuerte!$A:$A,RazónMuerte!C:C,"",0) -> 0 | L7: =_xlfn.XLOOKUP($I7,RazónMuerte!$A:$A,RazónMuerte!D:D,"",0) -> No fatal injury (chronic/medical) | N7: 981020033767998
A8: 14-ENERO-2026 | B8: =LEFT(A8,FIND("-",A8)-1) -> 14 | C8: =MID(A8,FIND("-",A8)+1,FIND("-",A8,FIND("-",A8)+1)-FIND("-",A8)-1) -> ENERO | D8: 0 | E8: 46036 | F8: J CARTAGENA JR | G8: =IFERROR(IF(D8=0,0,(E8-D8)*24),0) -> 0 | H8: WICKED SEÑORITA | I8: Múltiples fracturas del cuarto metatarso derecho. | J8: =_xlfn.XLOOKUP($I8,RazónMuerte!$A:$A,RazónMuerte!B:B,"",0) -> Fractura ósea | K8: =_xlfn.XLOOKUP($I8,RazónMuerte!$A:$A,RazónMuerte!C:C,"",0) -> No especificado | L8: =_xlfn.XLOOKUP($I8,RazónMuerte!$A:$A,RazónMuerte!D:D,"",0) -> Fatal injury | N8: 981020031315742
A9: 26-ENERO-2026 | B9: =LEFT(A9,FIND("-",A9)-1) -> 26 | C9: =MID(A9,FIND("-",A9)+1,FIND("-",A9,FIND("-",A9)+1)-FIND("-",A9)-1) -> ENERO | D9: 46047 | E9: 46048 | F9: LOS LEE | G9: =IFERROR(IF(D9=0,0,(E9-D9)*24),0) -> 24 | H9: ROAD SLEW | I9: RF severe tendon injury. | J9: =_xlfn.XLOOKUP($I9,RazónMuerte!$A:$A,RazónMuerte!B:B,"",0) -> Lesión de ligamentos/tendones | K9: =_xlfn.XLOOKUP($I9,RazónMuerte!$A:$A,RazónMuerte!C:C,"",0) -> 0 | L9: =_xlfn.XLOOKUP($I9,RazónMuerte!$A:$A,RazónMuerte!D:D,"",0) -> No clasificado | N9: 981020031320894
A10: 26-ENERO-2026 | B10: =LEFT(A10,FIND("-",A10)-1) -> 26 | C10: =MID(A10,FIND("-",A10)+1,FIND("-",A10,FIND("-",A10)+1)-FIND("-",A10)-1) -> ENERO | D10: 46047 | E10: 46048 | F10: LOS LEE | G10: =IFERROR(IF(D10=0,0,(E10-D10)*24),0) -> 24 | H10: SOY DE LEE | I10: Fractura rodilla derecha. | J10: =_xlfn.XLOOKUP($I10,RazónMuerte!$A:$A,RazónMuerte!B:B,"",0) -> Fractura ósea | K10: =_xlfn.XLOOKUP($I10,RazónMuerte!$A:$A,RazónMuerte!C:C,"",0) -> Rodilla / Carpal | L10: =_xlfn.XLOOKUP($I10,RazónMuerte!$A:$A,RazónMuerte!D:D,"",0) -> Fatal injury | N10: 981020045097308
A11: 26-ENERO-2026 | B11: =LEFT(A11,FIND("-",A11)-1) -> 26 | C11: =MID(A11,FIND("-",A11)+1,FIND("-",A11,FIND("-",A11)+1)-FIND("-",A11)-1) -> ENERO | D11: 46047 | E11: 46048 | F11: HCDA BASILISA | G11: =IFERROR(IF(D11=0,0,(E11-D11)*24),0) -> 24 | H11: ADINERADA | I11: Severe DJD + chip fractures both knees. | J11: =_xlfn.XLOOKUP($I11,RazónMuerte!$A:$A,RazónMuerte!B:B,"",0) -> Fractura ósea | K11: =_xlfn.XLOOKUP($I11,RazónMuerte!$A:$A,RazónMuerte!C:C,"",0) -> Rodilla / Carpal | L11: =_xlfn.XLOOKUP($I11,RazónMuerte!$A:$A,RazónMuerte!D:D,"",0) -> No fatal injury (chronic/medical) | N11: 981020051070564
A12: 26-ENERO-2026 | B12: =LEFT(A12,FIND("-",A12)-1) -> 26 | C12: =MID(A12,FIND("-",A12)+1,FIND("-",A12,FIND("-",A12)+1)-FIND("-",A12)-1) -> ENERO | D12: 46039 | E12: 46048 | F12: CUADRA BORICUA (1,000) | G12: =IFERROR(IF(D12=0,0,(E12-D12)*24),0) -> 216 | H12: CEPEDA BORICUA | I12: Referido PRHOA. | J12: =_xlfn.XLOOKUP($I12,RazónMuerte!$A:$A,RazónMuerte!B:B,"",0) -> Otras / No especificada | K12: =_xlfn.XLOOKUP($I12,RazónMuerte!$A:$A,RazónMuerte!C:C,"",0) -> 0 | L12: =_xlfn.XLOOKUP($I12,RazónMuerte!$A:$A,RazónMuerte!D:D,"",0) -> No clasificado | N12: 981020045099495
A13: 28-ENERO-2026 | B13: =LEFT(A13,FIND("-",A13)-1) -> 28 | C13: =MID(A13,FIND("-",A13)+1,FIND("-",A13,FIND("-",A13)+1)-FIND("-",A13)-1) -> ENERO | D13: 46016 | E13: 46050 | F13: MATTA | G13: =IFERROR(IF(D13=0,0,(E13-D13)*24),0) -> 816 | H13: PERLA DEL CARIBE | I13: Cólico. | J13: =_xlfn.XLOOKUP($I13,RazónMuerte!$A:$A,RazónMuerte!B:B,"",0) -> Otras / No especificada | K13: =_xlfn.XLOOKUP($I13,RazónMuerte!$A:$A,RazónMuerte!C:C,"",0) -> 0 | L13: =_xlfn.XLOOKUP($I13,RazónMuerte!$A:$A,RazónMuerte!D:D,"",0) -> No clasificado | N13: 981020049657662
... A100: 27-ABRIL-2026 | B100: =LEFT(A100,FIND("-",A100)-1) -> 27 | C100: =MID(A100,FIND("-",A100)+1,FIND("-",A100,FIND("-",A100)+1)-FIND("-",A100)-1) -> ABRIL | D100: 45701 | E100: 46139 | F100: CARMEN ANITA | G100: =IFERROR(IF(D100=0,0,(E100-D100)*24),0) -> 10512 | H100: COSI MOMOSI | I100: Grade 4 lame. Severe bilateral front fetlock OA. Multiple old sesamoid fractures. (Referido PRHOA) | J100: =_xlfn.XLOOKUP($I100,RazónMuerte!$A:$A,RazónMuerte!B:B,"",0) -> Fractura ósea | K100: =_xlfn.XLOOKUP($I100,RazónMuerte!$A:$A,RazónMuerte!C:C,"",0) -> Sesamoideo | L100: =_xlfn.XLOOKUP($I100,RazónMuerte!$A:$A,RazónMuerte!D:D,"",0) -> No fatal injury (chronic/medical) | N100: 981020021496655
A101: 29-ABRIL-2026 | B101: =LEFT(A101,FIND("-",A101)-1) -> 29 | C101: =MID(A101,FIND("-",A101)+1,FIND("-",A101,FIND("-",A101)+1)-FIND("-",A101)-1) -> ABRIL | D101: 0 | E101: 46141 | F101: PRECISE STAR | G101: =IFERROR(IF(D101=0,0,(E101-D101)*24),0) -> 0 | H101: MISS UBIÑA 2026 | I101: Arresto cardiorrespiratorio postop. | J101: =_xlfn.XLOOKUP($I101,RazónMuerte!$A:$A,RazónMuerte!B:B,"",0) -> Otras / No especificada | K101: =_xlfn.XLOOKUP($I101,RazónMuerte!$A:$A,RazónMuerte!C:C,"",0) -> 0 | L101: =_xlfn.XLOOKUP($I101,RazónMuerte!$A:$A,RazónMuerte!D:D,"",0) -> No clasificado | N101: N/A
A102: 2-MAYO-2026 | B102: =LEFT(A102,FIND("-",A102)-1) -> 2 | C102: =MID(A102,FIND("-",A102)+1,FIND("-",A102,FIND("-",A102)+1)-FIND("-",A102)-1) -> MAYO | F102: E.R.V. ENTERPRISES | G102: =IFERROR(IF(D102=0,0,(E102-D102)*24),0) -> 0 | H102: JOAQUÍN ANDRÉS | I102: R carpus severe fragmentation RC joint. Loss of joint space. Hycoat epidemic. (Referido PRHOA) | J102: =_xlfn.XLOOKUP($I102,RazónMuerte!$A:$A,RazónMuerte!B:B,"",0) -> Enfermedad degenerativa articular | K102: =_xlfn.XLOOKUP($I102,RazónMuerte!$A:$A,RazónMuerte!C:C,"",0) -> 0 | L102: =_xlfn.XLOOKUP($I102,RazónMuerte!$A:$A,RazónMuerte!D:D,"",0) -> No fatal injury (chronic/medical) | N102: 981020045086428
A103: 4-MAYO-2026 | B103: =LEFT(A103,FIND("-",A103)-1) -> 4 | C103: =MID(A103,FIND("-",A103)+1,FIND("-",A103,FIND("-",A103)+1)-FIND("-",A103)-1) -> MAYO | F103: PONCE | G103: =IFERROR(IF(D103=0,0,(E103-D103)*24),0) -> 0 | H103: MI NIÑA PONCEÑA | I103: Bilateral carpal sepsis. Hycoat epidemic. (Referido PRHOA) | J103: =_xlfn.XLOOKUP($I103,RazónMuerte!$A:$A,RazónMuerte!B:B,"",0) -> Enfermedad degenerativa articular | K103: =_xlfn.XLOOKUP($I103,RazónMuerte!$A:$A,RazónMuerte!C:C,"",0) -> 0 | L103: =_xlfn.XLOOKUP($I103,RazónMuerte!$A:$A,RazónMuerte!D:D,"",0) -> No fatal injury (chronic/medical) | N103: 981020027293506
A104: 4-MAYO-2026 | B104: =LEFT(A104,FIND("-",A104)-1) -> 4 | C104: =MID(A104,FIND("-",A104)+1,FIND("-",A104,FIND("-",A104)+1)-FIND("-",A104)-1) -> MAYO | F104: CARMEN ANITA | G104: =IFERROR(IF(D104=0,0,(E104-D104)*24),0) -> 0 | H104: BIG FIG | I104: Artritis severa en ambos menudillos delanteros. | J104: =_xlfn.XLOOKUP($I104,RazónMuerte!$A:$A,RazónMuerte!B:B,"",0) -> Enfermedad degenerativa articular | K104: =_xlfn.XLOOKUP($I104,RazónMuerte!$A:$A,RazónMuerte!C:C,"",0) -> 0 | L104: =_xlfn.XLOOKUP($I104,RazónMuerte!$A:$A,RazónMuerte!D:D,"",0) -> No fatal injury (chronic/medical) | N104: 981020037819461
A105: 5-MAYO-2026 | B105: =LEFT(A105,FIND("-",A105)-1) -> 5 | C105: =MID(A105,FIND("-",A105)+1,FIND("-",A105,FIND("-",A105)+1)-FIND("-",A105)-1) -> MAYO | F105: SONATA | G105: =IFERROR(IF(D105=0,0,(E105-D105)*24),0) -> 0 | H105: GO BIG BLUE | I105: LF ankle decreased joint space. Hycoat epidemic. (Referido PRHOA) | J105: =_xlfn.XLOOKUP($I105,RazónMuerte!$A:$A,RazónMuerte!B:B,"",0) -> Enfermedad degenerativa articular | K105: =_xlfn.XLOOKUP($I105,RazónMuerte!$A:$A,RazónMuerte!C:C,"",0) -> 0 | L105: =_xlfn.XLOOKUP($I105,RazónMuerte!$A:$A,RazónMuerte!D:D,"",0) -> No fatal injury (chronic/medical) | N105: 981020049224478
A106: 5-MAYO-2026 | B106: =LEFT(A106,FIND("-",A106)-1) -> 5 | C106: =MID(A106,FIND("-",A106)+1,FIND("-",A106,FIND("-",A106)+1)-FIND("-",A106)-1) -> MAYO | F106: A REYES | G106: =IFERROR(IF(D106=0,0,(E106-D106)*24),0) -> 0 | H106: LA INTOCABLE | I106: Multiple carpal fractures (L Knee). Severe RF fetlock DJD. Hycoat epidemic. (Referido PRHOA) | J106: =_xlfn.XLOOKUP($I106,RazónMuerte!$A:$A,RazónMuerte!B:B,"",0) -> Fractura ósea | K106: =_xlfn.XLOOKUP($I106,RazónMuerte!$A:$A,RazónMuerte!C:C,"",0) -> Rodilla / Carpal | L106: =_xlfn.XLOOKUP($I106,RazónMuerte!$A:$A,RazónMuerte!D:D,"",0) -> No fatal injury (chronic/medical) | N106: 981020051548195
A107: 8-MAYO-2026 | B107: =LEFT(A107,FIND("-",A107)-1) -> 8 | C107: =MID(A107,FIND("-",A107)+1,FIND("-",A107,FIND("-",A107)+1)-FIND("-",A107)-1) -> MAYO | F107: NARDI & DELIA | G107: =IFERROR(IF(D107=0,0,(E107-D107)*24),0) -> 0 | H107: VERÓNICA D | I107: Hycoat epidemic. (Referido PRHOA) | J107: =_xlfn.XLOOKUP($I107,RazónMuerte!$A:$A,RazónMuerte!B:B,"",0) -> Otras / No especificada | K107: =_xlfn.XLOOKUP($I107,RazónMuerte!$A:$A,RazónMuerte!C:C,"",0) -> 0 | L107: =_xlfn.XLOOKUP($I107,RazónMuerte!$A:$A,RazónMuerte!D:D,"",0) -> No clasificado | N107: 981020049172661
A108: 11-MAYO-2026 | B108: =LEFT(A108,FIND("-",A108)-1) -> 11 | C108: =MID(A108,FIND("-",A108)+1,FIND("-",A108,FIND("-",A108)+1)-FIND("-",A108)-1) -> MAYO | F108: INGA | G108: =IFERROR(IF(D108=0,0,(E108-D108)*24),0) -> 0 | H108: CONSEJERO | I108: Septic arthritis of coffin joint from a solar abscess. (Referido PRHOA) | J108: =_xlfn.XLOOKUP($I108,RazónMuerte!$A:$A,RazónMuerte!B:B,"",0) -> Enfermedad degenerativa articular | K108: =_xlfn.XLOOKUP($I108,RazónMuerte!$A:$A,RazónMuerte!C:C,"",0) -> 0 | L108: =_xlfn.XLOOKUP($I108,RazónMuerte!$A:$A,RazónMuerte!D:D,"",0) -> No fatal injury (chronic/medical) | N108: 981020041936598
A109: 12-MAYO-2026 | B109: =LEFT(A109,FIND("-",A109)-1) -> 12 | C109: =MID(A109,FIND("-",A109)+1,FIND("-",A109,FIND("-",A109)+1)-FIND("-",A109)-1) -> MAYO | F109: MA D CO | G109: =IFERROR(IF(D109=0,0,(E109-D109)*24),0) -> 0 | H109: THE UPPERCUT LADY | I109: Bilateral multiples carpal chip fractures. Hycoat epidemic. (Referido PRHOA) | J109: =_xlfn.XLOOKUP($I109,RazónMuerte!$A:$A,RazónMuerte!B:B,"",0) -> Fractura ósea | K109: =_xlfn.XLOOKUP($I109,RazónMuerte!$A:$A,RazónMuerte!C:C,"",0) -> Rodilla / Carpal | L109: =_xlfn.XLOOKUP($I109,RazónMuerte!$A:$A,RazónMuerte!D:D,"",0) -> No fatal injury (chronic/medical) | N109: 981020051778716
A110: 15-MAYO-2026 | B110: =LEFT(A110,FIND("-",A110)-1) -> 15 | C110: =MID(A110,FIND("-",A110)+1,FIND("-",A110,FIND("-",A110)+1)-FIND("-",A110)-1) -> MAYO | F110: JF | G110: =IFERROR(IF(D110=0,0,(E110-D110)*24),0) -> 0 | H110: EL GOLDY | I110: Septic arthritis of left hind ankle. Hycoat epidemic. (Referido PRHOA) | J110: =_xlfn.XLOOKUP($I110,RazónMuerte!$A:$A,RazónMuerte!B:B,"",0) -> Enfermedad degenerativa articular | K110: =_xlfn.XLOOKUP($I110,RazónMuerte!$A:$A,RazónMuerte!C:C,"",0) -> 0 | L110: =_xlfn.XLOOKUP($I110,RazónMuerte!$A:$A,RazónMuerte!D:D,"",0) -> No fatal injury (chronic/medical) | N110: 981020051001963
A111: 16-MAYO-2026 | B111: =LEFT(A111,FIND("-",A111)-1) -> 16 | C111: =MID(A111,FIND("-",A111)+1,FIND("-",A111,FIND("-",A111)+1)-FIND("-",A111)-1) -> MAYO | F111: CARLOS OYOLA | G111: =IFERROR(IF(D111=0,0,(E111-D111)*24),0) -> 0 | H111: DAY OF LOVE | I111: Multiple fragmentation of right radiocarpal joint with loss of joint space. Possibly hycoat case. (Referido PRHOA) | J111: =_xlfn.XLOOKUP($I111,RazónMuerte!$A:$A,RazónMuerte!B:B,"",0) -> Enfermedad degenerativa articular | K111: =_xlfn.XLOOKUP($I111,RazónMuerte!$A:$A,RazónMuerte!C:C,"",0) -> 0 | L111: =_xlfn.XLOOKUP($I111,RazónMuerte!$A:$A,RazónMuerte!D:D,"",0) -> No fatal injury (chronic/medical) | N111: 985141005942105
A112: 16-MAYO-2026 | B112: =LEFT(A112,FIND("-",A112)-1) -> 16 | C112: =MID(A112,FIND("-",A112)+1,FIND("-",A112,FIND("-",A112)+1)-FIND("-",A112)-1) -> MAYO | F112: JE | G112: =IFERROR(IF(D112=0,0,(E112-D112)*24),0) -> 0 | H112: CERVECERA | I112: T Base sesamoid fracture. (Referido PRHOA) | J112: =_xlfn.XLOOKUP($I112,RazónMuerte!$A:$A,RazónMuerte!B:B,"",0) -> Fractura ósea | K112: =_xlfn.XLOOKUP($I112,RazónMuerte!$A:$A,RazónMuerte!C:C,"",0) -> Sesamoideo | L112: =_xlfn.XLOOKUP($I112,RazónMuerte!$A:$A,RazónMuerte!D:D,"",0) -> Fatal injury | N112: 981020045107491
A113: 18-MAYO-2026 | B113: =LEFT(A113,FIND("-",A113)-1) -> 18 | C113: =MID(A113,FIND("-",A113)+1,FIND("-",A113,FIND("-",A113)+1)-FIND("-",A113)-1) -> MAYO | F113: R RACING | G113: =IFERROR(IF(D113=0,0,(E113-D113)*24),0) -> 0 | H113: CHIHUAHUA | I113: Fractura sesamoide medial menudillo derecho delantero. | J113: =_xlfn.XLOOKUP($I113,RazónMuerte!$A:$A,RazónMuerte!B:B,"",0) -> Fractura ósea | K113: =_xlfn.XLOOKUP($I113,RazónMuerte!$A:$A,RazónMuerte!C:C,"",0) -> Sesamoideo | L113: =_xlfn.XLOOKUP($I113,RazónMuerte!$A:$A,RazónMuerte!D:D,"",0) -> Fatal injury | N113: 981020045139600
... A130: 15-JUNIO-2026 | B130: =LEFT(A130,FIND("-",A130)-1) -> 15 | C130: =MID(A130,FIND("-",A130)+1,FIND("-",A130,FIND("-",A130)+1)-FIND("-",A130)-1) -> JUNIO | F130: ARTCOM | G130: =IFERROR(IF(D130=0,0,(E130-D130)*24),0) -> 0 | H130: SKELLETOR | I130: Tendonitis severa (crónica) en ambas patas delanteras. | J130: =_xlfn.XLOOKUP($I130,RazónMuerte!$A:$A,RazónMuerte!B:B,"",0) -> Lesión de ligamentos/tendones | K130: =_xlfn.XLOOKUP($I130,RazónMuerte!$A:$A,RazónMuerte!C:C,"",0) -> 0 | L130: =_xlfn.XLOOKUP($I130,RazónMuerte!$A:$A,RazónMuerte!D:D,"",0) -> No clasificado | N130: 933000220012971

Sheet Sheet3
A1: RAZON
A2: END STAGE ARTHRITIS RF FETLOCK
A3: FRACTURA RODILLA IZQUIERDA
A4: CONDYLAR FRACTURE
A5: SEVERE DJD BOTH ANKLES / SEVERE LIGAMENT INJURY WITH BROKEN SPLINT BONES
A6: FRACTURA DE LA CANA IZQUIERDA DELANTERA
A7: COMMINUTED SLAB FRACTURE OF RIGHT CIII
A8: SEPTIC JOINT RIGHT INTERCARPAL
A9: LAMINITIS
A10: COLICO
A11: TENDONITIS SEVERA IZQUIERDA DELANTERA
A12: FRACTURA AMBAS RODILLAS
... A443: Chronic diarrea for 5 weeks duration. R hind limb cellulitis. (Referido PRHOA)

Sheet RazónMuerte
A1: Razón de muerte | B1: Categoría | C1: Tipo de fractura | D1: Fatal injury
A2: END STAGE ARTHRITIS RF FETLOCK | B2: Enfermedad degenerativa articular | D2: Fatal injury
A3: FRACTURA RODILLA IZQUIERDA | B3: Fractura ósea | C3: Rodilla / Carpal | D3: Fatal injury
A4: CONDYLAR FRACTURE | B4: Fractura ósea | C4: Condylar | D4: Fatal injury
A5: SEVERE DJD BOTH ANKLES / SEVERE LIGAMENT INJURY WITH BROKEN SPLINT BONES | B5: Enfermedad degenerativa articular | D5: No fatal injury (chronic/medical)
A6: FRACTURA DE LA CANA IZQUIERDA DELANTERA | B6: Fractura ósea | C6: Caña / Cannon bone | D6: Fatal injury
A7: COMMINUTED SLAB FRACTURE OF RIGHT CIII | B7: Fractura ósea | C7: Slab | D7: Fatal injury
A8: SEPTIC JOINT RIGHT INTERCARPAL | B8: Otras / No especificada | D8: Fatal injury
A9: LAMINITIS | B9: Otras / No especificada | D9: No clasificado
A10: COLICO | B10: Otras / No especificada | D10: No clasificado
A11: TENDONITIS SEVERA IZQUIERDA DELANTERA | B11: Lesión de ligamentos/tendones | D11: No clasificado
A12: FRACTURA AMBAS RODILLAS | B12: Fractura ósea | C12: Rodilla / Carpal | D12: Fatal injury
A13: FRACTURA HOMBRO IZQUIERDO | B13: Fractura ósea | C13: No especificado | D13: Fatal injury
A14: FRACTURA RODILLA DERECHA | B14: Fractura ósea | C14: Rodilla / Carpal | D14: Fatal injury
A15: FETLOCK BREAKDOWN INJURY BOTH HIND LEGS. | B15: Otras / No especificada | D15: Fatal injury
A16: Fractura rodilla derecha | B16: Fractura ósea | C16: Rodilla / Carpal | D16: Fatal injury
A17: Artritis severa menudillo izquierdo delantero | B17: Enfermedad degenerativa articular | D17: No fatal injury (chronic/medical)
A18: Colico | B18: Otras / No especificada | D18: No clasificado
A19: Artritis septica (menudillo derecho delantero) | B19: Enfermedad degenerativa articular | D19: No fatal injury (chronic/medical)
A20: Right front ankle fracture sesamoid. Laminitis of both hands can't walk or train. | B20: Fractura ósea | C20: Sesamoideo | D20: Fatal injury
A21: Fractura rodilla derecha | B21: Fractura ósea | C21: Rodilla / Carpal | D21: Fatal injury
A22: Laminitis cronica. | B22: Otras / No especificada | D22: No clasificado
A23: Fractura Húmero | B23: Fractura ósea | C23: No especificado | D23: Fatal injury
A24: HERIDA PARTE POSTERIOR DEL MENUDILLO, CUARTILLA IZQUIERDA DELANTERA INCLUYENDO LA VAINA DEL TENDON | B24: Lesión de ligamentos/tendones | D24: No clasificado
A25: ARTRITIS SEVERA EN MENUDILLO DELANTERO. | B25: Enfermedad degenerativa articular | D25: No fatal injury (chronic/medical)
A26: COLICO & POOR BODY CONDITION. | B26: Otras / No especificada | D26: No clasificado
A27: ARTRITIS SEVERA DERECHO DELANTERO | B27: Enfermedad degenerativa articular | D27: No fatal injury (chronic/medical)
A28: ARTRITIS SEVERA | B28: Enfermedad degenerativa articular | D28: No fatal injury (chronic/medical)
A29: Artritis severa menudillo izquierdo delantero | B29: Enfermedad degenerativa articular | D29: No fatal injury (chronic/medical)
A30: FRACTURA AMBAS RODILLAS | B30: Fractura ósea | C30: Rodilla / Carpal | D30: Fatal injury
A31: ARTRITIS SEVERA RODILLA IZQUIERDA | B31: Enfermedad degenerativa articular | D31: Fatal injury
A32: TENDON BREAKDOWN RF LEG | B32: Lesión de ligamentos/tendones | D32: No clasificado
A33: FRACTURA SESAMOIDE PATA DERECHA DELANTERA | B33: Fractura ósea | C33: Sesamoideo | D33: Fatal injury
A34: FRACTURA AMBAS RODILLAS | B34: Fractura ósea | C34: Rodilla / Carpal | D34: Fatal injury
A35: Artritis severa rodilla derecha | B35: Enfermedad degenerativa articular | D35: Fatal injury
A36: Fractura sesamoide derecho delantero | B36: Fractura ósea | C36: Sesamoideo | D36: Fatal injury
A37: Aggressive eye cancer | B37: Otras / No especificada | D37: No clasificado
A38: Tendón desgarrado pata izquierda trasera/ Laminitis pata derecha trasera | B38: Otras / No especificada | D38: No clasificado
A39: Fractura rodillas | B39: Fractura ósea | C39: Rodilla / Carpal | D39: Fatal injury
A40: Fractura rodillas | B40: Fractura ósea | C40: Rodilla / Carpal | D40: Fatal injury
A41: Referido Drs. PRHOA. LF Front severe DID Knee and fetlock smooth rest. Cannot train. | B41: Otras / No especificada | D41: Fatal injury
A42: Cólico | B42: Otras / No especificada | D42: No clasificado
A43: Referido Drs. PRHOA. R Carpus. | B43: Otras / No especificada | D43: No clasificado
A44: Referido Drs. PRHOA. RF ankle fracture. Big piece of sesamoid with ligament. | B44: Fractura ósea | C44: Sesamoideo | D44: Fatal injury
A45: Referido Drs. PRHOA. Coyuntura infectada rodilla izquierda. | B45: Otras / No especificada | D45: Fatal injury
A46: Fractura rodilla derecha. | B46: Fractura ósea | C46: Rodilla / Carpal | D46: Fatal injury
A47: Referido Drs. PRHOA. Fractura sesamoide izquierdo delantero. | B47: Fractura ósea | C47: Sesamoideo | D47: Fatal injury
A48: Referido Drs. PRHOA. Cólico. | B48: Otras / No especificada | D48: No clasificado
A49: Tendinitis crónica. | B49: Otras / No especificada | D49: No clasificado
A50: Degloving injury RH cannon bone. | B50: Otras / No especificada | D50: Fatal injury
A51: Fractura catastrófica caña derecha delantera. | B51: Fractura ósea | C51: Caña / Cannon bone | D51: Fatal injury
A52: Fractura hombro izquierdo | B52: Fractura ósea | C52: No especificado | D52: Fatal injury
A53: Head Trauma | B53: Otras / No especificada | D53: No clasificado
A54: Severe Laminitis | B54: Otras / No especificada | D54: No clasificado
A55: Right Knee Slab Fracture | B55: Fractura ósea | C55: Slab | D55: Fatal injury
A56: Breakdown injury LF (menudillo izquierdo delantero) | B56: Otras / No especificada | D56: No clasificado
A57: Dx Drs. PRHOA. Severe laminitis. | B57: Otras / No especificada | D57: No clasificado
A58: Cólico | B58: Otras / No especificada | D58: No clasificado
A59: Fractura caña izquierda delantera. Dueño rehusó tratamiento. | B59: Fractura ósea | C59: Caña / Cannon bone | D59: Fatal injury
A60: Fractura rodilla izquierda. | B60: Fractura ósea | C60: Rodilla / Carpal | D60: Fatal injury
A61: Fractura caña izquierda delantera. | B61: Fractura ósea | C61: Caña / Cannon bone | D61: Fatal injury
A62: Fractura rodilla derecha (slab fracture of C3) | B62: Fractura ósea | C62: Slab | D62: Fatal injury
A63: Fractura sesaomide y artritis menudillo derecho delantero | B63: Fractura ósea | C63: No especificado | D63: Fatal injury
A64: Cólico severo (referido por Dr. Armand PRHOA) | B64: Otras / No especificada | D64: No clasificado
A65: Fractura y artritis de rodilla izquierda | B65: Fractura ósea | C65: Rodilla / Carpal | D65: Fatal injury
A66: Fractura rodilla derecha | B66: Fractura ósea | C66: Rodilla / Carpal | D66: Fatal injury
A67: Cólico (Nephrosplenic entrapment/Referido Dr. Armand PRHOA) | B67: Otras / No especificada | D67: No clasificado
A68: Múltiples fracturas rodillas + menudillos delanteros | B68: Fractura ósea | C68: Rodilla / Carpal | D68: Fatal injury
A69: RF Breakdown Injury. (PRHOA) | B69: Otras / No especificada | D69: No clasificado
A70: Fractura rodilla derecha | B70: Fractura ósea | C70: Rodilla / Carpal | D70: Fatal injury
A71: Fractura caña izquierda delantera | B71: Fractura ósea | C71: Caña / Cannon bone | D71: Fatal injury
A72: Chronic tendinitis (both front limbs) | B72: Otras / No especificada | D72: No fatal injury (chronic/medical)
A73: Chronic flexor tendinitis L front/R Carpal Fracture | B73: Fractura ósea | C73: Rodilla / Carpal | D73: Fatal injury
A74: Fractura sesamoide izquierdo delantero y rodilla derecha | B74: Fractura ósea | C74: Rodilla / Carpal | D74: Fatal injury
A75: Fractura sesamoide ambas patas delanteras durante la 3ra carrera. PRHOA. | B75: Fractura ósea | C75: Sesamoideo | D75: Fatal injury
A76: Fractura rodilla derecha | B76: Fractura ósea | C76: Rodilla / Carpal | D76: Fatal injury
A77: Pleuroneumonía. Referido Drs PRHOA. | B77: Otras / No especificada | D77: No clasificado
A78: Fractura del húmero derecho. Accidente en la pista. | B78: Fractura ósea | C78: No especificado | D78: Fatal injury
A79: Fractura y artritis rodilla derecha derecha. Referido Drs PRHOA. | B79: Fractura ósea | C79: Rodilla / Carpal | D79: Fatal injury
A80: Tendinitis crónica en ambas patas delanteras. | B80: Otras / No especificada | D80: No clasificado
A81: Breakdown injury LF leg with tissue necrosy. Referido Dr. García Blanco. | B81: Otras / No especificada | D81: No clasificado
A82: LF dorsal cortical MCIII fracture. Referido Drs. PRHOA. | B82: Fractura ósea | C82: No especificado | D82: Fatal injury
A83: Laminitis casco derecho/ Fractura rodilla derecha. | B83: Fractura ósea | C83: Rodilla / Carpal | D83: Fatal injury
A84: Artritis y coyuntura séptica (corvejón derecho) | B84: Enfermedad degenerativa articular | D84: No fatal injury (chronic/medical)
A85: Fractura ambas cañas delanteras | B85: Fractura ósea | C85: Caña / Cannon bone | D85: Fatal injury
A86: Artritis rodilla derecha | B86: Enfermedad degenerativa articular | D86: Fatal injury
A87: Breakdown injury (base sesamoid fracture). | B87: Fractura ósea | C87: Sesamoideo | D87: Fatal injury
A88: Fractura sesamoide pata izquierda delantera. | B88: Fractura ósea | C88: Sesamoideo | D88: Fatal injury
A89: Fractura rodilla derecha | B89: Fractura ósea | C89: Rodilla / Carpal | D89: Fatal injury
A90: Múltiples fracturas; DJD severo después de cirugía. No pudo terminar carrera. Referido Drs. PRHOA. | B90: Fractura ósea | C90: No especificado | D90: Fatal injury
A91: Breakdown injury LF + bilateral sesamoid fractures. | B91: Fractura ósea | C91: Sesamoideo | D91: Fatal injury
A92: Fractura rodilla derecha | B92: Fractura ósea | C92: Rodilla / Carpal | D92: Fatal injury
A93: Multiple chip fractures intercarpal joint, severe DJD, 4/5 lameness, infected accesory carpal area. Referido Drs. PRHOA. | B93: Fractura ósea | C93: Rodilla / Carpal | D93: Fatal injury
A94: Sesamoide medial derecho delantero | B94: Otras / No especificada | D94: Fatal injury
A95: Fractura rodilla derecha | B95: Fractura ósea | C95: Rodilla / Carpal | D95: Fatal injury
A96: Laminitis (all four limbs) | B96: Otras / No especificada | D96: No clasificado
A97: Rodilla derecha + caña derecha fracturada. Didn't finish race (2nd). PRHOA. | B97: Fractura ósea | C97: Caña / Cannon bone | D97: Fatal injury
A98: RF Chronic tendinitis | B98: Otras / No especificada | D98: No fatal injury (chronic/medical)
A99: Severe laminitis both front feet. Referido Drs. PRHOA. | B99: Otras / No especificada | D99: No clasificado
A100: Referido Drs. PRHOA. RF SDF Tendonitis, RF Fetlock hyperextension. | B100: Lesión de ligamentos/tendones | D100: Fatal injury
...

Sheet Meses
A1: Mes | B1: Día
A2: ENERO | B2: 1
A3: FEBRERO | B3: 2
A4: MARZO | B4: 3
A5: ABRIL | B5: 4
A6: MAYO | B6: 5
A7: JUNIO | B7: 6
A8: JULIO | B8: 7
A9: AGOSTO | B9: 8
A10: SEPTIEMBRE | B10: 9
A11: OCTUBRE | B11: 10
A12: NOVIEMBRE | B12: 11
A13: DICIEMBRE | B13: 12
